Workbook

Sheet Master Overview
A1: Robin - Site Audit & Analysis | Master Sheet
A2: Priority list (revenue, markets, flags) as provided by the user; audit columns pull live from the Issue Tracker. Blue = typed inputs, black = formulas.
A4: # | B4: Ahrefs project | C4: D2C net rev TTM (€k) | D4: Brand total, all ch. (€k) | E4: Brand total note | F4: Focus markets | G4: Flag | H4: D2C share of brand | I4: Audit status | J4: Audit deliverables | K4: Issues logged | L4: Open issues | M4: High / Critical open | N4: Affected URLs / rows | O4: Worksheet tabs in this file | P4: Key finding
A5: 1 | B5: Open Goaaal USA | C5: 1661 | D5: 3036 | E5: both stores | F5: US | G5: Only 21 kw tracked | H5: =IF(AND(ISNUMBER(C5),ISNUMBER(D5),D5<>0),C5/D5,"-") -> 0.54710145 | I5: =IF(K5=0,"Not started",IF(L5=0,"Complete","Audit delivered")) -> Audit delivered | J5: Blog content sheet + GSC countries; Duplicate content report; Site audit doc (images only) | K5: =COUNTIF('Issue Tracker'!$B$5:$B$84,B5) -> 1 | L5: =K5-COUNTIFS('Issue Tracker'!$B$5:$B$84,B5,'Issue Tracker'!$J$5:$J$84,"Fixed")-COUNTIFS('Issue Tracker'!$B$5:$B$84,B5,'Issue Tracker'!$J$5:$J$84,"Already Fixed") -> 1 | M5: =COUNTIFS('Issue Tracker'!$B$5:$B$84,B5,'Issue Tracker'!$I$5:$I$84,"High",'Issue Tracker'!$J$5:$J$84,"<>Fixed",'Issue Tracker'!$J$5:$J$84,"<>Already Fixed")+COUNTIFS('Issue Tracker'!$B$5:$B$84,B5,'Issue Tracker'!$I$5:$I$84,"Critical",'Issue Tracker'!$J$5:$J$84,"<>Fixed",'Issue Tracker'!$J$5:$J$84,"<>Already Fixed") -> 1 | N5: =SUMIF('Issue Tracker'!$B$5:$B$84,B5,'Issue Tracker'!$G$5:$G$84) -> 3 | O5: OGU_Blog Pages, OGU_Countries, OGU_Filters | P5: Duplicate blog content vs opengoaaal.com already triggered a penalty; US clicks 4.3k vs 10.4k prior 6 mo
A6: 2 | B6: Bigbatbox (WildYard) | C6: 325 | D6: 1650 | F6: US 49, DE 7 | G6: Unverified | H6: =IF(AND(ISNUMBER(C6),ISNUMBER(D6),D6<>0),C6/D6,"-") -> 0.1969697 | I6: =IF(K6=0,"Not started",IF(L6=0,"Complete","Audit delivered")) -> Audit delivered | J6: Site audit workbook (16 tabs); Site audit doc; Issues doc (translation) | K6: =COUNTIF('Issue Tracker'!$B$5:$B$84,B6) -> 19 | L6: =K6-COUNTIFS('Issue Tracker'!$B$5:$B$84,B6,'Issue Tracker'!$J$5:$J$84,"Fixed")-COUNTIFS('Issue Tracker'!$B$5:$B$84,B6,'Issue Tracker'!$J$5:$J$84,"Already Fixed") -> 19 | M6: =COUNTIFS('Issue Tracker'!$B$5:$B$84,B6,'Issue Tracker'!$I$5:$I$84,"High",'Issue Tracker'!$J$5:$J$84,"<>Fixed",'Issue Tracker'!$J$5:$J$84,"<>Already Fixed")+COUNTIFS('Issue Tracker'!$B$5:$B$84,B6,'Issue Tracker'!$I$5:$I$84,"Critical",'Issue Tracker'!$J$5:$J$84,"<>Fixed",'Issue Tracker'!$J$5:$J$84,"<>Already Fixed") -> 10 | N6: =SUMIF('Issue Tracker'!$B$5:$B$84,B6,'Issue Tracker'!$G$5:$G$84) -> 4912 | O6: BBB_Master Checklist, BBB_Broken Links, BBB_Broken Internal Link, BBB_Pages Marked No Index, BBB_Not submitted to IndexNow, BBB_Page has links to broken pa, BBB_Redirecting URLs, BBB_Too Long Meta Title, BBB_Too Long Meta Description, BBB_Missing H1 Tag, BBB_Missing Meta Description, BBB_Multiple H1 Tag, BBB_Page and SERP titles do not, BBB_Twitter and Open Graph tags, BBB_Image file size too large, BBB_Images Missing ALT text | P6: Manual action for thin content; 170/761 pages not indexed; 'bat house' impressions down
A7: 3 | B7: Luonkos Finland (.fi) | C7: 323 | D7: 513 | E7: both stores | F7: FI | H7: =IF(AND(ISNUMBER(C7),ISNUMBER(D7),D7<>0),C7/D7,"-") -> 0.62962963 | I7: =IF(K7=0,"Not started",IF(L7=0,"Complete","Audit delivered")) -> Audit delivered | J7: Audit & Analysis doc; Merge 404 report; Draft audit (not final) | K7: =COUNTIF('Issue Tracker'!$B$5:$B$84,B7) -> 6 | L7: =K7-COUNTIFS('Issue Tracker'!$B$5:$B$84,B7,'Issue Tracker'!$J$5:$J$84,"Fixed")-COUNTIFS('Issue Tracker'!$B$5:$B$84,B7,'Issue Tracker'!$J$5:$J$84,"Already Fixed") -> 6 | M7: =COUNTIFS('Issue Tracker'!$B$5:$B$84,B7,'Issue Tracker'!$I$5:$I$84,"High",'Issue Tracker'!$J$5:$J$84,"<>Fixed",'Issue Tracker'!$J$5:$J$84,"<>Already Fixed")+COUNTIFS('Issue Tracker'!$B$5:$B$84,B7,'Issue Tracker'!$I$5:$I$84,"Critical",'Issue Tracker'!$J$5:$J$84,"<>Fixed",'Issue Tracker'!$J$5:$J$84,"<>Already Fixed") -> 4 | N7: =SUMIF('Issue Tracker'!$B$5:$B$84,B7,'Issue Tracker'!$G$5:$G$84) -> 0 | O7: - | P7: After .fi/.com merge, EN & SV URLs with traffic return 404 - redirect map needed
A8: 4 | B8: Senseball | C8: 119 | D8: 682 | F8: US 40, +UK/DE/FR/ES/IT | G8: Declining fast (H2 39k vs H1 79k) | H8: =IF(AND(ISNUMBER(C8),ISNUMBER(D8),D8<>0),C8/D8,"-") -> 0.1744868 | I8: =IF(K8=0,"Not started",IF(L8=0,"Complete","Audit delivered")) -> Not started | J8: No audit file in folder | K8: =COUNTIF('Issue Tracker'!$B$5:$B$84,B8) -> 0 | L8: =K8-COUNTIFS('Issue Tracker'!$B$5:$B$84,B8,'Issue Tracker'!$J$5:$J$84,"Fixed")-COUNTIFS('Issue Tracker'!$B$5:$B$84,B8,'Issue Tracker'!$J$5:$J$84,"Already Fixed") -> 0 | M8: =COUNTIFS('Issue Tracker'!$B$5:$B$84,B8,'Issue Tracker'!$I$5:$I$84,"High",'Issue Tracker'!$J$5:$J$84,"<>Fixed",'Issue Tracker'!$J$5:$J$84,"<>Already Fixed")+COUNTIFS('Issue Tracker'!$B$5:$B$84,B8,'Issue Tracker'!$I$5:$I$84,"Critical",'Issue Tracker'!$J$5:$J$84,"<>Fixed",'Issue Tracker'!$J$5:$J$84,"<>Already Fixed") -> 0 | N8: =SUMIF('Issue Tracker'!$B$5:$B$84,B8,'Issue Tracker'!$G$5:$G$84) -> 0 | O8: -
A9: 5 | B9: Indo | C9: 117 | D9: 1750 | F9: US, UK, FI, CA, AU, DE, PL, FR, DK, CZ | G9: Unverified; 10 markets on 86 kw = thin | H9: =IF(AND(ISNUMBER(C9),ISNUMBER(D9),D9<>0),C9/D9,"-") -> 0.066857143 | I9: =IF(K9=0,"Not started",IF(L9=0,"Complete","Audit delivered")) -> Not started | J9: No audit file in folder | K9: =COUNTIF('Issue Tracker'!$B$5:$B$84,B9) -> 0 | L9: =K9-COUNTIFS('Issue Tracker'!$B$5:$B$84,B9,'Issue Tracker'!$J$5:$J$84,"Fixed")-COUNTIFS('Issue Tracker'!$B$5:$B$84,B9,'Issue Tracker'!$J$5:$J$84,"Already Fixed") -> 0 | M9: =COUNTIFS('Issue Tracker'!$B$5:$B$84,B9,'Issue Tracker'!$I$5:$I$84,"High",'Issue Tracker'!$J$5:$J$84,"<>Fixed",'Issue Tracker'!$J$5:$J$84,"<>Already Fixed")+COUNTIFS('Issue Tracker'!$B$5:$B$84,B9,'Issue Tracker'!$I$5:$I$84,"Critical",'Issue Tracker'!$J$5:$J$84,"<>Fixed",'Issue Tracker'!$J$5:$J$84,"<>Already Fixed") -> 0 | N9: =SUMIF('Issue Tracker'!$B$5:$B$84,B9,'Issue Tracker'!$G$5:$G$84) -> 0 | O9: -
A10: 6 | B10: Opengoaaal UK-EU | C10: 91 | F10: UK 20, DE/FR/SE/IT/ES | G10: 70 kw for 5% of Open Goaaal D2C | H10: =IF(AND(ISNUMBER(C10),ISNUMBER(D10),D10<>0),C10/D10,"-") -> - | I10: =IF(K10=0,"Not started",IF(L10=0,"Complete","Audit delivered")) -> Audit delivered | J10: Duplicate content report (shared with USA) | K10: =COUNTIF('Issue Tracker'!$B$5:$B$84,B10) -> 1 | L10: =K10-COUNTIFS('Issue Tracker'!$B$5:$B$84,B10,'Issue Tracker'!$J$5:$J$84,"Fixed")-COUNTIFS('Issue Tracker'!$B$5:$B$84,B10,'Issue Tracker'!$J$5:$J$84,"Already Fixed") -> 1 | M10: =COUNTIFS('Issue Tracker'!$B$5:$B$84,B10,'Issue Tracker'!$I$5:$I$84,"High",'Issue Tracker'!$J$5:$J$84,"<>Fixed",'Issue Tracker'!$J$5:$J$84,"<>Already Fixed")+COUNTIFS('Issue Tracker'!$B$5:$B$84,B10,'Issue Tracker'!$I$5:$I$84,"Critical",'Issue Tracker'!$J$5:$J$84,"<>Fixed",'Issue Tracker'!$J$5:$J$84,"<>Already Fixed") -> 1 | N10: =SUMIF('Issue Tracker'!$B$5:$B$84,B10,'Issue Tracker'!$G$5:$G$84) -> 3 | O10: - | P10: Duplicate blog content shared with opengoaaalusa.com
A11: 7 | B11: Bodyotics | C11: 71 | D11: 1404 | F11: US, UK, DE, FI | H11: =IF(AND(ISNUMBER(C11),ISNUMBER(D11),D11<>0),C11/D11,"-") -> 0.050569801 | I11: =IF(K11=0,"Not started",IF(L11=0,"Complete","Audit delivered")) -> Audit delivered | J11: Analysis doc | K11: =COUNTIF('Issue Tracker'!$B$5:$B$84,B11) -> 2 | L11: =K11-COUNTIFS('Issue Tracker'!$B$5:$B$84,B11,'Issue Tracker'!$J$5:$J$84,"Fixed")-COUNTIFS('Issue Tracker'!$B$5:$B$84,B11,'Issue Tracker'!$J$5:$J$84,"Already Fixed") -> 2 | M11: =COUNTIFS('Issue Tracker'!$B$5:$B$84,B11,'Issue Tracker'!$I$5:$I$84,"High",'Issue Tracker'!$J$5:$J$84,"<>Fixed",'Issue Tracker'!$J$5:$J$84,"<>Already Fixed")+COUNTIFS('Issue Tracker'!$B$5:$B$84,B11,'Issue Tracker'!$I$5:$I$84,"Critical",'Issue Tracker'!$J$5:$J$84,"<>Fixed",'Issue Tracker'!$J$5:$J$84,"<>Already Fixed") -> 1 | N11: =SUMIF('Issue Tracker'!$B$5:$B$84,B11,'Issue Tracker'!$G$5:$G$84) -> 0 | O11: - | P11: Wrong language URLs ranking in DE / NL / FR
A12: 8 | B12: ANSWR US (3P) | C12: 60 | D12: 232 | F12: US | G12: 3P - keep out of 1P totals | H12: =IF(AND(ISNUMBER(C12),ISNUMBER(D12),D12<>0),C12/D12,"-") -> 0.25862069 | I12: =IF(K12=0,"Not started",IF(L12=0,"Complete","Audit delivered")) -> Not started | J12: No audit file in folder | K12: =COUNTIF('Issue Tracker'!$B$5:$B$84,B12) -> 0 | L12: =K12-COUNTIFS('Issue Tracker'!$B$5:$B$84,B12,'Issue Tracker'!$J$5:$J$84,"Fixed")-COUNTIFS('Issue Tracker'!$B$5:$B$84,B12,'Issue Tracker'!$J$5:$J$84,"Already Fixed") -> 0 | M12: =COUNTIFS('Issue Tracker'!$B$5:$B$84,B12,'Issue Tracker'!$I$5:$I$84,"High",'Issue Tracker'!$J$5:$J$84,"<>Fixed",'Issue Tracker'!$J$5:$J$84,"<>Already Fixed")+COUNTIFS('Issue Tracker'!$B$5:$B$84,B12,'Issue Tracker'!$I$5:$I$84,"Critical",'Issue Tracker'!$J$5:$J$84,"<>Fixed",'Issue Tracker'!$J$5:$J$84,"<>Already Fixed") -> 0 | N12: =SUMIF('Issue Tracker'!$B$5:$B$84,B12,'Issue Tracker'!$G$5:$G$84) -> 0 | O12: -
A13: 9 | B13: Angles90 | C13: 56 | D13: 352 | F13: US 40, DE 8 | H13: =IF(AND(ISNUMBER(C13),ISNUMBER(D13),D13<>0),C13/D13,"-") -> 0.15909091 | I13: =IF(K13=0,"Not started",IF(L13=0,"Complete","Audit delivered")) -> Not started | J13: No audit file in folder | K13: =COUNTIF('Issue Tracker'!$B$5:$B$84,B13) -> 0 | L13: =K13-COUNTIFS('Issue Tracker'!$B$5:$B$84,B13,'Issue Tracker'!$J$5:$J$84,"Fixed")-COUNTIFS('Issue Tracker'!$B$5:$B$84,B13,'Issue Tracker'!$J$5:$J$84,"Already Fixed") -> 0 | M13: =COUNTIFS('Issue Tracker'!$B$5:$B$84,B13,'Issue Tracker'!$I$5:$I$84,"High",'Issue Tracker'!$J$5:$J$84,"<>Fixed",'Issue Tracker'!$J$5:$J$84,"<>Already Fixed")+COUNTIFS('Issue Tracker'!$B$5:$B$84,B13,'Issue Tracker'!$I$5:$I$84,"Critical",'Issue Tracker'!$J$5:$J$84,"<>Fixed",'Issue Tracker'!$J$5:$J$84,"<>Already Fixed") -> 0 | N13: =SUMIF('Issue Tracker'!$B$5:$B$84,B13,'Issue Tracker'!$G$5:$G$84) -> 0 | O13: -
A14: 10 | B14: Happy Sinks | C14: 54 | D14: 668 | F14: US 50 | G14: Unverified | H14: =IF(AND(ISNUMBER(C14),ISNUMBER(D14),D14<>0),C14/D14,"-") -> 0.080838323 | I14: =IF(K14=0,"Not started",IF(L14=0,"Complete","Audit delivered")) -> Audit delivered | J14: URL report workbook (5 tabs); SEO audit doc | K14: =COUNTIF('Issue Tracker'!$B$5:$B$84,B14) -> 8 | L14: =K14-COUNTIFS('Issue Tracker'!$B$5:$B$84,B14,'Issue Tracker'!$J$5:$J$84,"Fixed")-COUNTIFS('Issue Tracker'!$B$5:$B$84,B14,'Issue Tracker'!$J$5:$J$84,"Already Fixed") -> 8 | M14: =COUNTIFS('Issue Tracker'!$B$5:$B$84,B14,'Issue Tracker'!$I$5:$I$84,"High",'Issue Tracker'!$J$5:$J$84,"<>Fixed",'Issue Tracker'!$J$5:$J$84,"<>Already Fixed")+COUNTIFS('Issue Tracker'!$B$5:$B$84,B14,'Issue Tracker'!$I$5:$I$84,"Critical",'Issue Tracker'!$J$5:$J$84,"<>Fixed",'Issue Tracker'!$J$5:$J$84,"<>Already Fixed") -> 2 | N14: =SUMIF('Issue Tracker'!$B$5:$B$84,B14,'Issue Tracker'!$G$5:$G$84) -> 1704 | O14: HS_Missing H1 Tag, HS_Multiple H1 Tag, HS_Too Long Meta Title, HS_Too Long Meta Description, HS_Pages droped from top 10 Pos | P14: Pages dropped out of top 10 (homepage 249 -> 0 traffic); slow site; untranslated slugs
A15: 11 | B15: Striking Viking | C15: 53 | D15: 4107 | F15: US 31, DE 8 | G15: Biggest brand, 1.3% D2C | H15: =IF(AND(ISNUMBER(C15),ISNUMBER(D15),D15<>0),C15/D15,"-") -> 0.012904797 | I15: =IF(K15=0,"Not started",IF(L15=0,"Complete","Audit delivered")) -> Audit delivered | J15: Issues workbook (12 tabs) | K15: =COUNTIF('Issue Tracker'!$B$5:$B$84,B15) -> 12 | L15: =K15-COUNTIFS('Issue Tracker'!$B$5:$B$84,B15,'Issue Tracker'!$J$5:$J$84,"Fixed")-COUNTIFS('Issue Tracker'!$B$5:$B$84,B15,'Issue Tracker'!$J$5:$J$84,"Already Fixed") -> 12 | M15: =COUNTIFS('Issue Tracker'!$B$5:$B$84,B15,'Issue Tracker'!$I$5:$I$84,"High",'Issue Tracker'!$J$5:$J$84,"<>Fixed",'Issue Tracker'!$J$5:$J$84,"<>Already Fixed")+COUNTIFS('Issue Tracker'!$B$5:$B$84,B15,'Issue Tracker'!$I$5:$I$84,"Critical",'Issue Tracker'!$J$5:$J$84,"<>Fixed",'Issue Tracker'!$J$5:$J$84,"<>Already Fixed") -> 5 | N15: =SUMIF('Issue Tracker'!$B$5:$B$84,B15,'Issue Tracker'!$G$5:$G$84) -> 3127 | O15: SV_4xx, SV_3xx Redirection, SV_Page has links to broken pag, SV_Meta description too long, SV_Title too long, SV_Missing H1, SV_Meta description too short, SV_Meta description tag missing, SV_Multiple H1 tags, SV_Pages have high AI content l, SV_Missing alt text, SV_External 4XX | P15: 4xx / broken links incl. external 404s; 1.2k long meta descriptions
A16: 12 | B16: Luxsports (LUX) | C16: 50 | D16: 2004 | F16: US, UK, DE, ES, FR | H16: =IF(AND(ISNUMBER(C16),ISNUMBER(D16),D16<>0),C16/D16,"-") -> 0.0249501 | I16: =IF(K16=0,"Not started",IF(L16=0,"Complete","Audit delivered")) -> Audit delivered | J16: Technical SEO audit doc | K16: =COUNTIF('Issue Tracker'!$B$5:$B$84,B16) -> 9 | L16: =K16-COUNTIFS('Issue Tracker'!$B$5:$B$84,B16,'Issue Tracker'!$J$5:$J$84,"Fixed")-COUNTIFS('Issue Tracker'!$B$5:$B$84,B16,'Issue Tracker'!$J$5:$J$84,"Already Fixed") -> 8 | M16: =COUNTIFS('Issue Tracker'!$B$5:$B$84,B16,'Issue Tracker'!$I$5:$I$84,"High",'Issue Tracker'!$J$5:$J$84,"<>Fixed",'Issue Tracker'!$J$5:$J$84,"<>Already Fixed")+COUNTIFS('Issue Tracker'!$B$5:$B$84,B16,'Issue Tracker'!$I$5:$I$84,"Critical",'Issue Tracker'!$J$5:$J$84,"<>Fixed",'Issue Tracker'!$J$5:$J$84,"<>Already Fixed") -> 4 | N16: =SUMIF('Issue Tracker'!$B$5:$B$84,B16,'Issue Tracker'!$G$5:$G$84) -> 3 | O16: - | P16: en-NZ hreflang points to /en-au; overlapping & empty collections
A17: - | B17: Babysunnies | G17: Not on priority list - audit delivered | H17: =IF(AND(ISNUMBER(C17),ISNUMBER(D17),D17<>0),C17/D17,"-") -> - | I17: =IF(K17=0,"Not started",IF(L17=0,"Complete","Audit delivered")) -> Audit delivered | J17: Technical SEO audit doc (3 versions - latest used) | K17: =COUNTIF('Issue Tracker'!$B$5:$B$84,B17) -> 10 | L17: =K17-COUNTIFS('Issue Tracker'!$B$5:$B$84,B17,'Issue Tracker'!$J$5:$J$84,"Fixed")-COUNTIFS('Issue Tracker'!$B$5:$B$84,B17,'Issue Tracker'!$J$5:$J$84,"Already Fixed") -> 10 | M17: =COUNTIFS('Issue Tracker'!$B$5:$B$84,B17,'Issue Tracker'!$I$5:$I$84,"High",'Issue Tracker'!$J$5:$J$84,"<>Fixed",'Issue Tracker'!$J$5:$J$84,"<>Already Fixed")+COUNTIFS('Issue Tracker'!$B$5:$B$84,B17,'Issue Tracker'!$I$5:$I$84,"Critical",'Issue Tracker'!$J$5:$J$84,"<>Fixed",'Issue Tracker'!$J$5:$J$84,"<>Already Fixed") -> 1 | N17: =SUMIF('Issue Tracker'!$B$5:$B$84,B17,'Issue Tracker'!$G$5:$G$84) -> 150 | O17: - | P17: robots.txt keeps 120 dead URLs indexed
A18: - | B18: Coachsoak | G18: Not on priority list - audit delivered | H18: =IF(AND(ISNUMBER(C18),ISNUMBER(D18),D18<>0),C18/D18,"-") -> - | I18: =IF(K18=0,"Not started",IF(L18=0,"Complete","Audit delivered")) -> Audit delivered | J18: SEO audit & analysis doc | K18: =COUNTIF('Issue Tracker'!$B$5:$B$84,B18) -> 12 | L18: =K18-COUNTIFS('Issue Tracker'!$B$5:$B$84,B18,'Issue Tracker'!$J$5:$J$84,"Fixed")-COUNTIFS('Issue Tracker'!$B$5:$B$84,B18,'Issue Tracker'!$J$5:$J$84,"Already Fixed") -> 12 | M18: =COUNTIFS('Issue Tracker'!$B$5:$B$84,B18,'Issue Tracker'!$I$5:$I$84,"High",'Issue Tracker'!$J$5:$J$84,"<>Fixed",'Issue Tracker'!$J$5:$J$84,"<>Already Fixed")+COUNTIFS('Issue Tracker'!$B$5:$B$84,B18,'Issue Tracker'!$I$5:$I$84,"Critical",'Issue Tracker'!$J$5:$J$84,"<>Fixed",'Issue Tracker'!$J$5:$J$84,"<>Already Fixed") -> 5 | N18: =SUMIF('Issue Tracker'!$B$5:$B$84,B18,'Issue Tracker'!$G$5:$G$84) -> 5 | O18: - | P18: Sep clicks -40% vs Jul; broken sitemap in GSC
B19: Total priority list (1P, excl. ANSWR 3P) | C19: =SUM(C5:C16)-C12 -> 2920 | D19: =SUM(D5:D16)-D12 -> 16166 | H19: =IF(D19<>0,C19/D19,"-") -> 0.18062601 | K19: =SUM(K5:K18) -> 80 | L19: =SUM(L5:L18) -> 79 | M19: =SUM(M5:M18) -> 34 | N19: =SUM(N5:N18) -> 9907
B20: Brand total for Opengoaaal UK-EU is blank in the source list; Open Goaaal USA / Luonkos brand totals cover both stores. Revenue, markets and flags: from the user's priority list screenshot (12-Oct-2026).
B22: Issue status summary
B23: Status | C23: Issues | D23: Share
B24: Need to Fix | C24: =COUNTIF('Issue Tracker'!$J$5:$J$84,B24) -> 78 | D24: =IF($C$30=0,0,C24/$C$30) -> 0.975
B25: In Progress | C25: =COUNTIF('Issue Tracker'!$J$5:$J$84,B25) -> 0 | D25: =IF($C$30=0,0,C25/$C$30) -> 0
B26: To Validate | C26: =COUNTIF('Issue Tracker'!$J$5:$J$84,B26) -> 1 | D26: =IF($C$30=0,0,C26/$C$30) -> 0.0125
B27: Fixed | C27: =COUNTIF('Issue Tracker'!$J$5:$J$84,B27) -> 0 | D27: =IF($C$30=0,0,C27/$C$30) -> 0
B28: Already Fixed | C28: =COUNTIF('Issue Tracker'!$J$5:$J$84,B28) -> 1 | D28: =IF($C$30=0,0,C28/$C$30) -> 0.0125
B29: Won't Fix | C29: =COUNTIF('Issue Tracker'!$J$5:$J$84,B29) -> 0 | D29: =IF($C$30=0,0,C29/$C$30) -> 0
B30: Total | C30: =SUM(C24:C29) -> 80 | D30: =SUM(D24:D29) -> 1
B31: Legend: blue = typed input from source; black = formula; yellow cells on Issue Tracker = edit Priority / Status / Owner / Due date / Notes.

Sheet Issue Tracker
A1: Issue Tracker - all projects
A2: One row per issue. Counts in black are live formulas on the project tabs; blue counts are typed from the Word reports. Edit Priority / Status / Owner / Notes (yellow).
A4: # | B4: Project | C4: Issue | D4: Category | E4: Source | F4: Source file | G4: Affected URLs / rows | H4: Open tab | I4: Priority | J4: Status | K4: Owner | L4: Due date | M4: Notes
A5: 1 | B5: Bigbatbox (WildYard) | C5: Broken links (4xx pages) | D5: Links & Status Codes | E5: Sheet | F5: Bigbatbox - Site Audit.xlsx | G5: =COUNTA('BBB_Broken Links'!B2:B32) -> 31 | H5: =HYPERLINK("#'BBB_Broken Links'!A1","BBB_Broken Links") -> BBB_Broken Links | I5: High | J5: Need to Fix
A6: 2 | B6: Bigbatbox (WildYard) | C6: Broken Internal Link | D6: Links & Status Codes | E6: Sheet | F6: Bigbatbox - Site Audit.xlsx | G6: =COUNTA('BBB_Broken Internal Link'!B2:B32) -> 31 | H6: =HYPERLINK("#'BBB_Broken Internal Link'!A1","BBB_Broken Internal Link") -> BBB_Broken Internal Link | I6: High | J6: Need to Fix
A7: 3 | B7: Bigbatbox (WildYard) | C7: Pages Marked No Index | D7: Indexing / Intl / Content | E7: Sheet | F7: Bigbatbox - Site Audit.xlsx | G7: =COUNTA('BBB_Pages Marked No Index'!B2:B6) -> 5 | H7: =HYPERLINK("#'BBB_Pages Marked No Index'!A1","BBB_Pages Marked No Index") -> BBB_Pages Marked No Index | I7: High | J7: Need to Fix
A8: 4 | B8: Bigbatbox (WildYard) | C8: URLs not submitted to IndexNow | D8: Indexing / Intl / Content | E8: Sheet | F8: Bigbatbox - Site Audit.xlsx | G8: =COUNTA('BBB_Not submitted to IndexNow'!B2:B2111) -> 2110 | H8: =HYPERLINK("#'BBB_Not submitted to IndexNow'!A1","BBB_Not submitted to IndexNow") -> BBB_Not submitted to IndexNow | I8: High | J8: Need to Fix
A9: 5 | B9: Bigbatbox (WildYard) | C9: Page has links to broken page | D9: Links & Status Codes | E9: Sheet | F9: Bigbatbox - Site Audit.xlsx | G9: =COUNTA('BBB_Page has links to broken pa'!B2:B28) -> 27 | H9: =HYPERLINK("#'BBB_Page has links to broken pa'!A1","BBB_Page has links to broken pa") -> BBB_Page has links to broken pa | I9: High | J9: Need to Fix
A10: 6 | B10: Bigbatbox (WildYard) | C10: Redirecting URLs | D10: Links & Status Codes | E10: Sheet | F10: Bigbatbox - Site Audit.xlsx | G10: =COUNTA('BBB_Redirecting URLs'!B2:B33) -> 32 | H10: =HYPERLINK("#'BBB_Redirecting URLs'!A1","BBB_Redirecting URLs") -> BBB_Redirecting URLs | I10: High | J10: Need to Fix
A11: 7 | B11: Bigbatbox (WildYard) | C11: Too Long Meta Title | D11: On-page Meta & Headings | E11: Sheet | F11: Bigbatbox - Site Audit.xlsx | G11: =COUNTA('BBB_Too Long Meta Title'!B2:B1747) -> 1746 | H11: =HYPERLINK("#'BBB_Too Long Meta Title'!A1","BBB_Too Long Meta Title") -> BBB_Too Long Meta Title | I11: Medium | J11: Need to Fix
A12: 8 | B12: Bigbatbox (WildYard) | C12: Too Long Meta Description | D12: On-page Meta & Headings | E12: Sheet | F12: Bigbatbox - Site Audit.xlsx | G12: =COUNTA('BBB_Too Long Meta Description'!B2:B193) -> 192 | H12: =HYPERLINK("#'BBB_Too Long Meta Description'!A1","BBB_Too Long Meta Description") -> BBB_Too Long Meta Description | I12: Medium | J12: Need to Fix
A13: 9 | B13: Bigbatbox (WildYard) | C13: Missing H1 Tag | D13: On-page Meta & Headings | E13: Sheet | F13: Bigbatbox - Site Audit.xlsx | G13: =COUNTA('BBB_Missing H1 Tag'!B2:B109) -> 108 | H13: =HYPERLINK("#'BBB_Missing H1 Tag'!A1","BBB_Missing H1 Tag") -> BBB_Missing H1 Tag | I13: Medium | J13: Need to Fix
A14: 10 | B14: Bigbatbox (WildYard) | C14: Missing Meta Description | D14: On-page Meta & Headings | E14: Sheet | F14: Bigbatbox - Site Audit.xlsx | G14: =COUNTA('BBB_Missing Meta Description'!B2:B7) -> 6 | H14: =HYPERLINK("#'BBB_Missing Meta Description'!A1","BBB_Missing Meta Description") -> BBB_Missing Meta Description | I14: Medium | J14: Need to Fix
A15: 11 | B15: Bigbatbox (WildYard) | C15: Multiple H1 Tag | D15: On-page Meta & Headings | E15: Sheet | F15: Bigbatbox - Site Audit.xlsx | G15: =COUNTA('BBB_Multiple H1 Tag'!B2:B291) -> 290 | H15: =HYPERLINK("#'BBB_Multiple H1 Tag'!A1","BBB_Multiple H1 Tag") -> BBB_Multiple H1 Tag | I15: Medium | J15: Need to Fix
A16: 12 | B16: Bigbatbox (WildYard) | C16: Page and SERP titles do not match | D16: On-page Meta & Headings | E16: Sheet | F16: Bigbatbox - Site Audit.xlsx | G16: =COUNTA('BBB_Page and SERP titles do not'!B2:B30) -> 29 | H16: =HYPERLINK("#'BBB_Page and SERP titles do not'!A1","BBB_Page and SERP titles do not") -> BBB_Page and SERP titles do not | I16: Medium | J16: Need to Fix
A17: 13 | B17: Bigbatbox (WildYard) | C17: Twitter & Open Graph tags incomplete | D17: Media / Markup | E17: Sheet | F17: Bigbatbox - Site Audit.xlsx | G17: =COUNTA('BBB_Twitter and Open Graph tags'!B2:B7) -> 6 | H17: =HYPERLINK("#'BBB_Twitter and Open Graph tags'!A1","BBB_Twitter and Open Graph tags") -> BBB_Twitter and Open Graph tags | I17: Low | J17: Need to Fix
A18: 14 | B18: Bigbatbox (WildYard) | C18: Image file size too large | D18: Performance & Media | E18: Sheet | F18: Bigbatbox - Site Audit.xlsx | G18: =COUNTA('BBB_Image file size too large'!B2:B96) -> 95 | H18: =HYPERLINK("#'BBB_Image file size too large'!A1","BBB_Image file size too large") -> BBB_Image file size too large | I18: Medium | J18: Need to Fix
A19: 15 | B19: Bigbatbox (WildYard) | C19: Images Missing ALT text | D19: Performance & Media | E19: Sheet | F19: Bigbatbox - Site Audit.xlsx | G19: =COUNTA('BBB_Images Missing ALT text'!B2:B7) -> 6 | H19: =HYPERLINK("#'BBB_Images Missing ALT text'!A1","BBB_Images Missing ALT text") -> BBB_Images Missing ALT text | I19: Medium | J19: Need to Fix
A20: 16 | B20: Happy Sinks | C20: Missing H1 Tag | D20: On-page Meta & Headings | E20: Sheet | F20: https_happy-sinks.com_ - URL Report.xlsx | G20: =COUNTA('HS_Missing H1 Tag'!A2:A175) -> 174 | H20: =HYPERLINK("#'HS_Missing H1 Tag'!A1","HS_Missing H1 Tag") -> HS_Missing H1 Tag | I20: Medium | J20: Need to Fix
A21: 17 | B21: Happy Sinks | C21: Multiple H1 Tag | D21: On-page Meta & Headings | E21: Sheet | F21: https_happy-sinks.com_ - URL Report.xlsx | G21: =COUNTA('HS_Multiple H1 Tag'!A2:A103) -> 102 | H21: =HYPERLINK("#'HS_Multiple H1 Tag'!A1","HS_Multiple H1 Tag") -> HS_Multiple H1 Tag | I21: Medium | J21: Need to Fix
A22: 18 | B22: Happy Sinks | C22: Too Long Meta Title | D22: On-page Meta & Headings | E22: Sheet | F22: https_happy-sinks.com_ - URL Report.xlsx | G22: =COUNTA('HS_Too Long Meta Title'!A2:A335) -> 334 | H22: =HYPERLINK("#'HS_Too Long Meta Title'!A1","HS_Too Long Meta Title") -> HS_Too Long Meta Title | I22: Medium | J22: Need to Fix
A23: 19 | B23: Happy Sinks | C23: Too Long Meta Description | D23: On-page Meta & Headings | E23: Sheet | F23: https_happy-sinks.com_ - URL Report.xlsx | G23: =COUNTA('HS_Too Long Meta Description'!A2:A997) -> 996 | H23: =HYPERLINK("#'HS_Too Long Meta Description'!A1","HS_Too Long Meta Description") -> HS_Too Long Meta Description | I23: Medium | J23: Need to Fix
A24: 20 | B24: Happy Sinks | C24: Pages dropped from top-10 positions | D24: Indexing / Intl / Content | E24: Sheet | F24: https_happy-sinks.com_ - URL Report.xlsx | G24: =COUNTA('HS_Pages droped from top 10 Pos'!A2:A99) -> 98 | H24: =HYPERLINK("#'HS_Pages droped from top 10 Pos'!A1","HS_Pages droped from top 10 Pos") -> HS_Pages droped from top 10 Pos | I24: High | J24: Need to Fix
A25: 21 | B25: Striking Viking | C25: 4xx | D25: Links & Status Codes | E25: Sheet | F25: striking-viking - Issues.xlsx | G25: =COUNTA(SV_4xx!B5:B85) -> 81 | H25: =HYPERLINK("#'SV_4xx'!A1","SV_4xx") -> SV_4xx | I25: High | J25: Need to Fix
A26: 22 | B26: Striking Viking | C26: 3xx Redirection | D26: Links & Status Codes | E26: Sheet | F26: striking-viking - Issues.xlsx | G26: =COUNTA('SV_3xx Redirection'!A6:A215) -> 210 | H26: =HYPERLINK("#'SV_3xx Redirection'!A1","SV_3xx Redirection") -> SV_3xx Redirection | I26: High | J26: Need to Fix
A27: 23 | B27: Striking Viking | C27: Page has links to broken page | D27: Links & Status Codes | E27: Sheet | F27: striking-viking - Issues.xlsx | G27: =COUNTA('SV_Page has links to broken pag'!B5:B70) -> 66 | H27: =HYPERLINK("#'SV_Page has links to broken pag'!A1","SV_Page has links to broken pag") -> SV_Page has links to broken pag | I27: High | J27: Need to Fix
A28: 24 | B28: Striking Viking | C28: Meta description too long | D28: On-page Meta & Headings | E28: Sheet | F28: striking-viking - Issues.xlsx | G28: =COUNTA('SV_Meta description too long'!C5:C1220) -> 1216 | H28: =HYPERLINK("#'SV_Meta description too long'!A1","SV_Meta description too long") -> SV_Meta description too long | I28: Medium | J28: Need to Fix
A29: 25 | B29: Striking Viking | C29: Title too long | D29: On-page Meta & Headings | E29: Sheet | F29: striking-viking - Issues.xlsx | G29: =COUNTA('SV_Title too long'!B4:B775) -> 772 | H29: =HYPERLINK("#'SV_Title too long'!A1","SV_Title too long") -> SV_Title too long | I29: Medium | J29: Need to Fix
A30: 26 | B30: Striking Viking | C30: Missing H1 | D30: On-page Meta & Headings | E30: Sheet | F30: striking-viking - Issues.xlsx | G30: =COUNTA('SV_Missing H1'!C4:C91) -> 88 | H30: =HYPERLINK("#'SV_Missing H1'!A1","SV_Missing H1") -> SV_Missing H1 | I30: Medium | J30: Need to Fix
A31: 27 | B31: Striking Viking | C31: Meta description too short | D31: On-page Meta & Headings | E31: Sheet | F31: striking-viking - Issues.xlsx | G31: =COUNTA('SV_Meta description too short'!C5:C48) -> 44 | H31: =HYPERLINK("#'SV_Meta description too short'!A1","SV_Meta description too short") -> SV_Meta description too short | I31: Medium | J31: Need to Fix
A32: 28 | B32: Striking Viking | C32: Meta description tag missing or empty | D32: On-page Meta & Headings | E32: Sheet | F32: striking-viking - Issues.xlsx | G32: =COUNTA('SV_Meta description tag missing'!C6:C15) -> 10 | H32: =HYPERLINK("#'SV_Meta description tag missing'!A1","SV_Meta description tag missing") -> SV_Meta description tag missing | I32: Medium | J32: Need to Fix
A33: 29 | B33: Striking Viking | C33: Multiple H1 tags | D33: On-page Meta & Headings | E33: Sheet | F33: striking-viking - Issues.xlsx | G33: =COUNTA('SV_Multiple H1 tags'!C4:C255) -> 252 | H33: =HYPERLINK("#'SV_Multiple H1 tags'!A1","SV_Multiple H1 tags") -> SV_Multiple H1 tags | I33: Medium | J33: Need to Fix
A34: 30 | B34: Striking Viking | C34: Pages have high AI content levels | D34: Indexing / Intl / Content | E34: Sheet | F34: striking-viking - Issues.xlsx | G34: =COUNTA('SV_Pages have high AI content l'!C5:C5) -> 1 | H34: =HYPERLINK("#'SV_Pages have high AI content l'!A1","SV_Pages have high AI content l") -> SV_Pages have high AI content l | I34: High | J34: Need to Fix
A35: 31 | B35: Striking Viking | C35: Missing alt text | D35: Media / Markup | E35: Sheet | F35: striking-viking - Issues.xlsx | G35: =COUNTA('SV_Missing alt text'!C4:C324) -> 321 | H35: =HYPERLINK("#'SV_Missing alt text'!A1","SV_Missing alt text") -> SV_Missing alt text | I35: Low | J35: Need to Fix
A36: 32 | B36: Striking Viking | C36: External 4XX | D36: Links & Status Codes | E36: Sheet | F36: striking-viking - Issues.xlsx | G36: =COUNTA('SV_External 4XX'!B6:B71) -> 66 | H36: =HYPERLINK("#'SV_External 4XX'!A1","SV_External 4XX") -> SV_External 4XX | I36: High | J36: Need to Fix
A37: 33 | B37: Bigbatbox (WildYard) | C37: Pages not indexed in Google (GSC) | D37: Indexing / Intl / Content | E37: Report | F37: Site Audit & Analysis - Bigbatbox.docx | G37: 170 | I37: High | J37: Need to Fix | M37: 170 of 761 pages not indexed
A38: 34 | B38: Bigbatbox (WildYard) | C38: Manual action: thin content with little or no added value | D38: Indexing / Intl / Content | E38: Report | F38: Site Audit & Analysis - Bigbatbox.docx | I38: Critical | J38: Need to Fix | M38: Google manual spam action on /blogs section - top priority
A39: 35 | B39: Bigbatbox (WildYard) | C39: Organic traffic drop on key product/category pages | D39: Indexing / Intl / Content | E39: Report | F39: Site Audit & Analysis - Bigbatbox.docx | G39: 10 | I39: High | J39: Need to Fix | M39: Homepage -435 clicks; 'bat house' impressions -12.5k
A40: 36 | B40: Bigbatbox (WildYard) | C40: Translation issue: /de /es /fr /it /en-ca blog URLs still show English | D40: Indexing / Intl / Content | E40: Report | F40: Big Bat Box - Issues.docx | G40: 18 | I40: High | J40: Need to Fix | M40: 18 example URLs listed in report
A41: 37 | B41: Luonkos Finland (.fi) | C41: English pages not fully localized (Finnish text / Finnish slugs) | D41: Other | E41: Report | F41: Luonkos - Audit & Analysis.docx | I41: Medium | J41: Need to Fix | M41: luonkos.fi/en
A42: 38 | B42: Luonkos Finland (.fi) | C42: luonkos.com weak and overlapping with luonkos.fi/en | D42: Other | E42: Report | F42: Luonkos - Audit & Analysis.docx | I42: Medium | J42: Need to Fix
A43: 39 | B43: Luonkos Finland (.fi) | C43: Regional product pages not indexed (Google picks generic canonical) | D43: Indexing / Intl / Content | E43: Report | F43: Luonkos - Audit & Analysis.docx | I43: High | J43: Need to Fix | M43: e.g. /en-nl/ product URLs
A44: 40 | B44: Luonkos Finland (.fi) | C44: Post-merge: English URLs on luonkos.fi return 404 | D44: Links & Status Codes | E44: Report | F44: Luonkos_Merge_404_Report.docx | I44: High | J44: Need to Fix | M44: Report dated 23 Sep 2026; redirect map provided
A45: 41 | B45: Luonkos Finland (.fi) | C45: Post-merge: Swedish URLs with traffic return 404 | D45: Links & Status Codes | E45: Report | F45: Luonkos_Merge_404_Report.docx | I45: High | J45: Need to Fix
A46: 42 | B46: Luonkos Finland (.fi) | C46: Hreflang now points other languages to luonkos.com | D46: Indexing / Intl / Content | E46: Report | F46: Luonkos_Merge_404_Report.docx | I46: High | J46: Need to Fix
A47: 43 | B47: Bodyotics | C47: Spanish URL ranking in Germany (wrong language/market) | D47: Indexing / Intl / Content | E47: Report | F47: Bodyotics Analysis.docx | I47: High | J47: Need to Fix | M47: 'disco menstrual' query
A48: 44 | B48: Bodyotics | C48: English URLs ranking for NL and FR queries | D48: Other | E48: Report | F48: Bodyotics Analysis.docx | I48: Medium | J48: Need to Fix | M48: Blog index outranks translated articles
A49: 45 | B49: Open Goaaal USA | C49: Duplicate blog content between opengoaaal.com and opengoaaalusa.com | D49: Indexing / Intl / Content | E49: Report | F49: Opengoaaal - Duplicate Content Report.docx | G49: 3 | I49: High | J49: Need to Fix | M49: 3 cases documented; already caused a ranking penalty
A50: 46 | B50: Opengoaaal UK-EU | C50: Duplicate blog content between opengoaaal.com and opengoaaalusa.com | D50: Indexing / Intl / Content | E50: Report | F50: Opengoaaal - Duplicate Content Report.docx | G50: 3 | I50: High | J50: Need to Fix | M50: Same report - affects both stores
A51: 47 | B51: Happy Sinks | C51: Slow website speed (mobile & desktop) | D51: Performance & Media | E51: Report | F51: https_happy-sinks.com_ - SEO Audit & Analysis Report.docx | I51: Medium | J51: Need to Fix | M51: Home, collection, product pages tested
A52: 48 | B52: Happy Sinks | C52: Localized URL slugs not translated (e.g. /fi/) | D52: Other | E52: Report | F52: https_happy-sinks.com_ - SEO Audit & Analysis Report.docx | I52: Medium | J52: Need to Fix
A53: 49 | B53: Happy Sinks | C53: Empty metaobject sitemap files | D53: Indexing / Intl / Content | E53: Report | F53: https_happy-sinks.com_ - SEO Audit & Analysis Report.docx | I53: High | J53: Need to Fix
A54: 50 | B54: Luxsports (LUX) | C54: Incorrect en-NZ hreflang mapping (points to /en-au) | D54: Indexing / Intl / Content | E54: Report | F54: https_luxsports.co_.docx | I54: High | J54: Need to Fix
A55: 51 | B55: Luxsports (LUX) | C55: Duplicate product listed across multiple collection pages | D55: Indexing / Intl / Content | E55: Report | F55: https_luxsports.co_.docx | I55: High | J55: Need to Fix
A56: 52 | B56: Luxsports (LUX) | C56: Language URLs not maintained across localized pages | D56: Indexing / Intl / Content | E56: Report | F56: https_luxsports.co_.docx | I56: High | J56: Already Fixed | M56: Marked {Already Fixed} in report
A57: 53 | B57: Luxsports (LUX) | C57: Empty collection page (LUX - Retail Collection FAIRE) | D57: Other | E57: Report | F57: https_luxsports.co_.docx | G57: 1 | I57: Medium | J57: Need to Fix
A58: 54 | B58: Luxsports (LUX) | C58: Overlapping collection pages (/all vs /all-products-luxsports) | D58: Other | E58: Report | F58: https_luxsports.co_.docx | G58: 2 | I58: Medium | J58: Need to Fix
A59: 55 | B59: Luxsports (LUX) | C59: Search/filter URL crawl | D59: Other | E59: Report | F59: https_luxsports.co_.docx | I59: Medium | J59: To Validate | M59: Report says 'Need to validate'
A60: 56 | B60: Luxsports (LUX) | C60: Inconsistent meta title localization across language pages | D60: Indexing / Intl / Content | E60: Report | F60: https_luxsports.co_.docx | I60: High | J60: Need to Fix
A61: 57 | B61: Luxsports (LUX) | C61: Broken internal links (404) | D61: Links & Status Codes | E61: Report | F61: https_luxsports.co_.docx | I61: High | J61: Need to Fix
A62: 58 | B62: Luxsports (LUX) | C62: Website speed (Home: mobile 55 / desktop 74) | D62: Performance & Media | E62: Report | F62: https_luxsports.co_.docx | I62: Medium | J62: Need to Fix | M62: Checked 07-10-2026
A63: 59 | B63: Babysunnies | C63: robots.txt keeping dead URLs stuck in Google | D63: Indexing / Intl / Content | E63: Report | F63: Babysunnies.com _ Technical SEO Audit(1).docx | G63: 120 | I63: High | J63: Need to Fix
A64: 60 | B64: Babysunnies | C64: Homepage has no H1 tag | D64: On-page Meta & Headings | E64: Report | F64: Babysunnies.com _ Technical SEO Audit(1).docx | G64: 3 | I64: Medium | J64: Need to Fix | M64: Also Contact Us & Customer Reviews
A65: 61 | B65: Babysunnies | C65: Comparison pages show the same H1 twice | D65: On-page Meta & Headings | E65: Report | F65: Babysunnies.com _ Technical SEO Audit(1).docx | G65: 3 | I65: Medium | J65: Need to Fix
A66: 62 | B66: Babysunnies | C66: Brand name repeated in page titles | D66: On-page Meta & Headings | E66: Report | F66: Babysunnies.com _ Technical SEO Audit(1).docx | I66: Medium | J66: Need to Fix
A67: 63 | B67: Babysunnies | C67: Most page titles too long / truncated | D67: On-page Meta & Headings | E67: Report | F67: Babysunnies.com _ Technical SEO Audit(1).docx | I67: Medium | J67: Need to Fix
A68: 64 | B68: Babysunnies | C68: Meta descriptions missing or copied from page text | D68: On-page Meta & Headings | E68: Report | F68: Babysunnies.com _ Technical SEO Audit(1).docx | G68: 8 | I68: Medium | J68: Need to Fix
A69: 65 | B69: Babysunnies | C69: Key images have no alt text | D69: Performance & Media | E69: Report | F69: Babysunnies.com _ Technical SEO Audit(1).docx | I69: Medium | J69: Need to Fix
A70: 66 | B70: Babysunnies | C70: Product schema missing shipping & return details | D70: Media / Markup | E70: Report | F70: Babysunnies.com _ Technical SEO Audit(1).docx | I70: Low | J70: Need to Fix
A71: 67 | B71: Babysunnies | C71: Homepage slow on mobile (PageSpeed lab test) | D71: Performance & Media | E71: Report | F71: Babysunnies.com _ Technical SEO Audit(1).docx | G71: 1 | I71: Medium | J71: Need to Fix
A72: 68 | B72: Babysunnies | C72: Adult Cloudfield sunglasses on a baby sunglasses site | D72: Other | E72: Report | F72: Babysunnies.com _ Technical SEO Audit(1).docx | G72: 15 | I72: Medium | J72: Need to Fix
A73: 69 | B73: Coachsoak | C73: Old/broken sitemap in Search Console | D73: Links & Status Codes | E73: Report | F73: coachsoak.com - SEO Audit & Analysis Report.docx | I73: High | J73: Need to Fix | M73: Clicks Sep vs Jul -40%
A74: 70 | B74: Coachsoak | C74: Traffic concentrated on one blog post | D74: Indexing / Intl / Content | E74: Report | F74: coachsoak.com - SEO Audit & Analysis Report.docx | I74: High | J74: Need to Fix
A75: 71 | B75: Coachsoak | C75: Pages get impressions but low CTR (rewrite titles/meta) | D75: On-page Meta & Headings | E75: Report | F75: coachsoak.com - SEO Audit & Analysis Report.docx | G75: 5 | I75: Medium | J75: Need to Fix
A76: 72 | B76: Coachsoak | C76: Rich result warnings on products | D76: Media / Markup | E76: Report | F76: coachsoak.com - SEO Audit & Analysis Report.docx | I76: Low | J76: Need to Fix
A77: 73 | B77: Coachsoak | C77: Custom robots.txt rules do not work | D77: Indexing / Intl / Content | E77: Report | F77: coachsoak.com - SEO Audit & Analysis Report.docx | I77: High | J77: Need to Fix
A78: 74 | B78: Coachsoak | C78: Large image banner | D78: Performance & Media | E78: Report | F78: coachsoak.com - SEO Audit & Analysis Report.docx | I78: Medium | J78: Need to Fix
A79: 75 | B79: Coachsoak | C79: Low mobile page speed / poor LCP | D79: Performance & Media | E79: Report | F79: coachsoak.com - SEO Audit & Analysis Report.docx | I79: Medium | J79: Need to Fix
A80: 76 | B80: Coachsoak | C80: Sold-out item at top of page | D80: Other | E80: Report | F80: coachsoak.com - SEO Audit & Analysis Report.docx | I80: Medium | J80: Need to Fix
A81: 77 | B81: Coachsoak | C81: Thin content & weak internal linking on collections | D81: Indexing / Intl / Content | E81: Report | F81: coachsoak.com - SEO Audit & Analysis Report.docx | I81: High | J81: Need to Fix
A82: 78 | B82: Coachsoak | C82: H1 tag missing on multiple pages | D82: On-page Meta & Headings | E82: Report | F82: coachsoak.com - SEO Audit & Analysis Report.docx | I82: Medium | J82: Need to Fix
A83: 79 | B83: Coachsoak | C83: High bounce rate | D83: Other | E83: Report | F83: coachsoak.com - SEO Audit & Analysis Report.docx | I83: Medium | J83: Need to Fix
A84: 80 | B84: Coachsoak | C84: Translation not working properly | D84: Indexing / Intl / Content | E84: Report | F84: coachsoak.com - SEO Audit & Analysis Report.docx | I84: High | J84: Need to Fix

Sheet File Inventory
A1: File Inventory - Robin - Site Audit & Analysis folder
A2: Every file in the uploaded zip, what it contains, and where it lives in this master sheet.
A4: # | B4: File | C4: Type | D4: Project | E4: Last modified | F4: Contents | G4: In master as | H4: Note
A5: 1 | B5: Bigbatbox - Site Audit.xlsx | C5: xlsx | D5: Bigbatbox (WildYard) | E5: 46276 | F5: Master checklist + 15 Ahrefs issue tabs | G5: BBB_Master Checklist, BBB_Broken Links, BBB_Broken Internal Link, BBB_Pages Marked No Index, BBB_Not submitted to IndexNow, BBB_Page has links to broken pa, BBB_Redirecting URLs, BBB_Too Long Meta Title, BBB_Too Long Meta Description, BBB_Missing H1 Tag, BBB_Missing Meta Description, BBB_Multiple H1 Tag, BBB_Page and SERP titles do not, BBB_Twitter and Open Graph tags, BBB_Image file size too large, BBB_Images Missing ALT text
A6: 2 | B6: Site Audit & Analysis - Bigbatbox.docx | C6: docx | D6: Bigbatbox (WildYard) | E6: 46279 | F6: GSC indexing, traffic drop, manual action, tech issues | G6: Issue Tracker (Source = Report)
A7: 3 | B7: Big Bat Box - Issues.docx | C7: docx | D7: Bigbatbox (WildYard) | E7: 46280 | F7: Translation issue - language URLs show English | G7: Issue Tracker (Source = Report)
A8: 4 | B8: https_happy-sinks.com_ - URL Report.xlsx | C8: xlsx | D8: Happy Sinks | E8: 46304 | F8: H1, meta title/description, pages dropped from top 10 | G8: HS_Missing H1 Tag, HS_Multiple H1 Tag, HS_Too Long Meta Title, HS_Too Long Meta Description, HS_Pages droped from top 10 Pos
A9: 5 | B9: https_happy-sinks.com_ - SEO Audit & Analysis Report.docx | C9: docx | D9: Happy Sinks | E9: 46304 | F9: Speed, translation, hreflang, sitemap, headings, meta, GSC | G9: Issue Tracker (Source = Report)
A10: 6 | B10: opengoaaalusa.com - Blog Content_.xlsx | C10: xlsx | D10: Open Goaaal USA | E10: 46280 | F10: Blog pages clicks/impressions (6 mo vs prior), GSC countries, filters | G10: OGU_Blog Pages, OGU_Countries, OGU_Filters
A11: 7 | B11: Site Audit & Analysis - opengoaaalusa.com.docx | C11: docx | D11: Open Goaaal USA | E11: 46275 | F11: Screenshots only - no text | G11: - | H11: No text content to extract
A12: 8 | B12: Opengoaaal - Duplicate Content Report.docx | C12: docx | D12: Open Goaaal USA / UK-EU | E12: 46280 | F12: Duplicate blog content across the two stores (3 cases) | G12: Issue Tracker (Source = Report)
A13: 9 | B13: striking-viking - Issues.xlsx | C13: xlsx | D13: Striking Viking | E13: 46299 | F13: 12 Ahrefs issue tabs with Status column | G13: SV_4xx, SV_3xx Redirection, SV_Page has links to broken pag, SV_Meta description too long, SV_Title too long, SV_Missing H1, SV_Meta description too short, SV_Meta description tag missing, SV_Multiple H1 tags, SV_Pages have high AI content l, SV_Missing alt text, SV_External 4XX
A14: 10 | B14: Luonkos - Audit & Analysis.docx | C14: docx | D14: Luonkos Finland (.fi) | E14: 46283 | F14: hreflang & canonical review, localization, regional indexing | G14: Issue Tracker (Source = Report)
A15: 11 | B15: Luonkos-audit-------- Not Final.docx | C15: docx | D15: Luonkos Finland (.fi) | E15: 46282 | F15: Draft long-form audit + duplication assessment | G15: - | H15: Draft - superseded by 'Luonkos - Audit & Analysis'
A16: 12 | B16: Luonkos_Merge_404_Report.docx | C16: docx | D16: Luonkos Finland (.fi) | E16: 46288 | F16: Post-merge 404s on EN/SV URLs, hreflang, redirect map | G16: Issue Tracker (Source = Report)
A17: 13 | B17: Bodyotics Analysis.docx | C17: docx | D17: Bodyotics | E17: 46287 | F17: Wrong-language URLs ranking in DE / NL / FR | G17: Issue Tracker (Source = Report)
A18: 14 | B18: https_luxsports.co_.docx | C18: docx | D18: Luxsports (LUX) | E18: 46302 | F18: 9 technical/international SEO issues | G18: Issue Tracker (Source = Report)
A19: 15 | B19: Babysunnies.com _ Technical SEO Audit(1).docx | C19: docx | D19: Babysunnies | E19: 46304 | F19: 10 technical SEO issues | G19: Issue Tracker (Source = Report) | H19: Version used in tracker (states 120 dead URLs)
A20: 16 | B20: Babysunnies.com _ Technical SEO Audit.docx | C20: docx | D20: Babysunnies | E20: 46304 | F20: Same audit, alternate version | G20: - | H20: Duplicate version - consolidate
A21: 17 | B21: babysunnies.com Technical SEO Audit--.docx | C21: docx | D21: Babysunnies | E21: 46304 | F21: Same audit, alternate version | G21: - | H21: Duplicate version - consolidate
A22: 18 | B22: coachsoak.com - SEO Audit & Analysis Report.docx | C22: docx | D22: Coachsoak | E22: 46303 | F22: 13 GSC / on-page / technical issues | G22: Issue Tracker (Source = Report)
A23: 19 | B23: Untitled spreadsheet.xlsx | C23: xlsx | D23: - | E23: 46275 | F23: Empty sheet | G23: - | H23: Empty - can be deleted
A24: 20 | B24: Coach/ (folder) | C24: folder | D24: Coachsoak | F24: Empty folder | G24: - | H24: Empty

Sheet BBB_Master Checklist
A1: Project Name - Bigbatbox | E1: =HYPERLINK("#'Master Overview'!A1","<< Master Overview") -> << Master Overview
A2: Website URL - https://www.bigbatbox.com/ | E2: Source: Bigbatbox - Site Audit.xlsx / Master Checklist
A3: Task - SEO Audit
A7: S.No | B7: Issues | C7: Status
A8: 1 | B8: Broken Links | C8: Need to Fix
A9: 2 | B9: Broken Internal Links | C9: Need to Fix
A10: 3 | B10: Pages Marked No Index | C10: Need to Fix
A11: 4 | B11: URLs Not Submitted to Index Now | C11: Need to Fix
A12: 5 | B12: Page has links to broken page | C12: Need to Fix
A13: 6 | B13: Redirecting URLs | C13: Need to Fix
A14: 7 | B14: Too Long Meta Title | C14: Need to Fix
A15: 8 | B15: Too Long Meta Description | C15: Need to Fix
A16: 9 | B16: Missing H1 Tag | C16: Need to Fix
A17: 10 | B17: Missing Meta Description | C17: Need to Fix
A18: 11 | B18: Multiple H1 Tag | C18: Need to Fix
A19: 12 | B19: Page and SERP titles do not match | C19: Need to Fix
... A22: 15 | B22: Images Missing ALT text | C22: Need to Fix

Sheet BBB_Broken Links
A1: S.No | B1: URL | D1: =HYPERLINK("#'Master Overview'!A1","<< Master Overview") -> << Master Overview
A2: 1 | B2: https://www.bigbatbox.com/blogs/all-about-bats/big-bat-box-comparison | D2: Source: Bigbatbox - Site Audit.xlsx / Broken Links
A3: 2 | B3: https://www.bigbatbox.com/blogs/all-about-bees/how-to-maintain-your-bee-house-through-the-seasons
A4: 3 | B4: https://www.bigbatbox.com/blogs/all-about-bats/14-fascinating-facts-about-bats
A5: 4 | B5: https://www.bigbatbox.com/blogs/all-about-bats/the-surprising-benefits-of-bat-boxes-and-why-you-should-have-one
A6: 5 | B6: https://www.bigbatbox.com/blogs/news/introducing-the-wildyard-x-angry-birds%E2%84%A2-collection-turn-your-garden-into-a-wildlife-habitat
A7: 6 | B7: https://www.bigbatbox.com/it/products/bee-house-big-bee-box
A8: 7 | B8: https://www.bigbatbox.com/collections/3-chamber-bat-houses
A9: 8 | B9: https://www.bigbatbox.com/products/bee-house-big-bee-box
A10: 9 | B10: https://www.bigbatbox.com/en-ca/products/bee-house-big-bee-box
A11: 10 | B11: https://www.bigbatbox.com/fr/collections/3-chamber-bat-houses
A12: 11 | B12: https://www.bigbatbox.com/es/products/big-bat-barn-certified-bat-house
A13: 12 | B13: https://www.bigbatbox.com/de/blogs/all-about-bats/how-to-attract-bats-to-your-backyard
A14: 13 | B14: https://www.bigbatbox.com/en-ca/collections/3-chamber-bat-houses
... A32: 31 | B32: https://www.bigbatbox.com/de/collections/3-chamber-bat-houses

Sheet BBB_Broken Internal Link
A1: S.No | B1: URL | C1: Broken Internal Link | E1: =HYPERLINK("#'Master Overview'!A1","<< Master Overview") -> << Master Overview
A2: 1 | B2: https://www.bigbatbox.com/de/blogs/habitat-of-bats/some-interesting-busted-myths-and-facts-about-bats | C2: https://www.bigbatbox.com/blogs/all-about-bats/big-bat-box-comparison | E2: Source: Bigbatbox - Site Audit.xlsx / Broken Internal Link
A3: 2 | B3: https://www.bigbatbox.com/de/blogs/bee-species/bee-wise-how-bee-houses-and-hotels-can-help-save-bees-the-environment | C3: https://www.bigbatbox.com/blogs/all-about-bees/how-to-maintain-your-bee-house-through-the-seasons
A4: 3 | B4: https://www.bigbatbox.com/de/blogs/habitat-of-bats/9-fantastic-bat-facts-you-need-to-know | C4: https://www.bigbatbox.com/blogs/all-about-bats/14-fascinating-facts-about-bats
A5: 4 | B5: https://www.bigbatbox.com/de/blogs/habitat-of-bats/eco-friendly-bat-house-for-backyard-the-complete-guide | C5: https://www.bigbatbox.com/blogs/all-about-bats/the-surprising-benefits-of-bat-boxes-and-why-you-should-have-one
A6: 5 | B6: https://www.bigbatbox.com/products/angry-birds-wildyard-diy-birdhouse-kit | C6: https://www.bigbatbox.com/blogs/news/introducing-the-wildyard-x-angry-birds%E2%84%A2-collection-turn-your-garden-into-a-wildlife-habitat
A7: 6 | B7: https://www.bigbatbox.com/it/blogs/habitat-of-bats/bat-box-casetta-pipistrelli-guida | C7: https://www.bigbatbox.com/it/products/bee-house-big-bee-box
A8: 7 | B8: https://www.bigbatbox.com/blogs/habitat-of-bats/how-to-hang-a-bat-house-complete-guide | C8: https://www.bigbatbox.com/collections/3-chamber-bat-houses
A9: 8 | B9: https://www.bigbatbox.com/blogs/habitat-of-bats/how-to-hang-a-bat-house-complete-guide | C9: https://www.bigbatbox.com/products/bee-house-big-bee-box
A10: 9 | B10: https://www.bigbatbox.com/en-ca/blogs/habitat-of-bats/how-to-hang-a-bat-house-complete-guide | C10: https://www.bigbatbox.com/en-ca/products/bee-house-big-bee-box
A11: 10 | B11: https://www.bigbatbox.com/fr/blogs/habitat-of-bats/nichoir-chauve-souris-guide-installation | C11: https://www.bigbatbox.com/fr/collections/3-chamber-bat-houses
A12: 11 | B12: https://www.bigbatbox.com/es/blogs/habitat-of-bats/how-to-hang-a-bat-house-complete-guide | C12: https://www.bigbatbox.com/es/products/big-bat-barn-certified-bat-house
A13: 12 | B13: https://www.bigbatbox.com/de/blogs/habitat-of-bats/the-definitive-guide-to-backyard-mosquito-control | C13: https://www.bigbatbox.com/de/blogs/all-about-bats/how-to-attract-bats-to-your-backyard
A14: 13 | B14: https://www.bigbatbox.com/en-ca/blogs/habitat-of-bats/how-to-hang-a-bat-house-complete-guide | C14: https://www.bigbatbox.com/en-ca/collections/3-chamber-bat-houses
... A32: 31 | B32: https://www.bigbatbox.com/de/blogs/habitat-of-bats/fledermauskasten-aufhaengen-leitfaden | C32: https://www.bigbatbox.com/de/collections/3-chamber-bat-houses

Sheet BBB_Pages Marked No Index
A1: S.No | B1: URL | D1: =HYPERLINK("#'Master Overview'!A1","<< Master Overview") -> << Master Overview
A2: 1 | B2: https://www.bigbatbox.com/products/discreet-packaging | D2: Source: Bigbatbox - Site Audit.xlsx / Pages Marked No Index
A3: 2 | B3: https://www.bigbatbox.com/de/products/discreet-packaging
A4: 3 | B4: https://www.bigbatbox.com/fr/products/discreet-packaging
A5: 4 | B5: https://www.bigbatbox.com/it/products/discreet-packaging
A6: 5 | B6: https://www.bigbatbox.com/es/products/discreet-packaging

Sheet BBB_Not submitted to IndexNow
A1: S.No | B1: URL | D1: =HYPERLINK("#'Master Overview'!A1","<< Master Overview") -> << Master Overview
A2: 1 | B2: https://www.bigbatbox.com/en-ca | D2: Source: Bigbatbox - Site Audit.xlsx / Not submitted to IndexNow
A3: 2 | B3: https://www.bigbatbox.com/en-ca/products/squirrel-house-hideout-feeder
A4: 3 | B4: https://www.bigbatbox.com/en-ca/products/squirrel-feeder
A5: 4 | B5: https://www.bigbatbox.com/en-ca/products/owl-box
A6: 5 | B6: https://www.bigbatbox.com/en-ca/cart
A7: 6 | B7: https://www.bigbatbox.com/de/search
A8: 7 | B8: https://www.bigbatbox.com/it/blogs/wildyard-learn
A9: 8 | B9: https://www.bigbatbox.com/fr/products/squirrel-feeder
A10: 9 | B10: https://www.bigbatbox.com/en-ca/collections/angry-birds-x-wildyard-birdhouses
A11: 10 | B11: https://www.bigbatbox.com/fr/pages/warranty-registration
A12: 11 | B12: https://www.bigbatbox.com/it/pages/work-with-us
A13: 12 | B13: https://www.bigbatbox.com/fr/products/owl-box
A14: 13 | B14: https://www.bigbatbox.com/es/cart
... A2111: 2110 | B2111: https://www.bigbatbox.com/fr/blogs/fun-facts-about-owls/tagged/ecological-balance

Sheet BBB_Page has links to broken pa
A1: S.No | B1: URL | C1: Internal outlinks to 4xx | E1: =HYPERLINK("#'Master Overview'!A1","<< Master Overview") -> << Master Overview
A2: 1 | B2: https://www.bigbatbox.com/products/angry-birds-wildyard-diy-birdhouse-kit | C2: https://www.bigbatbox.com/blogs/news/introducing-the-wildyard-x-angry-birds%E2%84%A2-collection-turn-your-garden-into-a-wildlife-habitat | E2: Source: Bigbatbox - Site Audit.xlsx / Page has links to broken page
A3: 2 | B3: https://www.bigbatbox.com/products/angry-birds-wildyard-flowerpot-birdhouse | C3: https://www.bigbatbox.com/blogs/news/introducing-the-wildyard-x-angry-birds%E2%84%A2-collection-turn-your-garden-into-a-wildlife-habitat
A4: 3 | B4: https://www.bigbatbox.com/es/products/angry-birds-wildyard-diy-birdhouse-kit | C4: https://www.bigbatbox.com/es/blogs/news/introducing-the-wildyard-x-angry-birds%E2%84%A2-collection-turn-your-garden-into-a-wildlife-habitat
A5: 4 | B5: https://www.bigbatbox.com/es/products/angry-birds-wildyard-flowerpot-birdhouse | C5: https://www.bigbatbox.com/es/blogs/news/introducing-the-wildyard-x-angry-birds%E2%84%A2-collection-turn-your-garden-into-a-wildlife-habitat
A6: 5 | B6: https://www.bigbatbox.com/fr/products/angry-birds-wildyard-diy-birdhouse-kit | C6: https://www.bigbatbox.com/fr/blogs/news/introducing-the-wildyard-x-angry-birds%E2%84%A2-collection-turn-your-garden-into-a-wildlife-habitat
A7: 6 | B7: https://www.bigbatbox.com/de/products/angry-birds-wildyard-diy-birdhouse-kit | C7: https://www.bigbatbox.com/de/blogs/news/introducing-the-wildyard-x-angry-birds%E2%84%A2-collection-turn-your-garden-into-a-wildlife-habitat
A8: 7 | B8: https://www.bigbatbox.com/it/products/angry-birds-wildyard-flowerpot-birdhouse | C8: https://www.bigbatbox.com/it/blogs/news/introducing-the-wildyard-x-angry-birds%E2%84%A2-collection-turn-your-garden-into-a-wildlife-habitat
A9: 8 | B9: https://www.bigbatbox.com/it/products/angry-birds-wildyard-diy-birdhouse-kit | C9: https://www.bigbatbox.com/it/blogs/news/introducing-the-wildyard-x-angry-birds%E2%84%A2-collection-turn-your-garden-into-a-wildlife-habitat
A10: 9 | B10: https://www.bigbatbox.com/fr/products/angry-birds-wildyard-flowerpot-birdhouse | C10: https://www.bigbatbox.com/fr/blogs/news/introducing-the-wildyard-x-angry-birds%E2%84%A2-collection-turn-your-garden-into-a-wildlife-habitat
A11: 10 | B11: https://www.bigbatbox.com/en-ca/products/angry-birds-wildyard-flowerpot-birdhouse | C11: https://www.bigbatbox.com/en-ca/blogs/news/introducing-the-wildyard-x-angry-birds%E2%84%A2-collection-turn-your-garden-into-a-wildlife-habitat
A12: 11 | B12: https://www.bigbatbox.com/de/products/angry-birds-wildyard-flowerpot-birdhouse | C12: https://www.bigbatbox.com/de/blogs/news/introducing-the-wildyard-x-angry-birds%E2%84%A2-collection-turn-your-garden-into-a-wildlife-habitat
A13: 12 | B13: https://www.bigbatbox.com/en-ca/products/angry-birds-wildyard-diy-birdhouse-kit | C13: https://www.bigbatbox.com/en-ca/blogs/news/introducing-the-wildyard-x-angry-birds%E2%84%A2-collection-turn-your-garden-into-a-wildlife-habitat
A14: 13 | B14: https://www.bigbatbox.com/blogs/habitat-of-bats/how-to-hang-a-bat-house-complete-guide | C14: https://www.bigbatbox.com/collections/3-chamber-bat-houses https://www.bigbatbox.com/products/bee-house-big-bee-box https://www.bigbatbox.com/products/big-bat-barn-certified-bat-house
... A28: 27 | B28: https://www.bigbatbox.com/it/blogs/habitat-of-bats/bat-box-casetta-pipistrelli-guida | C28: https://www.bigbatbox.com/it/collections/3-chamber-bat-houses https://www.bigbatbox.com/it/products/bee-house-big-bee-box https://www.bigbatbox.com/it/products/big-bat-barn-certified-bat-house

Sheet BBB_Redirecting URLs
A1: S.No | B1: URL | C1: Internal outlinks to 3xx | D1: Internal outlinks codes (3xx) | F1: =HYPERLINK("#'Master Overview'!A1","<< Master Overview") -> << Master Overview
A2: 1 | B2: https://www.bigbatbox.com/products/discreet-packaging | C2: https://www.bigbatbox.com/customer_authentication/redirect?locale=en&region_country=US | D2: 302 | F2: Source: Bigbatbox - Site Audit.xlsx / Redirecting URLs
A3: 2 | B3: https://www.bigbatbox.com/collections/ | C3: https://www.bigbatbox.com/customer_authentication/redirect?locale=en&region_country=US | D3: 302
A4: 3 | B4: https://www.bigbatbox.com/es/blogs/bee-species?page=1 | C4: https://www.bigbatbox.com/customer_authentication/redirect?locale=es&region_country=US https://www.bigbatbox.com/es/account | D4: 302 302
A5: 4 | B5: https://www.bigbatbox.com/blogs/fun-facts-about-owls?page=1 | C5: https://www.bigbatbox.com/customer_authentication/redirect?locale=en&region_country=US | D5: 302
A6: 5 | B6: https://www.bigbatbox.com/fr/blogs/bee-species?page=1 | C6: https://www.bigbatbox.com/customer_authentication/redirect?locale=fr&region_country=US https://www.bigbatbox.com/fr/account | D6: 302 302
A7: 6 | B7: https://www.bigbatbox.com/en-ca/blogs/bee-species?page=1 | C7: https://www.bigbatbox.com/customer_authentication/redirect?locale=en&region_country=CA https://www.bigbatbox.com/en-ca/account | D7: 302 302
A8: 7 | B8: https://www.bigbatbox.com/en-ca/blogs/fun-facts-about-owls?page=1 | C8: https://www.bigbatbox.com/customer_authentication/redirect?locale=en&region_country=CA https://www.bigbatbox.com/en-ca/account | D8: 302 302
A9: 8 | B9: https://www.bigbatbox.com/de/products/discreet-packaging | C9: https://www.bigbatbox.com/customer_authentication/redirect?locale=de&region_country=US https://www.bigbatbox.com/de/account https://www.bigbatbox.com/de/products/owl-box | D9: 302 302 301
A10: 9 | B10: https://www.bigbatbox.com/fr/products/discreet-packaging | C10: https://www.bigbatbox.com/customer_authentication/redirect?locale=fr&region_country=US https://www.bigbatbox.com/fr/account | D10: 302 302
A11: 10 | B11: https://www.bigbatbox.com/blogs/habitat-of-bats?page=1 | C11: https://www.bigbatbox.com/customer_authentication/redirect?locale=en&region_country=US | D11: 302
A12: 11 | B12: https://www.bigbatbox.com/fr/blogs/habitat-of-bats?page=1 | C12: https://www.bigbatbox.com/customer_authentication/redirect?locale=fr&region_country=US https://www.bigbatbox.com/fr/account https://www.bigbatbox.com/fr/blogs/habitat-of-bats/how-to-attract-bats-to-a-bat-house https://www.bigbatbox.com/fr/blogs/habitat-of-bats/how-to-hang-a-bat-house-complete-guide | D12: 302 302 301 301
A13: 12 | B13: https://www.bigbatbox.com/blogs/fun-facts-about-owls/owl-nesting-boxes-providing-safe-havens-for-nighttime-raptors?_pos=1&_ss=r | C13: https://www.bigbatbox.com/customer_authentication/redirect?locale=en&region_country=US | D13: 302
A14: 13 | B14: https://www.bigbatbox.com/blogs/habitat-of-bats/the-night-guardians-the-importance-of-bats-to-our-world?_pos=1&_ss=r | C14: https://www.bigbatbox.com/collections/shop-our-bat-houses https://www.bigbatbox.com/customer_authentication/redirect?locale=en&region_country=US | D14: 301 302
A15: 14 | B15: https://www.bigbatbox.com/de/blogs/fun-facts-about-owls?page=1 | C15: https://www.bigbatbox.com/customer_authentication/redirect?locale=de&region_country=US https://www.bigbatbox.com/de/account https://www.bigbatbox.com/de/products/owl-box | D15: 302 302 301
A16: 15 | B16: https://www.bigbatbox.com/es/blogs/habitat-of-bats?page=1 | C16: https://www.bigbatbox.com/customer_authentication/redirect?locale=es&region_country=US https://www.bigbatbox.com/es/account https://www.bigbatbox.com/es/blogs/habitat-of-bats/how-to-attract-bats-to-a-bat-house | D16: 302 302 301
A17: 16 | B17: https://www.bigbatbox.com/it/blogs/fun-facts-about-owls?page=1 | C17: https://www.bigbatbox.com/customer_authentication/redirect?locale=it&region_country=US https://www.bigbatbox.com/it/account | D17: 302 302
A18: 17 | B18: https://www.bigbatbox.com/it/blogs/habitat-of-bats?page=1 | C18: https://www.bigbatbox.com/customer_authentication/redirect?locale=it&region_country=US https://www.bigbatbox.com/it/account https://www.bigbatbox.com/it/blogs/habitat-of-bats/how-to-attract-bats-to-a-bat-house https://www.bigbatbox.com/it/blogs/habitat-of-bats/how-to-hang-a-bat-house-complete-guide | D18: 302 302 301 301
A19: 18 | B19: https://www.bigbatbox.com/it/products/discreet-packaging | C19: https://www.bigbatbox.com/customer_authentication/redirect?locale=it&region_country=US https://www.bigbatbox.com/it/account | D19: 302 302
A20: 19 | B20: https://www.bigbatbox.com/fr/blogs/fun-facts-about-owls?page=1 | C20: https://www.bigbatbox.com/customer_authentication/redirect?locale=fr&region_country=US https://www.bigbatbox.com/fr/account | D20: 302 302
A21: 20 | B21: https://www.bigbatbox.com/es/blogs/fun-facts-about-owls?page=1 | C21: https://www.bigbatbox.com/customer_authentication/redirect?locale=es&region_country=US https://www.bigbatbox.com/es/account | D21: 302 302
A22: 21 | B22: https://www.bigbatbox.com/it/blogs/bee-species?page=1 | C22: https://www.bigbatbox.com/customer_authentication/redirect?locale=it&region_country=US https://www.bigbatbox.com/it/account | D22: 302 302
A23: 22 | B23: https://www.bigbatbox.com/blogs/habitat-of-bats/a-brief-guide-to-building-and-installing-bat-boxes?_pos=5&_ss=r | C23: https://www.bigbatbox.com/customer_authentication/redirect?locale=en&region_country=US | D23: 302
A24: 23 | B24: https://www.bigbatbox.com/en-ca/blogs/habitat-of-bats?page=1 | C24: https://www.bigbatbox.com/customer_authentication/redirect?locale=en&region_country=CA https://www.bigbatbox.com/en-ca/account | D24: 302 302
A25: 24 | B25: https://www.bigbatbox.com/blogs/habitat-of-bats/5-best-tips-for-bat-house-maintenance?_pos=16&_ss=r | C25: https://www.bigbatbox.com/collections/shop-our-bat-houses https://www.bigbatbox.com/customer_authentication/redirect?locale=en&region_country=US | D25: 301 302
A26: 25 | B26: https://www.bigbatbox.com/de/blogs/bee-species?page=1 | C26: https://www.bigbatbox.com/customer_authentication/redirect?locale=de&region_country=US https://www.bigbatbox.com/de/account https://www.bigbatbox.com/de/products/owl-box | D26: 302 302 301
A27: 26 | B27: https://www.bigbatbox.com/blogs/bee-species?page=1 | C27: https://www.bigbatbox.com/customer_authentication/redirect?locale=en&region_country=US | D27: 302
A28: 27 | B28: https://www.bigbatbox.com/blogs/habitat-of-bats/how-to-get-bats-in-a-bat-house?_pos=1&_ss=r | C28: https://www.bigbatbox.com/customer_authentication/redirect?locale=en&region_country=US https://www.bigbatbox.com/products/big-bat-box | D28: 302 301
A29: 28 | B29: https://www.bigbatbox.com/es/products/discreet-packaging | C29: https://www.bigbatbox.com/customer_authentication/redirect?locale=es&region_country=US https://www.bigbatbox.com/es/account | D29: 302 302
A30: 29 | B30: https://www.bigbatbox.com/blogs/fun-facts-about-owls/the-silent-hunters-why-owl-boxes-and-bat-boxes-shouldnt-mix?_pos=1&_ss=r | C30: https://www.bigbatbox.com/collections/shop-our-bat-houses https://www.bigbatbox.com/customer_authentication/redirect?locale=en&region_country=US https://www.bigbatbox.com/products/owl-house | D30: 301 302 301
A31: 30 | B31: https://www.bigbatbox.com/products/squirrel-house-hideout-feeder?view=squirrel-house | C31: https://www.bigbatbox.com/customer_authentication/redirect?locale=en&region_country=US | D31: 302
A32: 31 | B32: https://www.bigbatbox.com/blogs/habitat-of-bats/how-to-attract-bats-your-go-to-guide?_pos=1&_ss=r | C32: https://www.bigbatbox.com/collections/bat-house-kits https://www.bigbatbox.com/customer_authentication/redirect?locale=en&region_country=US | D32: 301 302
A33: 32 | B33: https://www.bigbatbox.com/de/blogs/habitat-of-bats?page=1 | C33: https://www.bigbatbox.com/customer_authentication/redirect?locale=de&region_country=US https://www.bigbatbox.com/de/account https://www.bigbatbox.com/de/blogs/habitat-of-bats/how-to-attract-bats-to-a-bat-house https://www.bigbatbox.com/de/blogs/habitat-of-bats/how-to-hang-a-bat-house-complete-guide https://www.bigbatbox.com/de/products/owl-box | D33: 302 302 301 301 301

Sheet BBB_Too Long Meta Title
A1: S.No | B1: URL | C1: Title | D1: Title length | F1: =HYPERLINK("#'Master Overview'!A1","<< Master Overview") -> << Master Overview
A2: 1 | B2: https://www.bigbatbox.com/pages/faq | C2: Wildyard FAQ — Box Installation, Mounting & Care | Wildyard – Big Bat Box | D2: 73 | F2: Source: Bigbatbox - Site Audit.xlsx / Too Long Meta Title
A3: 2 | B3: https://www.bigbatbox.com/blogs/fun-facts-about-owls | C3: Fun Facts About Owls: Their Mysteries and Habits Unveiled – Big Bat Box | D3: 71
A4: 3 | B4: https://www.bigbatbox.com/products/angry-birds-wildyard-diy-birdhouse-kit | C4: WildYard X Angry Birds™ DIY Birdhouse Kit – Build & Paint | Big Bat Box | D4: 71
A5: 4 | B5: https://www.bigbatbox.com/products/squirrel-house-hideout-feeder | C5: Squirrel House - Hideout & Feeder Cedar Outdoor Nesting Box – Big Bat Box | D5: 73
A6: 5 | B6: https://www.bigbatbox.com/pages/1-for-the-planet | C6: Wildyard x 1% for the Planet I Giving Back to Protect Wildlife & Earth – Big Bat Box | D6: 84
A7: 6 | B7: https://www.bigbatbox.com/en-ca/products/squirrel-house-hideout-feeder | C7: Squirrel House - Hideout & Feeder Cedar Outdoor Nesting Box – Big Bat Box | D7: 73
A8: 7 | B8: https://www.bigbatbox.com/es/products/angry-birds-wildyard-diy-birdhouse-kit | C8: WildYard X Angry Birds™ DIY Birdhouse Kit – Build & Paint | Big Bat Box | D8: 71
A9: 8 | B9: https://www.bigbatbox.com/fr/blogs/fun-facts-about-owls | C9: Fun Facts About Owls: Their Mysteries and Habits Unveiled – Big Bat Box | D9: 71
A10: 9 | B10: https://www.bigbatbox.com/es/blogs/fun-facts-about-owls | C10: Fun Facts About Owls: Their Mysteries and Habits Unveiled – Big Bat Box | D10: 71
A11: 10 | B11: https://www.bigbatbox.com/es/products/squirrel-house-hideout-feeder | C11: Squirrel House - Hideout & Feeder Cedar Outdoor Nesting Box – Big Bat Box | D11: 73
A12: 11 | B12: https://www.bigbatbox.com/de/pages/1-for-the-planet | C12: Wildyard x 1 % für den Planeten I Wir geben etwas zurück, um die Tierwelt und die Erde zu schützen – Big Bat Box | D12: 112
A13: 12 | B13: https://www.bigbatbox.com/fr/pages/1-for-the-planet | C13: Wildyard x 1% for the Planet I Giving Back to Protect Wildlife & Earth – Big Bat Box | D13: 84
A14: 13 | B14: https://www.bigbatbox.com/fr/products/angry-birds-wildyard-diy-birdhouse-kit | C14: WildYard X Angry Birds™ DIY Birdhouse Kit – Build & Paint | Big Bat Box | D14: 71
... A1747: 1746 | B1747: https://www.bigbatbox.com/fr/blogs/fun-facts-about-owls/tagged/ecological-balance | C1747: Fun Facts About Owls: Their Mysteries and Habits Unveiled – Étiqueter "ecological balance" – Big Bat Box | D1747: 104

Sheet BBB_Too Long Meta Description
A1: S.No | B1: URL | C1: Title | D1: Meta description | E1: Meta description length | G1: =HYPERLINK("#'Master Overview'!A1","<< Master Overview") -> << Master Overview
A2: 1 | B2: https://www.bigbatbox.com/ | C2: Bat Houses, Owl Boxes & Bee Hotels | Big Bat Box | D2: Shop Big Bat Box for premium cedar bat houses, owl boxes, and bee hotels. Eco-friendly, handcrafted by WildYard — built to attract wildlife and control pests naturally. | E2: 168 | G2: Source: Bigbatbox - Site Audit.xlsx / Too Long Meta Description
A3: 2 | B3: https://www.bigbatbox.com/products/owl-box | C3: Owl Box — Cedar Owl House for Screech & Saw-Whet Owls | Big Bat Box | D3: Attract Eastern Screech Owls, Saw-Whet & Boreal Owls naturally. Handcrafted cedar owl box, easy to mount, built for real backyard wildlife. Ships to US & Canada. | E3: 161
A4: 3 | B4: https://www.bigbatbox.com/pages/faq | C4: Wildyard FAQ — Box Installation, Mounting & Care | Wildyard – Big Bat Box | D4: Find answers to questions about the bat box, owl box, and bee box. Learn installation tips, maintenance advice, wildlife benefits, shipping, returns, and more from Wildyard. | E4: 173
A5: 4 | B5: https://www.bigbatbox.com/products/double-chamber-bat-house-black | C5: Two Chamber Black Bat House — Holds 75 Bats | Big Bat Box | D5: Black cedar two-chamber bat house holds up to 75 bats. Heat-retentive design ideal for cooler climates — natural pest control for your backyard. Shop Big Bat Box. | E5: 162
A6: 5 | B6: https://www.bigbatbox.com/products/bat-house-single-chamber-black | C6: Single Chamber Black Bat House — Holds 50 Bats | Big Bat Box | D6: Cedar black bat house holds up to 50 bats. Weather-resistant, heat-retentive, and eco-friendly — ideal for natural mosquito control in any backyard. By Big Bat Box. | E6: 164
A7: 6 | B7: https://www.bigbatbox.com/pages/collab | C7: Collabs – Big Bat Box | D7: Shop Big Bat Box for premium cedar bat houses, owl boxes, and bee hotels. Eco-friendly, handcrafted by WildYard — built to attract wildlife and control pests naturally. | E7: 168
A8: 7 | B8: https://www.bigbatbox.com/en-ca | C8: Bat Houses, Owl Boxes & Bee Hotels | Big Bat Box | D8: Shop Big Bat Box for premium cedar bat houses, owl boxes, and bee hotels. Eco-friendly, handcrafted by WildYard — built to attract wildlife and control pests naturally. | E8: 168
A9: 8 | B9: https://www.bigbatbox.com/en-ca/products/owl-box | C9: Owl Box — Cedar Owl House for Screech & Saw-Whet Owls | Big Bat Box | D9: Attract Eastern Screech Owls, Saw-Whet & Boreal Owls naturally. Handcrafted cedar owl box, easy to mount, built for real backyard wildlife. Ships to US & Canada. | E9: 161
A10: 9 | B10: https://www.bigbatbox.com/en-ca/cart | C10: Your Shopping Cart – Big Bat Box | D10: Shop Big Bat Box for premium cedar bat houses, owl boxes, and bee hotels. Eco-friendly, handcrafted by WildYard — built to attract wildlife and control pests naturally. | E10: 168
A11: 10 | B11: https://www.bigbatbox.com/de/search | C11: Suche – Big Bat Box | D11: Shop Big Bat Box for premium cedar bat houses, owl boxes, and bee hotels. Eco-friendly, handcrafted by WildYard — built to attract wildlife and control pests naturally. | E11: 168
A12: 11 | B12: https://www.bigbatbox.com/de/blogs/wildyard-learn | C12: Blog - Große Fledermausbox – Big Bat Box | D12: In unserem Blog haben wir alle wichtigen Informationen rund um Fledermäuse und Fledermaushäuser zusammengestellt – von den Vorteilen bis zur Installation. Lesen Sie unsere Artikel! | E12: 180
A13: 12 | B13: https://www.bigbatbox.com/es/products/owl-box | C13: Owl Box — Cedar Owl House for Screech & Saw-Whet Owls | Big Bat Box | D13: Attract Eastern Screech Owls, Saw-Whet & Boreal Owls naturally. Handcrafted cedar owl box, easy to mount, built for real backyard wildlife. Ships to US & Canada. | E13: 161
A14: 13 | B14: https://www.bigbatbox.com/fr/products/owl-box | C14: Owl Box — Cedar Owl House for Screech & Saw-Whet Owls | Big Bat Box | D14: Attract Eastern Screech Owls, Saw-Whet & Boreal Owls naturally. Handcrafted cedar owl box, easy to mount, built for real backyard wildlife. Ships to US & Canada. | E14: 161
... A193: 192 | B193: https://www.bigbatbox.com/en-ca/blogs/conservation-partners/tagged/1-for-the-planet | C193: Conservation & Partners: WildYard & 1% For The Planet – Tagged "1% for the Planet" – Big Bat Box | D193: Shop Big Bat Box for premium cedar bat houses, owl boxes, and bee hotels. Eco-friendly, handcrafted by WildYard — built to attract wildlife and control pests naturally. | E193: 168

Sheet BBB_Missing H1 Tag
A1: S.No | B1: URL | D1: =HYPERLINK("#'Master Overview'!A1","<< Master Overview") -> << Master Overview
A2: 1 | B2: https://www.bigbatbox.com/products/owl-box | D2: Source: Bigbatbox - Site Audit.xlsx / Missing H1 Tag
A3: 2 | B3: https://www.bigbatbox.com/pages/faq
A4: 3 | B4: https://www.bigbatbox.com/pages/1-for-the-planet
A5: 4 | B5: https://www.bigbatbox.com/pages/become-a-reseller
A6: 5 | B6: https://www.bigbatbox.com/en-ca/products/owl-box
A7: 6 | B7: https://www.bigbatbox.com/de/search
A8: 7 | B8: https://www.bigbatbox.com/es/products/owl-box
A9: 8 | B9: https://www.bigbatbox.com/fr/products/owl-box
A10: 9 | B10: https://www.bigbatbox.com/de/pages/1-for-the-planet
A11: 10 | B11: https://www.bigbatbox.com/es/pages/become-a-reseller
A12: 11 | B12: https://www.bigbatbox.com/fr/search
A13: 12 | B13: https://www.bigbatbox.com/de/pages/become-a-reseller
A14: 13 | B14: https://www.bigbatbox.com/it/products/owl-box
... A109: 108 | B109: https://www.bigbatbox.com/es/pages/1-for-the-planet-merlin-tuttle-x-wild-yard

Sheet BBB_Missing Meta Description
A1: S.No | B1: URL | D1: =HYPERLINK("#'Master Overview'!A1","<< Master Overview") -> << Master Overview
A2: 1 | B2: https://www.bigbatbox.com/products/certified-triple-chamber-bat-house-black | D2: Source: Bigbatbox - Site Audit.xlsx / Missing Meta Description
A3: 2 | B3: https://www.bigbatbox.com/en-ca/products/certified-triple-chamber-bat-house-black
A4: 3 | B4: https://www.bigbatbox.com/de/products/dreikammer-fledermaushaus
A5: 4 | B5: https://www.bigbatbox.com/es/products/certified-triple-chamber-bat-house-black
A6: 5 | B6: https://www.bigbatbox.com/fr/products/certified-triple-chamber-bat-house-black
A7: 6 | B7: https://www.bigbatbox.com/it/products/certified-triple-chamber-bat-house-black

Sheet BBB_Multiple H1 Tag
A1: S.No | B1: URL | C1: No. of H1 | E1: =HYPERLINK("#'Master Overview'!A1","<< Master Overview") -> << Master Overview
A2: 1 | B2: https://www.bigbatbox.com/ | C2: 2 | E2: Source: Bigbatbox - Site Audit.xlsx / Multiple H1 Tag
A3: 2 | B3: https://www.bigbatbox.com/pages/guide | C3: 2
A4: 3 | B4: https://www.bigbatbox.com/en-ca | C4: 2
A5: 4 | B5: https://www.bigbatbox.com/en-ca/cart | C5: 2
A6: 5 | B6: https://www.bigbatbox.com/es/cart | C6: 2
A7: 6 | B7: https://www.bigbatbox.com/it | C7: 2
A8: 7 | B8: https://www.bigbatbox.com/fr | C8: 2
A9: 8 | B9: https://www.bigbatbox.com/es | C9: 2
A10: 9 | B10: https://www.bigbatbox.com/it/pages/guide | C10: 2
A11: 10 | B11: https://www.bigbatbox.com/fr/cart | C11: 2
A12: 11 | B12: https://www.bigbatbox.com/de | C12: 3
A13: 12 | B13: https://www.bigbatbox.com/de/blogs/bee-species | C13: 2
A14: 13 | B14: https://www.bigbatbox.com/de/blogs/habitat-of-bats | C14: 2
... A291: 290 | B291: https://www.bigbatbox.com/de/blogs/habitat-of-bats/tagged/usa-bat-house-guide | C291: 2

Sheet BBB_Page and SERP titles do not
A1: S.No | B1: URL | C1: Title | D1: SERP title | F1: =HYPERLINK("#'Master Overview'!A1","<< Master Overview") -> << Master Overview
A2: 1 | B2: https://www.bigbatbox.com/ | C2: Bat Houses, Owl Boxes & Bee Hotels | Big Bat Box | D2: Big Bat Box: Bat Houses, Owl Boxes & Bee Hotels | F2: Source: Bigbatbox - Site Audit.xlsx / Page and SERP titles do not mat
A3: 2 | B3: https://www.bigbatbox.com/products/bee-house | C3: Bee House — Bamboo Pollinator Hotel for Gardens | Big Bat Box | D3: Bee House — Bamboo Pollinator Hotel for Gardens
A4: 3 | B4: https://www.bigbatbox.com/products/owl-box | C4: Owl Box — Cedar Owl House for Screech & Saw-Whet Owls | Big Bat Box | D4: Owl Box — Cedar Owl House for Screech & Saw-Whet Owls
A5: 4 | B5: https://www.bigbatbox.com/products/big-bat-barn | C5: Big Bat Barn Brown — 3-Chamber Cedar Bat House, 150 Bats | Big Bat Box | D5: Big Bat Barn Brown — 3-Chamber Cedar Bat House, 150 ...
A6: 5 | B6: https://www.bigbatbox.com/blogs/habitat-of-bats | C6: Habitat of Bats: Discover Where They Live and Thrive – Big Bat Box | D6: BCI Certified Bat House: Importance of Certification
A7: 6 | B7: https://www.bigbatbox.com/products/angry-birds-wildyard-diy-birdhouse-kit | C7: WildYard X Angry Birds™ DIY Birdhouse Kit – Build & Paint | Big Bat Box | D7: WildYard X Angry Birds™ DIY Birdhouse Kit – Build & Paint
A8: 7 | B8: https://www.bigbatbox.com/pages/guide | C8: Bat House Installation Guide — How to Mount a Bat Box | Big Bat Box | D8: Bat House Installation Guide — How to Mount a Bat Box
A9: 8 | B9: https://www.bigbatbox.com/products/squirrel-house-hideout-feeder | C9: Squirrel House - Hideout & Feeder Cedar Outdoor Nesting Box – Big Bat Box | D9: Squirrel House - Hideout & Feeder Cedar Outdoor Nesting ...
A10: 9 | B10: https://www.bigbatbox.com/products/double-chamber-bat-house-black | C10: Two Chamber Black Bat House — Holds 75 Bats | Big Bat Box | D10: Two Chamber Black Bat House — Holds 75 Bats
A11: 10 | B11: https://www.bigbatbox.com/en-ca | C11: Bat Houses, Owl Boxes & Bee Hotels | Big Bat Box | D11: Big Bat Box: Bat Houses, Owl Boxes & Bee Hotels
A12: 11 | B12: https://www.bigbatbox.com/en-ca/products/squirrel-house-hideout-feeder | C12: Squirrel House - Hideout & Feeder Cedar Outdoor Nesting Box – Big Bat Box | D12: Squirrel House - Hideout & Feeder Cedar Outdoor Nesting ...
A13: 12 | B13: https://www.bigbatbox.com/fr/products/bee-house | C13: Bee House — Bamboo Pollinator Hotel for Gardens | Big Bat Box | D13: Bee House — Bamboo Pollinator Hotel for Gardens
A14: 13 | B14: https://www.bigbatbox.com/fr | C14: Nichoirs chauve-souris, chouette & abeilles | Big Bat Box | D14: Nichoirs chauve-souris, chouette & abeilles
... A30: 29 | B30: https://www.bigbatbox.com/blogs/habitat-of-bats/how-to-attract-bats-your-go-to-guide | C30: How to Attract Bats: Your Go-To Guide – Big Bat Box | D30: How to Attract Bats: Your Go-To Guide

Sheet BBB_Twitter and Open Graph tags
A1: S.No | B1: URL | D1: =HYPERLINK("#'Master Overview'!A1","<< Master Overview") -> << Master Overview
A2: 1 | B2: https://www.bigbatbox.com/products/certified-triple-chamber-bat-house-black | D2: Source: Bigbatbox - Site Audit.xlsx / Twitter and Open Graph tags inc
A3: 2 | B3: https://www.bigbatbox.com/en-ca/products/certified-triple-chamber-bat-house-black
A4: 3 | B4: https://www.bigbatbox.com/de/products/dreikammer-fledermaushaus
A5: 4 | B5: https://www.bigbatbox.com/es/products/certified-triple-chamber-bat-house-black
A6: 5 | B6: https://www.bigbatbox.com/fr/products/certified-triple-chamber-bat-house-black
A7: 6 | B7: https://www.bigbatbox.com/it/products/certified-triple-chamber-bat-house-black

Sheet BBB_Image file size too large
A1: S.No | B1: URL | C1: Content type | D1: Size (bytes) | E1: Loading time (ms) | F1: No. of IMG inlinks | H1: =HYPERLINK("#'Master Overview'!A1","<< Master Overview") -> << Master Overview
A2: 1 | B2: https://www.bigbatbox.com/cdn/shop/files/T_Light_Barn_Logo.webp?crop=center&height=4000&v=1784043894&width=4000 | C2: image/png | D2: 14921755 | E2: 39 | F2: 12 | H2: Source: Bigbatbox - Site Audit.xlsx / Image file size too large
A3: 2 | B3: https://www.bigbatbox.com/cdn/shop/files/DSC03158.png?crop=center&height=3734&v=1748795579&width=3734 | C3: image/png | D3: 14897107 | E3: 27 | F3: 18
A4: 3 | B4: https://www.bigbatbox.com/cdn/shop/files/T_Dark_Barn_Logo.webp?crop=center&height=4000&v=1784043987&width=4000 | C4: image/png | D4: 13185991 | E4: 58 | F4: 6
A5: 4 | B5: https://www.bigbatbox.com/cdn/shop/files/T_Light_Barn_Bottom.webp?crop=center&height=4000&v=1784043894&width=4000 | C5: image/png | D5: 7888706 | E5: 16 | F5: 12
A6: 5 | B6: https://www.bigbatbox.com/cdn/shop/files/T_Light_Barn_Tilt.webp?crop=center&height=4920&v=1784043894&width=4100 | C6: image/png | D6: 7669534 | E6: 39 | F6: 6
A7: 6 | B7: https://www.bigbatbox.com/cdn/shop/articles/bird_partner_blog_be073551-87a6-4f5a-a3f2-67e9937ebf07.png?crop=center&height=2462&v=1787913154&width=4100 | C7: image/png | D7: 7566117 | E7: 1402 | F7: 6
A8: 7 | B8: https://www.bigbatbox.com/cdn/shop/files/T_Dark_Barn_Bottom.webp?crop=center&height=4000&v=1784043986&width=4000 | C8: image/png | D8: 6904717 | E8: 37 | F8: 6
A9: 8 | B9: https://www.bigbatbox.com/cdn/shop/files/T_WildYard_Flowerpot_TopAngle_Flowers.webp?crop=center&height=4100&v=1776429379&width=4100 | C9: image/png | D9: 6603292 | E9: 64 | F9: 18
A10: 9 | B10: https://www.bigbatbox.com/cdn/shop/files/bird_partner_blog.png?crop=center&height=2747&v=1787912702&width=4574 | C10: image/png | D10: 6158660 | E10: 67 | F10: 6
A11: 10 | B11: https://www.bigbatbox.com/cdn/shop/files/squirrel3.jpg?crop=center&height=3456&v=1786347989&width=5184 | C11: image/jpeg | D11: 5806140 | E11: 2531 | F11: 6
A12: 11 | B12: https://www.bigbatbox.com/cdn/shop/files/T_Light_Barn_Tilt.webp?crop=center&height=4100&v=1784043894&width=4100 | C12: image/png | D12: 5741874 | E12: 17 | F12: 43
A13: 12 | B13: https://www.bigbatbox.com/cdn/shop/files/T_Light_Barn_Logo_2048x.webp?v=1784043894 | C13: image/png | D13: 5721013 | E13: 1412 | F13: 0
A14: 13 | B14: https://www.bigbatbox.com/cdn/shop/files/T_Light_Barn_Logo_2048x2048.webp?v=1784043894 | C14: image/png | D14: 5721013 | E14: 1450 | F14: 0
... A96: 95 | B96: https://www.bigbatbox.com/cdn/shop/files/Bee_Box_Hero.jpg?crop=center&height=2733&v=1763149795&width=4100 | C96: image/jpeg | D96: 1006079 | E96: 1122 | F96: 234

Sheet BBB_Images Missing ALT text
A1: S.No | B1: URL | C1: HTTP status code | D1: Organic traffic | E1: Linked images without alt attribute | F1: No. of linked images without alt attribute | H1: =HYPERLINK("#'Master Overview'!A1","<< Master Overview") -> << Master Overview
A2: 1 | B2: https://www.bigbatbox.com/es/blogs/wildyard-learn/bats-bees-as-your-garden-pollinators | C2: 200 | D2: 0 | E2: https://cdn.shopify.com/s/files/1/0002/0447/2339/files/DSC02696_600x600.webp?v=1724404416 https://cdn.shopify.com/s/files/1/0002/0447/2339/files/DSC03255_600x600.webp?v=1724404416 | F2: 2 | H2: Source: Bigbatbox - Site Audit.xlsx / Images Missing ALT text
A3: 2 | B3: https://www.bigbatbox.com/en-ca/blogs/wildyard-learn/bats-bees-as-your-garden-pollinators | C3: 200 | D3: 0 | E3: https://cdn.shopify.com/s/files/1/0002/0447/2339/files/DSC02696_600x600.webp?v=1724404416 https://cdn.shopify.com/s/files/1/0002/0447/2339/files/DSC03255_600x600.webp?v=1724404416 | F3: 2
A4: 3 | B4: https://www.bigbatbox.com/de/blogs/wildyard-learn/bats-bees-as-your-garden-pollinators | C4: 200 | D4: 0 | E4: https://cdn.shopify.com/s/files/1/0002/0447/2339/files/DSC02696_600x600.webp?v=1724404416 https://cdn.shopify.com/s/files/1/0002/0447/2339/files/DSC03255_600x600.webp?v=1724404416 | F4: 2
A5: 4 | B5: https://www.bigbatbox.com/fr/blogs/wildyard-learn/bats-bees-as-your-garden-pollinators | C5: 200 | D5: 0 | E5: https://cdn.shopify.com/s/files/1/0002/0447/2339/files/DSC02696_600x600.webp?v=1724404416 https://cdn.shopify.com/s/files/1/0002/0447/2339/files/DSC03255_600x600.webp?v=1724404416 | F5: 2
A6: 5 | B6: https://www.bigbatbox.com/it/blogs/wildyard-learn/bats-bees-as-your-garden-pollinators | C6: 200 | D6: 0 | E6: https://cdn.shopify.com/s/files/1/0002/0447/2339/files/DSC02696_600x600.webp?v=1724404416 https://cdn.shopify.com/s/files/1/0002/0447/2339/files/DSC03255_600x600.webp?v=1724404416 | F6: 2
A7: 6 | B7: https://www.bigbatbox.com/blogs/wildyard-learn/bats-bees-as-your-garden-pollinators | C7: 200 | D7: 0 | E7: https://cdn.shopify.com/s/files/1/0002/0447/2339/files/DSC02696_600x600.webp?v=1724404416 https://cdn.shopify.com/s/files/1/0002/0447/2339/files/DSC03255_600x600.webp?v=1724404416 | F7: 2

Sheet HS_Missing H1 Tag
A1: URL | B1: No. of H1 | D1: =HYPERLINK("#'Master Overview'!A1","<< Master Overview") -> << Master Overview
A2: https://happy-sinks.com/collections/kitchen-accessories | B2: 0 | D2: Source: https_happy-sinks.com_ - URL Report.xlsx / Missing H1 Tag
A3: https://happy-sinks.com/collections/sink-accessories | B3: 0
A4: https://happy-sinks.com/collections/all | B4: 0
A5: https://happy-sinks.com/collections/cloth-holders | B5: 0
A6: https://happy-sinks.com/collections/new-arrivals | B6: 0
A7: https://happy-sinks.com/collections/sponge-holders | B7: 0
A8: https://happy-sinks.com/collections/gift-cards | B8: 0
A9: https://happy-sinks.com/collections/dishcloths | B9: 0
A10: https://happy-sinks.com/collections/kitchen-sink-sets | B10: 0
A11: https://happy-sinks.com/collections/konna-the-fly-trap | B11: 0
A12: https://happy-sinks.com/pages/sustainability | B12: 0
A13: https://happy-sinks.com/pages/become-a-reseller | B13: 0
A14: https://happy-sinks.com/pages/happy-sinks-affiliate-program | B14: 0
... A175: https://happy-sinks.com/pages/cookie-policy | B175: 0

Sheet HS_Multiple H1 Tag
A1: URL | B1: No. of H1 | D1: =HYPERLINK("#'Master Overview'!A1","<< Master Overview") -> << Master Overview
A2: https://happy-sinks.com/pages/installation | B2: 2 | D2: Source: https_happy-sinks.com_ - URL Report.xlsx / Multiple H1 Tag
A3: https://happy-sinks.com/sv/pages/installation | B3: 2
A4: https://happy-sinks.com/de/pages/installation | B4: 2
A5: https://happy-sinks.com/fi/cart | B5: 2
A6: https://happy-sinks.com/fi/pages/installation | B6: 2
A7: https://happy-sinks.com/de/cart | B7: 2
A8: https://happy-sinks.com/da/pages/installation | B8: 2
A9: https://happy-sinks.com/blogs/magisso/5-eco-friendly-cleaning-products-your-home-will-thank-you-for | B9: 6
A10: https://happy-sinks.com/en-gb/pages/installation | B10: 2
A11: https://happy-sinks.com/es/pages/installation | B11: 2
A12: https://happy-sinks.com/en-au/pages/installation | B12: 2
A13: https://happy-sinks.com/es/cart | B13: 2
A14: https://happy-sinks.com/fi/blogs/magisso/5-spring-cleaning-tips-with-happy-sinks | B14: 6
... A103: https://happy-sinks.com/de/pages/mioeco-simple-sustainable-living | B103: 2

Sheet HS_Too Long Meta Title
A1: URL | B1: Meta Title | C1: Title length | E1: =HYPERLINK("#'Master Overview'!A1","<< Master Overview") -> << Master Overview
A2: https://happy-sinks.com/collections/all | B2: All Kitchen Accessories - Sustainable, Vibrant & Essential – HAPPY SiNKS | C2: 72 | E2: Source: https_happy-sinks.com_ - URL Report.xlsx / Too Long Meta Title
A3: https://happy-sinks.com/collections/new-arrivals | B3: New Arrivals - Discover the Latest Trends in Our Collection – HAPPY SiNKS | C3: 73
A4: https://happy-sinks.com/collections/dishcloths | B4: Eco-friendly Swedish Dishcloths for a Sustainable Kitchen – HAPPY SiNKS | C4: 71
A5: https://happy-sinks.com/da/collections/dishcloths | B5: Miljøvenlige svenske opvaskeklude til et bæredygtigt køkken – HAPPY SiNKS | C5: 73
A6: https://happy-sinks.com/de/collections/cloth-holders | B6: Magnetischer Spültuchhalter – Geschirrtuchhalter ohne Bohren | HAPPY SiNKS | C6: 74
A7: https://happy-sinks.com/fi/collections/all | B7: Kaikki keittiötarvikkeet – Kestävät, värikkäät ja välttämättömät – HAPPY SiNKS | C7: 78
A8: https://happy-sinks.com/da/collections/cloth-holders | B8: Magnetisk Karkludeholder – Holder til Karklud uden Boring | HAPPY SiNKS | C8: 71
A9: https://happy-sinks.com/de/collections/new-arrivals | B9: Neuheiten – Entdecken Sie die neuesten Trends in unserer Kollektion – HAPPY SiNKS | C9: 81
A10: https://happy-sinks.com/de/collections/all | B10: Alle Küchenaccessoires – Nachhaltig, Lebendig & Unverzichtbar – HAPPY SiNKS | C10: 75
A11: https://happy-sinks.com/da/collections/all | B11: Alt køkkentilbehør - Bæredygtigt, farverigt og uundværligt – HAPPY SiNKS | C11: 72
A12: https://happy-sinks.com/de/collections/dishcloths | B12: Umweltfreundliche schwedische Spültücher für eine nachhaltige Küche – HAPPY SiNKS | C12: 81
A13: https://happy-sinks.com/fi/pages/about-us | B13: HAPPY SiNKS | Pohjoismainen keittiöjärjestys ja kestävät allasratkaisut | C13: 71
A14: https://happy-sinks.com/de/pages/about-us | B14: HAPPY SiNKS | Nordische Küchenorganisation & nachhaltige Spülenlösungen | C14: 71
... A335: https://happy-sinks.com/fi/blogs/magisso/tagged/reusable-spray-bottles | B335: Blogi - ONNELLINEN SiNKS – Merkitty "Reusable Spray Bottles" – HAPPY SiNKS | C335: 74

Sheet HS_Too Long Meta Description
A1: URL | B1: Meta description | C1: Meta description length | E1: =HYPERLINK("#'Master Overview'!A1","<< Master Overview") -> << Master Overview
A2: https://happy-sinks.com/pages/about-us | B2: Smart, sustainable Nordic kitchen tools that make cleaning easier and happier. Shop magnetic holders, dish racks, and eco-friendly accessories for a tidier home. | C2: 161 | E2: Source: https_happy-sinks.com_ - URL Report.xlsx / Too Long Meta Description
A3: https://happy-sinks.com/sv/pages/sustainability | B3: På HAPPY SiNKS går vårt engagemang för hållbarhet hand i hand med vår passion för att sprida glädje till ditt dagliga liv. Läs mer om hur vi jobbar med hållbarhet! | C3: 163
A4: https://happy-sinks.com/sv/collections/sponge-holders | B4: HAPPY SiNKS magnetisk svamphållare i biokomposit eller rostfritt stål. Utan borrning, snabb torkning, mindre bakterier. Prisbelönt finsk design för en renare diskbänk. | C4: 167
A5: https://happy-sinks.com/sv/pages/about-us | B5: Smarta, hållbara nordiska köksredskap som gör städningen enklare och roligare. Handla magnetiska hållare, diskställ och miljövänliga tillbehör för ett prydligare hem. | C5: 166
A6: https://happy-sinks.com/sv | B6: Kolla in vårt utbud av stilrena, funktionella och miljövänliga kökstillbehör för ett renare, snyggare och mer organiserat kök. Vi har allt du och ditt kök behöver! | C6: 163
A7: https://happy-sinks.com/sv/collections/cloth-holders | B7: HAPPY SiNKS magnetisk disktrashållare i biokomposit eller rostfritt stål. Utan borrning, passar stål- och kompositdiskhoar. Prisbelönt finsk design. Snabb torkning, mindre bakterier. | C7: 182
A8: https://happy-sinks.com/de/collections/cloth-holders | B8: Entdecken Sie den HAPPY SiNKS Spültuchhalter: magnetischer Geschirrtuchhalter aus Biokomposit oder Edelstahl. Ohne Bohren, für Edelstahl- und Kompositspülen. Preisgekröntes finnisches Design. | C8: 191
A9: https://happy-sinks.com/da/pages/happy-sinks-affiliate-program | B9: HAPPY SiNKS tilknyttede program er en måde for skabere at tjene provision på salg ved at henvise kunder til hjemmesiden ved hjælp af unikke links. Tilmeld dig i dag! | C9: 165
A10: https://happy-sinks.com/de/pages/happy-sinks-affiliate-program | B10: Das HAPPY SiNKS-Partnerprogramm ist eine Möglichkeit für Entwickler, Provisionen für Verkäufe zu verdienen, indem sie Kunden über eindeutige Links auf die Website verweisen. Tritt heute bei! | C10: 190
A11: https://happy-sinks.com/fi/collections/all | B11: Tutustu keittiötarvikevalikoimaamme, joka on valmistettu kestävistä materiaaleista ja eloisissa väreissä. Täydellisiä siivoukseen, järjestämiseen ja bakteerien vähentämiseen. | C11: 174
A12: https://happy-sinks.com/da/blogs/magisso | B12: Fra hurtige rengøringstips til de seneste nyheder, har vores blog alt, hvad du behøver for at holde dig informeret og blive inspireret til en renere og sundere livsstil! | C12: 169
A13: https://happy-sinks.com/da/collections/cloth-holders | B13: HAPPY SiNKS magnetisk karkludeholder i biokomposit eller rustfrit stål. Ingen boring, passer stål- og kompositvaske. Prisbelønnet finsk design. Hurtig tørring, færre bakterier. | C13: 176
A14: https://happy-sinks.com/de/collections/new-arrivals | B14: Entdecken Sie unsere New Arrivals Kollektion für die frischesten Styles und neuesten Trends. Finden Sie jetzt Ihren perfekten Look unter unseren neuesten Artikeln. | C14: 163
... A127: https://happy-sinks.com/sv/products/kitchen-set-dish-cloth-holder-sponge-holder-fruit-fly-trap | B127: Få Kitchen Set med Biocomposite Disktrasehållare, Svamphållare och KONNA Fruktflugefälla för att hålla köket snyggt, stilrent och hygieniskt. Ett komplett paket! | C127: 161
A128: https://happy-sinks.com/en-au/blogs/magisso/happy-sinks-vs-competitors | B128: HAPPY SiNKS vs Competitors: Compare with Moen, Kohler, Delta, Kraus, and American Standard to see why HAPPY SiNKS wins in design, durability, and value. Compare HAPPY SINKS with Carysil, Blanco, Franke, Lapetek, and Elkay. Discover why HAPPY SINKS offers the best ergonomic design, durability, and value for your kitchen. | C128: 152 168
A129: https://happy-sinks.com/es/products/happy-sinks-konna-the-fruit-fly-trap | B129: Deshazte de las moscas de la fruta en tu cocina con la ayuda de nuestra Trampa para Moscas de la Fruta - KONNA en un hermoso color rosa jardín. Diseñada para atraer y atrapar moscas de la fruta. | C129: 194
A130: https://happy-sinks.com/da/blogs/magisso/tagged/cutting-knives | B130: Fra hurtige rengøringstips til de seneste nyheder, har vores blog alt, hvad du behøver for at holde dig informeret og blive inspireret til en renere og sundere livsstil! | C130: 169
A131: https://happy-sinks.com/products/swedish-dishcloths-forest-green-3pc | B131: At HAPPY SiNKS, we start improving daily cleaning tasks by one dishcloth at a time. This versatile and eco-friendly Swedish dishcloths are designed to revolutionize your kitchen cleaning routine, making it more efficient and enjoyable. These Swedish Dishcloths come in a convenient pack of three, ensuring you always h | C131: 318
A132: https://happy-sinks.com/blogs/magisso/happy-sinks-vs-competitors | B132: HAPPY SiNKS vs Competitors: Compare with Moen, Kohler, Delta, Kraus, and American Standard to see why HAPPY SiNKS wins in design, durability, and value. Compare HAPPY SINKS with Carysil, Blanco, Franke, Lapetek, and Elkay. Discover why HAPPY SINKS offers the best ergonomic design, durability, and value for your kitchen. | C132: 152 168
A133: https://happy-sinks.com/fi/blogs/magisso/small-kitchen-solutions | B133: Löydä olennaiset pienet keittiöratkaisut monipuolisilla työkaluilla ja älykkäillä järjestelyideoilla. Hyödynnä tilaa ja tehokkuutta pienessä keittiössäsi jo tänään. | C133: 164
A134: https://happy-sinks.com/da/collections/kitchen-accessories | B134: Opdag stilfulde og funktionelle køkkentilbehør fra HAPPY SiNKS. Smarte løsninger designet til at forenkle dine daglige rutiner og bringe mere glæde til dit køkken. | C134: 163
A135: https://happy-sinks.com/fi/blogs/magisso/how-to-keep-the-kitchen-sink-sparking | B135: Löydä asiantuntijavinkit siitä, kuinka pitää keittiöallas hohtavan puhtaana HAPPY SiNKS!:n avulla! Pidä altaasi tahrattomana, hygieenisenä ja kiiltävänä joka päivä vaivattomasti. | C135: 178
A136: https://happy-sinks.com/fi/collections/sink-accessories | B136: Tutustu HAPPY SiNKSin älykkäisiin allaslisävarusteisiin. Tyylikkäitä, toimivia ratkaisuja, jotka pitävät altaasi järjestyksessä, puhtaana ja helppokäyttöisenä joka päivä. | C136: 170
A137: https://happy-sinks.com/en-gb/products/swedish-dishcloths-go-ahead-spill-the-tea-3pc | B137: Tired of wasteful paper towels? The HAPPY SiNKS Swedish Dishcloths – Go Ahead, Spill the Tea – are your perfect eco-friendly alternative! These ultra-absorbent cloths tackle spills effortlessly while reducing your carbon footprint. Durable, reusable, and 100% biodegradable, they keep your kitchen spotless and help the | C137: 319
A138: https://happy-sinks.com/es/collections/sink-accessories | B138: Descubre accesorios inteligentes para fregaderos de HAPPY SiNKS. Soluciones elegantes y funcionales que mantienen tu fregadero organizado, limpio y fácil de usar todos los días. | C138: 177
A139: https://happy-sinks.com/de/blogs/magisso/magnetic-vs-suction-sponge-holders-which-one-is-better | B139: Erfahren Sie den Unterschied zwischen magnetischen und Saugnapfschwammhaltern. Finden Sie heraus, welcher Ihren Spülbecken sauberer, frischer und leichter zu pflegen hält. | C139: 171
A140: https://happy-sinks.com/de/blogs/magisso/tagged/odor-removal | B140: Von schnellen Reinigungstipps bis hin zu den neuesten Nachrichten finden Sie in unserem Blog alles, was Sie brauchen, um auf dem Laufenden zu bleiben und sich für einen saubereren und gesünderen Lebensstil inspirieren zu lassen! | C140: 228
A141: https://happy-sinks.com/de/products/happy-sinks-konna-the-fruit-fly-trap | B141: Beseitigen Sie Fruchtfliegen in Ihrer Küche mit der Hilfe unserer Fruchtfliegenfalle - KONNA in wunderschöner Gartenrosenfarbe. Entwickelt, um Fruchtfliegen anzulocken und zu fangen. | C141: 182
A142: https://happy-sinks.com/fi/products/fruit-fly-trap-konna | B142: Pidä keittiösi raikkaana KONNA hedelmäkärpäspaperilla. Tämä tyylikäs kärpäspaperi luonnollisissa väreissä auttaa houkuttelemaan ja pyydystämään hedelmäkärpäsiä nopeasti ja huomaamattomasti. | C142: 189
A143: https://happy-sinks.com/de/products/fruit-fly-trap-konna | B143: Halten Sie Ihre Küche mit der KONNA Fruchtfliegenfalle frisch. Dieser stilvolle Fliegenfänger in natürlichen Farben hilft, Fruchtfliegen schnell und diskret anzulocken und zu fangen. | C143: 182
A144: https://happy-sinks.com/de/blogs/magisso/tagged/natural-repellents | B144: Von schnellen Reinigungstipps bis hin zu den neuesten Nachrichten finden Sie in unserem Blog alles, was Sie brauchen, um auf dem Laufenden zu bleiben und sich für einen saubereren und gesünderen Lebensstil inspirieren zu lassen! | C144: 228
... A149: https://happy-sinks.com/da/blogs/magisso/tagged/swedish-dishcloth | B149: Fra hurtige rengøringstips til de seneste nyheder, har vores blog alt, hvad du behøver for at holde dig informeret og blive inspireret til en renere og sundere livsstil! | C149: 169
A150: https://happy-sinks.com/en-gb/blogs/magisso/happy-sinks-vs-competitors | B150: HAPPY SiNKS vs Competitors: Compare with Moen, Kohler, Delta, Kraus, and American Standard to see why HAPPY SiNKS wins in design, durability, and value. Compare HAPPY SINKS with Carysil, Blanco, Franke, Lapetek, and Elkay. Discover why HAPPY SINKS offers the best ergonomic design, durability, and value for your kitchen. | C150: 152 168
A151: https://happy-sinks.com/de/blogs/magisso/tagged/kitchen-towels | B151: Von schnellen Reinigungstipps bis hin zu den neuesten Nachrichten finden Sie in unserem Blog alles, was Sie brauchen, um auf dem Laufenden zu bleiben und sich für einen saubereren und gesünderen Lebensstil inspirieren zu lassen! | C151: 228
A152: https://happy-sinks.com/de/blogs/magisso/tagged/fly-traps | B152: Von schnellen Reinigungstipps bis hin zu den neuesten Nachrichten finden Sie in unserem Blog alles, was Sie brauchen, um auf dem Laufenden zu bleiben und sich für einen saubereren und gesünderen Lebensstil inspirieren zu lassen! | C152: 228
A153: https://happy-sinks.com/de/blogs/magisso/tagged/fruit-fly-control | B153: Von schnellen Reinigungstipps bis hin zu den neuesten Nachrichten finden Sie in unserem Blog alles, was Sie brauchen, um auf dem Laufenden zu bleiben und sich für einen saubereren und gesünderen Lebensstil inspirieren zu lassen! | C153: 228
A154: https://happy-sinks.com/fi/blogs/magisso/magnetic-vs-suction-sponge-holders-which-one-fits-your-kitchen | B154: Vertaile magneettisia ja imukuppikiinnikkeitä sieniä varten löytääksesi parhaan vaihtoehdon keittiöösi. Opi niiden edut, haitat ja kumpi sopii paremmin tiskialtaasi tyyppiin. | C154: 174
A155: https://happy-sinks.com/de/blogs/magisso/tagged/kitchen-organization | B155: Von schnellen Reinigungstipps bis hin zu den neuesten Nachrichten finden Sie in unserem Blog alles, was Sie brauchen, um auf dem Laufenden zu bleiben und sich für einen saubereren und gesünderen Lebensstil inspirieren zu lassen! | C155: 228
A156: https://happy-sinks.com/fi/blogs/magisso/tagged/sanitization-techniques | B156: Nopeat siivousvinkit ja viimeisimmät uutiset – blogistamme löydät kaiken, mitä tarvitset pysyäksesi ajan tasalla ja saadaksesi inspiraatiota puhtaampaan ja terveellisempään elämäntapaan! | C156: 186
A157: https://happy-sinks.com/da/blogs/magisso/tagged/food-prep | B157: Fra hurtige rengøringstips til de seneste nyheder, har vores blog alt, hvad du behøver for at holde dig informeret og blive inspireret til en renere og sundere livsstil! | C157: 169
A158: https://happy-sinks.com/de/products/dish-cloth-holder-steel | B158: Hören Sie auf, das Geschirrtuch über den Wasserhahn zu hängen. Bewahren Sie es mit dem HAPPY SiNKS magnetischen Geschirrtuchhalter stilvoll, hygienisch und einfach zu installieren in Ihrem Spülbecken auf. | C158: 204
A159: https://happy-sinks.com/es/collections/kitchen-accessories | B159: Descubre accesorios de cocina elegantes y funcionales de HAPPY SiNKS. Soluciones inteligentes diseñadas para simplificar las rutinas diarias y aportar más alegría a tu cocina. | C159: 175
A160: https://happy-sinks.com/fi/products/happy-sinks-konna-the-fruit-fly-trap | B160: Päästä eroon hedelmäkärpäsistä keittiössäsi apuna hedelmäkärpäspaperimme - KONNA kauniissa puutarharuusun värissä. Suunniteltu houkuttelemaan ja pyydystämään hedelmäkärpäsiä. | C160: 174
A161: https://happy-sinks.com/de/collections/sink-accessories | B161: Entdecken Sie intelligente Spülbecken-Zubehör von HAPPY SiNKS. Stilvolle, funktionale Lösungen, die Ihr Spülbecken organisiert, sauber und jeden Tag einfach zu benutzen halten. | C161: 176
A162: https://happy-sinks.com/en-au/products/sink-cutlery-caddy | B162: Organize Your Kitchen in Style with HAPPY SiNKS. Are you tired of drying your forks, knives, and spoons on a drying rack or towel next to the sink? End the chaos with HAPPY SiNKS' sophisticated Sink Cutlery Caddy. This sleek kitchen essential not only dries them neatly inside the sink but also keeps your cutlery organi | C162: 320
... A171: https://happy-sinks.com/fi/blogs/magisso/tagged/sponge-hygiene-tips | B171: Nopeat siivousvinkit ja viimeisimmät uutiset – blogistamme löydät kaiken, mitä tarvitset pysyäksesi ajan tasalla ja saadaksesi inspiraatiota puhtaampaan ja terveellisempään elämäntapaan! | C171: 186
A172: https://happy-sinks.com/en-ca/blogs/magisso/happy-sinks-vs-competitors | B172: HAPPY SiNKS vs Competitors: Compare with Moen, Kohler, Delta, Kraus, and American Standard to see why HAPPY SiNKS wins in design, durability, and value. Compare HAPPY SINKS with Carysil, Blanco, Franke, Lapetek, and Elkay. Discover why HAPPY SINKS offers the best ergonomic design, durability, and value for your kitchen. | C172: 152 168
A173: https://happy-sinks.com/de/blogs/magisso/tagged/scandinavian-kitchen-essentials | B173: Von schnellen Reinigungstipps bis hin zu den neuesten Nachrichten finden Sie in unserem Blog alles, was Sie brauchen, um auf dem Laufenden zu bleiben und sich für einen saubereren und gesünderen Lebensstil inspirieren zu lassen! | C173: 228
A174: https://happy-sinks.com/fi/blogs/magisso/tagged/dish-drying-racks | B174: Nopeat siivousvinkit ja viimeisimmät uutiset – blogistamme löydät kaiken, mitä tarvitset pysyäksesi ajan tasalla ja saadaksesi inspiraatiota puhtaampaan ja terveellisempään elämäntapaan! | C174: 186
A175: https://happy-sinks.com/de/blogs/magisso/tagged/stockholm-events | B175: Von schnellen Reinigungstipps bis hin zu den neuesten Nachrichten finden Sie in unserem Blog alles, was Sie brauchen, um auf dem Laufenden zu bleiben und sich für einen saubereren und gesünderen Lebensstil inspirieren zu lassen! | C175: 228
A176: https://happy-sinks.com/de/blogs/magisso/tagged/home-silver-cleaning-methods | B176: Von schnellen Reinigungstipps bis hin zu den neuesten Nachrichten finden Sie in unserem Blog alles, was Sie brauchen, um auf dem Laufenden zu bleiben und sich für einen saubereren und gesünderen Lebensstil inspirieren zu lassen! | C176: 228
A177: https://happy-sinks.com/es/blogs/magisso/keeping-dishcloths-dry-hygienically-simple-tips-for-a-cleaner-kitchen | B177: Mantener los paños de cocina secos de manera higiénica es clave para una cocina más limpia. Descubre consejos sencillos para evitar bacterias y mantener la frescura. | C177: 165
A178: https://happy-sinks.com/fi/blogs/magisso/tagged/easy-kitchen-upgrade | B178: Nopeat siivousvinkit ja viimeisimmät uutiset – blogistamme löydät kaiken, mitä tarvitset pysyäksesi ajan tasalla ja saadaksesi inspiraatiota puhtaampaan ja terveellisempään elämäntapaan! | C178: 186
A179: https://happy-sinks.com/da/blogs/magisso/tagged/kitchen-sink-cleaning | B179: Fra hurtige rengøringstips til de seneste nyheder, har vores blog alt, hvad du behøver for at holde dig informeret og blive inspireret til en renere og sundere livsstil! | C179: 169
A180: https://happy-sinks.com/de/blogs/magisso/tagged/sink-maintenance | B180: Von schnellen Reinigungstipps bis hin zu den neuesten Nachrichten finden Sie in unserem Blog alles, was Sie brauchen, um auf dem Laufenden zu bleiben und sich für einen saubereren und gesünderen Lebensstil inspirieren zu lassen! | C180: 228
A181: https://happy-sinks.com/de/blogs/magisso/9-essential-must-have-kitchen-items-that-you-need | B181: Entdecken Sie 9 unverzichtbare Küchenutensilien, die Sie benötigen. Statten Sie Ihre Küche mit den Werkzeugen aus, die das Kochen einfacher, effizienter und angenehmer machen. | C181: 175
A182: https://happy-sinks.com/de/pages/cookie-policy | B182: Ein Cookie ist eine kleine Menge an Informationen, die in Ihrem Browser gespeichert wird, wenn Sie unsere Website besuchen. Lesen Sie hier unsere Cookie-Richtlinie. | C182: 164
A183: https://happy-sinks.com/da/blogs/magisso/tagged/hygiene | B183: Fra hurtige rengøringstips til de seneste nyheder, har vores blog alt, hvad du behøver for at holde dig informeret og blive inspireret til en renere og sundere livsstil! | C183: 169
A184: https://happy-sinks.com/fi/blogs/magisso/tagged/2026-trends | B184: Nopeat siivousvinkit ja viimeisimmät uutiset – blogistamme löydät kaiken, mitä tarvitset pysyäksesi ajan tasalla ja saadaksesi inspiraatiota puhtaampaan ja terveellisempään elämäntapaan! | C184: 186
... A356: https://happy-sinks.com/de/blogs/magisso/tagged/how-to-dry-kitchen-sponge | B356: Von schnellen Reinigungstipps bis hin zu den neuesten Nachrichten finden Sie in unserem Blog alles, was Sie brauchen, um auf dem Laufenden zu bleiben und sich für einen saubereren und gesünderen Lebensstil inspirieren zu lassen! | C356: 228
A357: https://happy-sinks.com/da/blogs/magisso/happy-sinks-vs-competitors | B357: HAPPY SiNKS vs konkurrenter: Sammenlign med Moen, Kohler, Delta, Kraus og American Standard for at se, hvorfor HAPPY SiNKS vinder på design, holdbarhed og værdi. Compare HAPPY SINKS with Carysil, Blanco, Franke, Lapetek, and Elkay. Discover why HAPPY SINKS offers the best ergonomic design, durability, and value for your kitchen. | C357: 161 168
A358: https://happy-sinks.com/fi/blogs/magisso/tagged/happy-sinks-dish-rack | B358: Nopeat siivousvinkit ja viimeisimmät uutiset – blogistamme löydät kaiken, mitä tarvitset pysyäksesi ajan tasalla ja saadaksesi inspiraatiota puhtaampaan ja terveellisempään elämäntapaan! | C358: 186
A359: https://happy-sinks.com/de/blogs/magisso/tagged/hygienic-dishwashing | B359: Von schnellen Reinigungstipps bis hin zu den neuesten Nachrichten finden Sie in unserem Blog alles, was Sie brauchen, um auf dem Laufenden zu bleiben und sich für einen saubereren und gesünderen Lebensstil inspirieren zu lassen! | C359: 228
A360: https://happy-sinks.com/fi/blogs/magisso/tagged/happy-sinks-products | B360: Nopeat siivousvinkit ja viimeisimmät uutiset – blogistamme löydät kaiken, mitä tarvitset pysyäksesi ajan tasalla ja saadaksesi inspiraatiota puhtaampaan ja terveellisempään elämäntapaan! | C360: 186
A361: https://happy-sinks.com/da/blogs/magisso/tagged/swedish-dishcloths | B361: Fra hurtige rengøringstips til de seneste nyheder, har vores blog alt, hvad du behøver for at holde dig informeret og blive inspireret til en renere og sundere livsstil! | C361: 169
A362: https://happy-sinks.com/sv/products/happy-sinks-gift-card-25 | B362: Letar du efter den perfekta presentidén? Varför inte ge bort ett HAPPY SiNKS E-Gåvokort med möjligheten att hitta en funktionell produkt som hjälper dem att organisera drömköket. | C362: 178
A363: https://happy-sinks.com/de/blogs/magisso/tagged/kitchen-space-savers | B363: Von schnellen Reinigungstipps bis hin zu den neuesten Nachrichten finden Sie in unserem Blog alles, was Sie brauchen, um auf dem Laufenden zu bleiben und sich für einen saubereren und gesünderen Lebensstil inspirieren zu lassen! | C363: 228
A364: https://happy-sinks.com/fi/blogs/magisso/tagged/kitchen-organization | B364: Nopeat siivousvinkit ja viimeisimmät uutiset – blogistamme löydät kaiken, mitä tarvitset pysyäksesi ajan tasalla ja saadaksesi inspiraatiota puhtaampaan ja terveellisempään elämäntapaan! | C364: 186
A365: https://happy-sinks.com/de/blogs/magisso/tagged/kitchen-care | B365: Von schnellen Reinigungstipps bis hin zu den neuesten Nachrichten finden Sie in unserem Blog alles, was Sie brauchen, um auf dem Laufenden zu bleiben und sich für einen saubereren und gesünderen Lebensstil inspirieren zu lassen! | C365: 228
A366: https://happy-sinks.com/da/blogs/magisso/tagged/stainless-steel-kitchen | B366: Fra hurtige rengøringstips til de seneste nyheder, har vores blog alt, hvad du behøver for at holde dig informeret og blive inspireret til en renere og sundere livsstil! | C366: 169
A367: https://happy-sinks.com/de/blogs/magisso/tagged/roll-up-sink-rack | B367: Von schnellen Reinigungstipps bis hin zu den neuesten Nachrichten finden Sie in unserem Blog alles, was Sie brauchen, um auf dem Laufenden zu bleiben und sich für einen saubereren und gesünderen Lebensstil inspirieren zu lassen! | C367: 228
A368: https://happy-sinks.com/da/blogs/magisso/tagged/reusable-spray-bottles | B368: Fra hurtige rengøringstips til de seneste nyheder, har vores blog alt, hvad du behøver for at holde dig informeret og blive inspireret til en renere og sundere livsstil! | C368: 169
A369: https://happy-sinks.com/fi/blogs/magisso/tagged/time-saving-cleaning | B369: Nopeat siivousvinkit ja viimeisimmät uutiset – blogistamme löydät kaiken, mitä tarvitset pysyäksesi ajan tasalla ja saadaksesi inspiraatiota puhtaampaan ja terveellisempään elämäntapaan! | C369: 186
... A419: https://happy-sinks.com/fi/blogs/magisso/tagged/kitchen-space-savers | B419: Nopeat siivousvinkit ja viimeisimmät uutiset – blogistamme löydät kaiken, mitä tarvitset pysyäksesi ajan tasalla ja saadaksesi inspiraatiota puhtaampaan ja terveellisempään elämäntapaan! | C419: 186
A420: https://happy-sinks.com/es/blogs/magisso/happy-sinks-vs-competitors | B420: HAPPY SiNKS vs Competidores: Compáralo con Moen, Kohler, Delta, Kraus y American Standard para ver por qué HAPPY SiNKS gana en diseño, durabilidad y valor. Compare HAPPY SINKS with Carysil, Blanco, Franke, Lapetek, and Elkay. Discover why HAPPY SINKS offers the best ergonomic design, durability, and value for your kitchen. | C420: 155 168
A421: https://happy-sinks.com/de/blogs/magisso/tagged/magnetic-cloth-holders | B421: Von schnellen Reinigungstipps bis hin zu den neuesten Nachrichten finden Sie in unserem Blog alles, was Sie brauchen, um auf dem Laufenden zu bleiben und sich für einen saubereren und gesünderen Lebensstil inspirieren zu lassen! | C421: 228
A422: https://happy-sinks.com/fi/blogs/magisso/tagged/dry-dishcloth | B422: Nopeat siivousvinkit ja viimeisimmät uutiset – blogistamme löydät kaiken, mitä tarvitset pysyäksesi ajan tasalla ja saadaksesi inspiraatiota puhtaampaan ja terveellisempään elämäntapaan! | C422: 186
A423: https://happy-sinks.com/fi/blogs/magisso/tagged/keep-dishcloths-fresh | B423: Nopeat siivousvinkit ja viimeisimmät uutiset – blogistamme löydät kaiken, mitä tarvitset pysyäksesi ajan tasalla ja saadaksesi inspiraatiota puhtaampaan ja terveellisempään elämäntapaan! | C423: 186
A424: https://happy-sinks.com/da/blogs/magisso/tagged/sustainable-living | B424: Fra hurtige rengøringstips til de seneste nyheder, har vores blog alt, hvad du behøver for at holde dig informeret og blive inspireret til en renere og sundere livsstil! | C424: 169
A425: https://happy-sinks.com/es/products/happy-sinks-gift-card-25 | B425: ¿Buscas la idea de regalo perfecta? ¿Por qué no regalar una tarjeta de regalo electrónica HAPPY SiNKS con la oportunidad de encontrar un artículo funcional que les ayude a organizar la cocina de sus sueños? | C425: 206
A426: https://happy-sinks.com/da/blogs/magisso/tagged/interior-design-fair | B426: Fra hurtige rengøringstips til de seneste nyheder, har vores blog alt, hvad du behøver for at holde dig informeret og blive inspireret til en renere og sundere livsstil! | C426: 169
A427: https://happy-sinks.com/fi/blogs/magisso/tagged/eco-friendly-cleaning | B427: Nopeat siivousvinkit ja viimeisimmät uutiset – blogistamme löydät kaiken, mitä tarvitset pysyäksesi ajan tasalla ja saadaksesi inspiraatiota puhtaampaan ja terveellisempään elämäntapaan! | C427: 186
A428: https://happy-sinks.com/sv/blogs/magisso/fruit-fly-control-simple-solutions-for-a-pest-free-kitchen | B428: Håll ditt kök fritt från skadedjur med tips för att kontrollera fruktflugor. Lär dig enkla och effektiva lösningar för att förebygga angrepp och hålla köket rent. | C428: 162
A429: https://happy-sinks.com/fi/blogs/magisso/tagged/appliance-maintenance | B429: Nopeat siivousvinkit ja viimeisimmät uutiset – blogistamme löydät kaiken, mitä tarvitset pysyäksesi ajan tasalla ja saadaksesi inspiraatiota puhtaampaan ja terveellisempään elämäntapaan! | C429: 186
A430: https://happy-sinks.com/da/blogs/magisso/tagged/january-blues | B430: Fra hurtige rengøringstips til de seneste nyheder, har vores blog alt, hvad du behøver for at holde dig informeret og blive inspireret til en renere og sundere livsstil! | C430: 169
A431: https://happy-sinks.com/de/blogs/magisso/tagged/dish-drying-racks | B431: Von schnellen Reinigungstipps bis hin zu den neuesten Nachrichten finden Sie in unserem Blog alles, was Sie brauchen, um auf dem Laufenden zu bleiben und sich für einen saubereren und gesünderen Lebensstil inspirieren zu lassen! | C431: 228
A432: https://happy-sinks.com/fi/blogs/magisso/tagged/magnetic-sink-accessories | B432: Nopeat siivousvinkit ja viimeisimmät uutiset – blogistamme löydät kaiken, mitä tarvitset pysyäksesi ajan tasalla ja saadaksesi inspiraatiota puhtaampaan ja terveellisempään elämäntapaan! | C432: 186
... A695: https://happy-sinks.com/es/blogs/magisso/fruit-fly-control-simple-solutions-for-a-pest-free-kitchen | B695: Mantén tu cocina libre de plagas con consejos para el control de moscas de la fruta. Descubre soluciones simples y efectivas para prevenir infestaciones y mantener una cocina limpia. | C695: 182
A696: https://happy-sinks.com/sv/blogs/magisso/happy-sinks-vs-competitors | B696: HAPPY SiNKS vs Konkurrenter: Jämför med Moen, Kohler, Delta, Kraus och American Standard för att se varför HAPPY SiNKS vinner när det gäller design, hållbarhet och värde. Compare HAPPY SINKS with Carysil, Blanco, Franke, Lapetek, and Elkay. Discover why HAPPY SINKS offers the best ergonomic design, durability, and value for your kitchen. | C696: 170 168
A697: https://happy-sinks.com/fi/blogs/magisso/tagged/formex-2023 | B697: Nopeat siivousvinkit ja viimeisimmät uutiset – blogistamme löydät kaiken, mitä tarvitset pysyäksesi ajan tasalla ja saadaksesi inspiraatiota puhtaampaan ja terveellisempään elämäntapaan! | C697: 186
A698: https://happy-sinks.com/de/blogs/magisso/tagged/home-cleaning-tips | B698: Von schnellen Reinigungstipps bis hin zu den neuesten Nachrichten finden Sie in unserem Blog alles, was Sie brauchen, um auf dem Laufenden zu bleiben und sich für einen saubereren und gesünderen Lebensstil inspirieren zu lassen! | C698: 228
A699: https://happy-sinks.com/da/blogs/magisso/tagged/spring-cleaning | B699: Fra hurtige rengøringstips til de seneste nyheder, har vores blog alt, hvad du behøver for at holde dig informeret og blive inspireret til en renere og sundere livsstil! | C699: 169
A700: https://happy-sinks.com/fi/blogs/magisso/tagged/home-pest-control | B700: Nopeat siivousvinkit ja viimeisimmät uutiset – blogistamme löydät kaiken, mitä tarvitset pysyäksesi ajan tasalla ja saadaksesi inspiraatiota puhtaampaan ja terveellisempään elämäntapaan! | C700: 186
A701: https://happy-sinks.com/es/blogs/magisso?page=3 | B701: Desde consejos rápidos de limpieza hasta las últimas noticias, nuestro blog tiene todo lo que necesita para mantenerse informado e inspirarse para un estilo de vida más limpio y saludable. | C701: 188
A702: https://happy-sinks.com/fi/blogs/magisso/tagged/ceramic-sink-accessories | B702: Nopeat siivousvinkit ja viimeisimmät uutiset – blogistamme löydät kaiken, mitä tarvitset pysyäksesi ajan tasalla ja saadaksesi inspiraatiota puhtaampaan ja terveellisempään elämäntapaan! | C702: 186
A703: https://happy-sinks.com/da/blogs/magisso/tagged/modernization | B703: Fra hurtige rengøringstips til de seneste nyheder, har vores blog alt, hvad du behøver for at holde dig informeret og blive inspireret til en renere og sundere livsstil! | C703: 169
A704: https://happy-sinks.com/da/blogs/magisso/tagged/scandinavian-sink-accessories | B704: Fra hurtige rengøringstips til de seneste nyheder, har vores blog alt, hvad du behøver for at holde dig informeret og blive inspireret til en renere og sundere livsstil! | C704: 169
A705: https://happy-sinks.com/da/blogs/magisso/tagged/wellbeing | B705: Fra hurtige rengøringstips til de seneste nyheder, har vores blog alt, hvad du behøver for at holde dig informeret og blive inspireret til en renere og sundere livsstil! | C705: 169
A706: https://happy-sinks.com/fi/blogs/magisso/tagged/society | B706: Nopeat siivousvinkit ja viimeisimmät uutiset – blogistamme löydät kaiken, mitä tarvitset pysyäksesi ajan tasalla ja saadaksesi inspiraatiota puhtaampaan ja terveellisempään elämäntapaan! | C706: 186
...

Sheet HS_Pages droped from top 10 Pos
A1: URL | B1: Organic traffic | C1: Organic traffic previous | D1: No. of referring domains | E1: No. of referring domains previous | F1: No. of backlinks | G1: No. of backlinks previous | H1: No. of dofollow backlinks | I1: No. of dofollow backlinks previous | J1: No. of keywords with Top 3 position | K1: No. of keywords with Top 3 position previous | L1: No. of keywords with Top 10 position | M1: No. of keywords with Top 10 position previous | N1: No. of all inlinks | O1: No. of all inlinks previous | P1: Top keyword | Q1: Top keyword previous | R1: Top keyword position previous | T1: =HYPERLINK("#'Master Overview'!A1","<< Master Overview") -> << Master Overview
A2: https://happy-sinks.com/ | B2: 0 | C2: 249 | D2: 0 | E2: 761 | F2: 0 | G2: 921 | H2: 0 | I2: 543 | J2: 0 | K2: 6 | L2: 0 | M2: 16 | N2: 435 | O2: 423 | Q2: how to sanitize sponges | R2: 8 | T2: Source: https_happy-sinks.com_ - URL Report.xlsx / Pages droped from top 10 Possit
A3: https://happy-sinks.com/collections/all | B3: 0 | C3: 19 | D3: 0 | E3: 0 | F3: 0 | G3: 0 | H3: 0 | I3: 0 | J3: 0 | K3: 3 | L3: 0 | M3: 7 | N3: 501 | O3: 489 | Q3: happy sinks | R3: 5
A4: https://happy-sinks.com/collections/cloth-holders | B4: 0 | C4: 946 | D4: 0 | E4: 1 | F4: 0 | G4: 1 | H4: 0 | I4: 1 | J4: 0 | K4: 26 | L4: 0 | M4: 35 | N4: 504 | O4: 483 | Q4: disktrasehållare | R4: 1
A5: https://happy-sinks.com/collections/sponge-holders | B5: 0 | C5: 349 | D5: 0 | E5: 1 | F5: 0 | G5: 1 | H5: 0 | I5: 1 | J5: 0 | K5: 27 | L5: 0 | M5: 50 | N5: 453 | O5: 435 | Q5: sponge holder for sink | R5: 2
A6: https://happy-sinks.com/pages/installation | B6: 0 | C6: 1 | D6: 0 | E6: 0 | F6: 0 | G6: 0 | H6: 0 | I6: 0 | J6: 0 | K6: 0 | L6: 0 | M6: 3 | N6: 434 | O6: 400 | Q6: happy sinks dishcloth holder | R6: 5
A7: https://happy-sinks.com/products/potato-washer | B7: 0 | C7: 0 | D7: 0 | E7: 390 | F7: 0 | G7: 428 | H7: 0 | I7: 111 | J7: 0 | K7: 0 | L7: 0 | M7: 1 | N7: 403 | O7: 383 | Q7: potatistvätt | R7: 6
A8: https://happy-sinks.com/sv/collections/all | B8: 0 | C8: 0 | D8: 0 | E8: 0 | F8: 0 | G8: 0 | H8: 0 | I8: 0 | J8: 0 | K8: 1 | L8: 0 | M8: 1 | N8: 131 | O8: 372 | Q8: happy sink | R8: 1
A9: https://happy-sinks.com/sv/products/potato-washer | B9: 0 | C9: 0 | D9: 0 | E9: 0 | F9: 0 | G9: 0 | H9: 0 | I9: 0 | J9: 0 | K9: 1 | L9: 0 | M9: 1 | N9: 128 | O9: 369 | Q9: potturi | R9: 3
A10: https://happy-sinks.com/sv/pages/faq | B10: 0 | C10: 0 | D10: 0 | E10: 0 | F10: 0 | G10: 0 | H10: 0 | I10: 0 | J10: 0 | K10: 1 | L10: 0 | M10: 1 | N10: 131 | O10: 372 | Q10: happy sink | R10: 1
A11: https://happy-sinks.com/sv | B11: 0 | C11: 32 | D11: 0 | E11: 0 | F11: 0 | G11: 0 | H11: 0 | I11: 0 | J11: 0 | K11: 2 | L11: 0 | M11: 3 | N11: 131 | O11: 372 | Q11: happy sinks | R11: 2
A12: https://happy-sinks.com/products/dish-cloth-holder-bio-composite-charcoal | B12: 0 | C12: 0 | D12: 0 | E12: 5 | F12: 0 | G12: 12 | H12: 0 | I12: 4 | J12: 0 | K12: 0 | L12: 0 | M12: 5 | N12: 128 | O12: 110 | Q12: dish cloth holder for sink | R12: 5
A13: https://happy-sinks.com/sv/collections/cloth-holders | B13: 0 | C13: 175 | D13: 0 | E13: 0 | F13: 0 | G13: 0 | H13: 0 | I13: 0 | J13: 0 | K13: 8 | L13: 0 | M13: 18 | N13: 131 | O13: 372 | Q13: hållare disktrasa | R13: 5
A14: https://happy-sinks.com/products/dish-cloth-holder-steel | B14: 0 | C14: 0 | D14: 0 | E14: 6 | F14: 0 | G14: 22 | H14: 0 | I14: 21 | J14: 0 | K14: 0 | L14: 0 | M14: 1 | N14: 89 | O14: 72 | Q14: happy sinks dish cloth holder | R14: 7
... A69: https://happy-sinks.com/blogs/magisso/quick-cleaning-tips-you-can-tackle-in-5-minutes-or-less | B69: 0 | C69: 5 | D69: 0 | E69: 0 | F69: 0 | G69: 0 | H69: 0 | I69: 0 | J69: 0 | K69: 0 | L69: 0 | M69: 1 | N69: 48 | O69: 49 | Q69: speedy cleaning tips | R69: 6
A70: https://happy-sinks.com/fi/blogs/magisso/how-to-clean-a-sponge | B70: 0 | C70: 5 | D70: 0 | E70: 0 | F70: 0 | G70: 0 | H70: 0 | I70: 0 | J70: 0 | K70: 0 | L70: 0 | M70: 1 | N70: 15 | O70: 15
A71: https://happy-sinks.com/es/blogs/magisso/quick-tips-and-tricks-on-how-to-clean-an-oven-at-home | B71: 0 | C71: 1 | D71: 0 | E71: 0 | F71: 0 | G71: 0 | H71: 0 | I71: 0 | J71: 0 | K71: 0 | L71: 0 | M71: 1 | N71: 8 | O71: 13 | Q71: cómo limpiar la puerta del horno | R71: 8
A72: https://happy-sinks.com/sv/blogs/magisso/how-to-get-rid-of-fruit-flies-summer-tips-for-a-fruit-fly-free-home | B72: 0 | C72: 7 | D72: 0 | E72: 0 | F72: 0 | G72: 0 | H72: 0 | I72: 0 | J72: 0 | K72: 0 | L72: 0 | M72: 1 | N72: 8 | O72: 9 | Q72: hur länge lever en bananfluga | R72: 9
A73: https://happy-sinks.com/sv/blogs/magisso/15-most-asked-questions-about-kitchen-towels-and-where-to-keep-them | B73: 0 | C73: 2 | D73: 0 | E73: 0 | F73: 0 | G73: 0 | H73: 0 | I73: 0 | J73: 0 | K73: 0 | L73: 0 | M73: 3 | N73: 8 | O73: 13 | Q73: koka disktrasor | R73: 6
A74: https://happy-sinks.com/es/blogs/magisso/12-quick-cleaning-tips-you-can-tackle-in-5-minutes-part-2 | B74: 0 | C74: 12 | D74: 0 | E74: 0 | F74: 0 | G74: 0 | H74: 0 | I74: 0 | J74: 0 | K74: 1 | L74: 0 | M74: 5 | N74: 8 | O74: 13 | Q74: cómo se limpia | R74: 8
A75: https://happy-sinks.com/de/blogs/magisso/fruit-fly-control-simple-solutions-for-a-pest-free-kitchen | B75: 0 | C75: 524 | D75: 0 | E75: 0 | F75: 0 | G75: 0 | H75: 0 | I75: 0 | J75: 0 | K75: 8 | L75: 0 | M75: 22 | N75: 13 | O75: 14 | Q75: was hilft gegen obstfliegen | R75: 7
A76: https://happy-sinks.com/blogs/magisso/15-most-asked-questions-about-kitchen-towels-and-where-to-keep-them | B76: 0 | C76: 1 | D76: 0 | E76: 0 | F76: 0 | G76: 0 | H76: 0 | I76: 0 | J76: 0 | K76: 0 | L76: 0 | M76: 1 | N76: 35 | O76: 31 | Q76: where to hang wet dish cloth | R76: 7
A77: https://happy-sinks.com/da/products/kitchen-set-dish-cloth-holder-sponge-holder-fruit-fly-trap | B77: 0 | C77: 0 | D77: 0 | E77: 0 | F77: 0 | G77: 0 | H77: 0 | I77: 0 | J77: 0 | K77: 0 | L77: 0 | M77: 1 | N77: 9 | O77: 9 | Q77: karkludeholder | R77: 10
A78: https://happy-sinks.com/de/products/wine-glass-rack | B78: 0 | C78: 3 | D78: 0 | E78: 0 | F78: 0 | G78: 0 | H78: 0 | I78: 0 | J78: 0 | K78: 0 | L78: 0 | M78: 1 | N78: 18 | O78: 24 | Q78: weinglashalter spülmaschine | R78: 9
A79: https://happy-sinks.com/de/products/kitchen-sink-mat-silicone | B79: 0 | C79: 0 | D79: 0 | E79: 0 | F79: 0 | G79: 0 | H79: 0 | I79: 0 | J79: 0 | K79: 0 | L79: 0 | M79: 1 | N79: 28 | O79: 44 | Q79: spülmatte silikon | R79: 10
A80: https://happy-sinks.com/collections/dishcloth-holder | B80: 0 | C80: 6 | D80: 0 | E80: 0 | F80: 0 | G80: 0 | H80: 0 | I80: 0 | J80: 0 | K80: 0 | L80: 0 | M80: 4 | N80: 16 | O80: 16 | Q80: swedish dishcloth holder | R80: 6
A81: https://happy-sinks.com/fi/blogs/magisso/quick-tips-and-tricks-on-how-to-clean-an-oven-at-home | B81: 0 | C81: 1 | D81: 0 | E81: 0 | F81: 0 | G81: 0 | H81: 0 | I81: 0 | J81: 0 | K81: 0 | L81: 0 | M81: 1 | N81: 13 | O81: 14 | Q81: hedelmäkärpäsistä eroon | R81: 6
A82: https://happy-sinks.com/sv/blogs/magisso/the-do-s-and-donts-of-how-to-use-swedish-dishcloths | B82: 0 | C82: 2 | D82: 0 | E82: 0 | F82: 0 | G82: 0 | H82: 0 | I82: 0 | J82: 0 | K82: 0 | L82: 0 | M82: 1 | N82: 8 | O82: 14 | Q82: tvätta disktrasor | R82: 8
... A94: https://happy-sinks.com/sv/blogs/magisso/small-kitchen-solutions | B94: 0 | C94: 3 | D94: 0 | E94: 0 | F94: 0 | G94: 0 | H94: 0 | I94: 0 | J94: 0 | K94: 1 | L94: 0 | M94: 1 | N94: 8 | O94: 14 | Q94: kompakt kök | R94: 3
A95: https://happy-sinks.com/en-ca/blogs/magisso/how-to-clean-a-sponge | B95: 0 | C95: 351 | D95: 0 | E95: 0 | F95: 0 | G95: 0 | H95: 0 | I95: 0 | J95: 0 | K95: 0 | L95: 0 | M95: 1 | N95: 9 | O95: 15
A96: https://happy-sinks.com/es/blogs/magisso/the-do-s-and-donts-of-how-to-use-swedish-dishcloths | B96: 0 | C96: 0 | D96: 0 | E96: 0 | F96: 0 | G96: 0 | H96: 0 | I96: 0 | J96: 0 | K96: 0 | L96: 0 | M96: 1 | N96: 10 | O96: 14 | Q96: paños suecos | R96: 4
A97: https://happy-sinks.com/de/blogs/magisso/how-to-clean-stinky-dishcloths | B97: 0 | C97: 2 | D97: 0 | E97: 0 | F97: 0 | G97: 0 | H97: 0 | I97: 0 | J97: 0 | K97: 0 | L97: 0 | M97: 2 | N97: 13 | O97: 13 | Q97: spüllappen waschen | R97: 8
A98: https://happy-sinks.com/pages/mioeco-simple-sustainable-living | B98: 0 | C98: 0 | D98: 0 | E98: 0 | F98: 0 | G98: 0 | H98: 0 | I98: 0 | J98: 0 | K98: 0 | L98: 0 | M98: 1 | N98: 16 | O98: 16 | Q98: mioeco | R98: 4
A99: https://happy-sinks.com/de/products/kitchen-set-wine-glass-holder-sink-mats | B99: 0 | C99: 0 | D99: 0 | E99: 0 | F99: 0 | G99: 0 | H99: 0 | I99: 0 | J99: 0 | K99: 1 | L99: 0 | M99: 1 | N99: 9 | O99: 9 | Q99: happy sinks | R99: 1

Sheet OGU_Blog Pages
Y1: =HYPERLINK("#'Master Overview'!A1","<< Master Overview") -> << Master Overview
Y2: Source: opengoaaalusa.com - Blog Content_.xlsx / Blog Pages
B5: Top pages | C5: Last 6 months Clicks | D5: Previous 6 months Clicks | E5: Clicks Difference | F5: Last 6 months Impressions | G5: Previous 6 months Impressions | H5: Impressions Difference | I5: Content Sheet | J5: Suggested Meta Title | K5: Suggested Meta Description | L5: Internal Linking Status | W5: Status
B6: https://opengoaaalusa.com/blogs/news/soccer-drills-for-8-year-olds | C6: 977 | D6: 2510 | E6: =C6-D6 -> -1533 | F6: 27955 | G6: 44666 | H6: =F6-G6 -> -16711
B7: https://opengoaaalusa.com/blogs/news/soccer-ball-sizes | C7: 752 | D7: 290 | E7: =C7-D7 -> 462 | F7: 26191 | G7: 35458 | H7: =F7-G7 -> -9267
B8: https://opengoaaalusa.com/blogs/news/soccer-ball-size-by-age | C8: 709 | D8: 1994 | E8: =C8-D8 -> -1285 | F8: 167018 | G8: 477697 | H8: =F8-G8 -> -310679
B9: https://opengoaaalusa.com/blogs/news/soccer-warm-up-drills | C9: 696 | D9: 2496 | E9: =C9-D9 -> -1800 | F9: 23805 | G9: 59927 | H9: =F9-G9 -> -36122
B10: https://opengoaaalusa.com/blogs/news/what-does-fifa-stand-for | C10: 639 | D10: 109 | E10: =C10-D10 -> 530 | F10: 325848 | G10: 211738 | H10: =F10-G10 -> 114110
B11: https://opengoaaalusa.com/blogs/news/types-of-kicks-in-soccer | C11: 445 | D11: 1473 | E11: =C11-D11 -> -1028 | F11: 64868 | G11: 115536 | H11: =F11-G11 -> -50668
B12: https://opengoaaalusa.com/blogs/news/soccer-defense-positions | C12: 362 | D12: 499 | E12: =C12-D12 -> -137 | F12: 61390 | G12: 98671 | H12: =F12-G12 -> -37281
B13: https://opengoaaalusa.com/blogs/news/10-simple-soccer-footwork-drills | C13: 356 | D13: 654 | E13: =C13-D13 -> -298 | F13: 15246 | G13: 24307 | H13: =F13-G13 -> -9061
B14: https://opengoaaalusa.com/blogs/news/famous-soccer-player-numbers | C14: 344 | D14: 1186 | E14: =C14-D14 -> -842 | F14: 51019 | G14: 152080 | H14: =F14-G14 -> -101061
B15: https://opengoaaalusa.com/blogs/news/give-and-go-drills | C15: 342 | D15: 722 | E15: =C15-D15 -> -380 | F15: 7666 | G15: 14046 | H15: =F15-G15 -> -6380
B16: https://opengoaaalusa.com/blogs/news/soccer-formations-11v11 | C16: 341 | D16: 573 | E16: =C16-D16 -> -232 | F16: 26144 | G16: 36159 | H16: =F16-G16 -> -10015
B17: https://opengoaaalusa.com/blogs/news/center-forward-vs-striker | C17: 309 | D17: 230 | E17: =C17-D17 -> 79 | F17: 92678 | G17: 99182 | H17: =F17-G17 -> -6504
... B23: https://opengoaaalusa.com/blogs/news/how-long-is-a-soccer-game | C23: 182 | D23: 492 | E23: =C23-D23 -> -310 | F23: 255383 | G23: 581555 | H23: =F23-G23 -> -326172
C24: 182 | D24: 15 | F24: 5993 | G24: 756
C25: 173 | D25: 157 | F25: 54897 | G25: 47258
B26: https://opengoaaalusa.com/blogs/news/fundamentals-of-soccer | C26: 157 | D26: 332 | E26: =C26-D26 -> -175 | F26: 11378 | G26: 26984 | H26: =F26-G26 -> -15606
B27: https://opengoaaalusa.com/blogs/news/best-soccer-rebounders | C27: 156 | D27: 0 | E27: =C27-D27 -> 156 | F27: 10011 | G27: 0 | H27: =F27-G27 -> 10011
B28: https://opengoaaalusa.com/blogs/news/what-is-a-soccer-draw | C28: 146 | D28: 180 | E28: =C28-D28 -> -34 | F28: 90524 | G28: 169188 | H28: =F28-G28 -> -78664
B29: https://opengoaaalusa.com/blogs/news/where-is-soccer-most-popular | C29: 138 | D29: 246 | E29: =C29-D29 -> -108 | F29: 12829 | G29: 23385 | H29: =F29-G29 -> -10556
B30: https://opengoaaalusa.com/blogs/news/build-a-backyard-soccer-field | C30: 124 | D30: 338 | E30: =C30-D30 -> -214 | F30: 11856 | G30: 24648 | H30: =F30-G30 -> -12792
B31: https://opengoaaalusa.com/blogs/news/yellow-card-in-soccer | C31: 121 | D31: 248 | E31: =C31-D31 -> -127 | F31: 77675 | G31: 189501 | H31: =F31-G31 -> -111826
C32: 119 | D32: 17 | F32: 19922 | G32: 3203
C33: 113 | D33: 16 | F33: 28891 | G33: 5293
B34: https://opengoaaalusa.com/blogs/news/rules-of-soccer-a-quick-overview | C34: 111 | D34: 153 | E34: =C34-D34 -> -42 | F34: 19449 | G34: 36991 | H34: =F34-G34 -> -17542
B35: https://opengoaaalusa.com/blogs/news/soccer-tic-tac-toe | C35: 111 | D35: 420 | E35: =C35-D35 -> -309 | F35: 5634 | G35: 14592 | H35: =F35-G35 -> -8958
B36: https://opengoaaalusa.com/blogs/news/soccer-conditioning-drills | C36: 110 | D36: 1071 | E36: =C36-D36 -> -961 | F36: 11129 | G36: 38585 | H36: =F36-G36 -> -27456
C37: 109 | D37: 12 | F37: 4657 | G37: 378
B38: https://opengoaaalusa.com/blogs/news/soccer-attacking-drills | C38: 104 | D38: 434 | E38: =C38-D38 -> -330 | F38: 5003 | G38: 11701 | H38: =F38-G38 -> -6698
C39: 103 | D39: 5 | F39: 56369 | G39: 11288
B40: https://opengoaaalusa.com/blogs/news/soccer-transition-drills | C40: 103 | D40: 481 | E40: =C40-D40 -> -378 | F40: 4494 | G40: 10069 | H40: =F40-G40 -> -5575
C41: 99 | D41: 46 | F41: 58733 | G41: 38342
C42: 92 | D42: 21 | F42: 13108 | G42: 1865
C43: 88 | D43: 0 | F43: 1734 | G43: 0
B44: https://opengoaaalusa.com/blogs/news/soccer-nutmeg | C44: 87 | D44: 150 | E44: =C44-D44 -> -63 | F44: 103058 | G44: 107529 | H44: =F44-G44 -> -4471
B45: https://opengoaaalusa.com/blogs/news/what-to-eat-before-a-soccer-game | C45: 86 | D45: 722 | E45: =C45-D45 -> -636 | F45: 27222 | G45: 74658 | H45: =F45-G45 -> -47436
B46: https://opengoaaalusa.com/blogs/news/fun-soccer-games-for-kids | C46: 86 | D46: 1746 | E46: =C46-D46 -> -1660 | F46: 9386 | G46: 50227 | H46: =F46-G46 -> -40841
C47: 85 | D47: 0 | F47: 3089 | G47: 0
C48: 82 | D48: 21 | F48: 15590 | G48: 5877
C49: 80 | D49: 18 | F49: 32279 | G49: 14322
C50: 80 | D50: 22 | F50: 4602 | G50: 2752
B51: https://opengoaaalusa.com/blogs/news/what-is-a-soccer-kickoff | C51: 78 | D51: 250 | E51: =C51-D51 -> -172 | F51: 45837 | G51: 80227 | H51: =F51-G51 -> -34390
B52: https://opengoaaalusa.com/blogs/news/5-kids-soccer-drills-to-improve-shooting | C52: 77 | D52: 57 | E52: =C52-D52 -> 20 | F52: 3180 | G52: 4387 | H52: =F52-G52 -> -1207
B53: https://opengoaaalusa.com/blogs/news/penalty-box-soccer | C53: 76 | D53: 92 | E53: =C53-D53 -> -16 | F53: 35026 | G53: 66235 | H53: =F53-G53 -> -31209
C54: 76 | D54: 28 | F54: 17567 | G54: 5119
B55: https://opengoaaalusa.com/blogs/news/how-to-train-like-ronaldo-with-workouts-and-drills | C55: 75 | D55: 354 | E55: =C55-D55 -> -279 | F55: 15856 | G55: 99905 | H55: =F55-G55 -> -84049
C56: 74 | D56: 20 | F56: 2957 | G56: 1800
B57: https://opengoaaalusa.com/blogs/news/soccer-lingo-common-soccer-terms-every-player-should-know | C57: 73 | D57: 166 | E57: =C57-D57 -> -93 | F57: 22140 | G57: 44150 | H57: =F57-G57 -> -22010
C58: 72 | D58: 21 | F58: 10623 | G58: 2883
B59: https://opengoaaalusa.com/blogs/news/soccer-possession-drills | C59: 70 | D59: 144 | E59: =C59-D59 -> -74 | F59: 4104 | G59: 8981 | H59: =F59-G59 -> -4877
C60: 65 | D60: 24 | F60: 20084 | G60: 10610
B61: https://opengoaaalusa.com/blogs/news/5-practical-ways-to-keep-soccer-balls-in-your-backyard-and-keep-the-neighbors-happy | C61: 65 | D61: 90 | E61: =C61-D61 -> -25 | F61: 4666 | G61: 8076 | H61: =F61-G61 -> -3410
C62: 65 | D62: 11 | F62: 2738 | G62: 566
C63: 65 | D63: 0 | F63: 1721 | G63: 0
B64: https://opengoaaalusa.com/blogs/news/red-card-in-soccer | C64: 64 | D64: 148 | E64: =C64-D64 -> -84 | F64: 50078 | G64: 143785 | H64: =F64-G64 -> -93707
C65: 63 | D65: 27 | F65: 44999 | G65: 28317
C66: 60 | D66: 20 | F66: 4423 | G66: 2063
B67: https://opengoaaalusa.com/blogs/news/regulation-soccer-goal-sizes | C67: 59 | D67: 155 | E67: =C67-D67 -> -96 | F67: 50022 | G67: 105502 | H67: =F67-G67 -> -55480
C68: 59 | D68: 0 | F68: 1416 | G68: 0
B69: https://opengoaaalusa.com/blogs/news/the-best-female-soccer-players-of-all-time | C69: 56 | D69: 483 | E69: =C69-D69 -> -427 | F69: 33979 | G69: 119481 | H69: =F69-G69 -> -85502
B70: https://opengoaaalusa.com/blogs/news/what-is-a-soccer-rebounder-and-why-every-player-needs-one-in-2025 | C70: 54 | D70: 269 | E70: =C70-D70 -> -215 | F70: 7517 | G70: 36713 | H70: =F70-G70 -> -29196
C71: 53 | D71: 8 | F71: 2228 | G71: 295
B72: https://opengoaaalusa.com/blogs/news/the-best-soccer-goalies-of-all-time-top-10-legends | C72: 49 | D72: 290 | E72: =C72-D72 -> -241 | F72: 114275 | G72: 196101 | H72: =F72-G72 -> -81826
C73: 49 | D73: 11 | F73: 3626 | G73: 698
C74: 48 | D74: 6 | F74: 5079 | G74: 146
B75: https://opengoaaalusa.com/blogs/news/how-to-dribble-like-messi-mastering-the-art-of-soccer-dribbling | C75: 42 | D75: 109 | E75: =C75-D75 -> -67 | F75: 10273 | G75: 20642 | H75: =F75-G75 -> -10369
B76: https://opengoaaalusa.com/blogs/news/what-is-a-goal-kick-in-soccer | C76: 40 | D76: 66 | E76: =C76-D76 -> -26 | F76: 26704 | G76: 66786 | H76: =F76-G76 -> -40082
B77: https://opengoaaalusa.com/blogs/news/goalie-drills | C77: 40 | D77: 506 | E77: =C77-D77 -> -466 | F77: 9794 | G77: 31523 | H77: =F77-G77 -> -21729
B78: https://opengoaaalusa.com/blogs/news/messi-training | C78: 40 | D78: 64 | E78: =C78-D78 -> -24 | F78: 8408 | G78: 16087 | H78: =F78-G78 -> -7679
B79: https://opengoaaalusa.com/blogs/news/what-is-a-cap-in-soccer | C79: 39 | D79: 54 | E79: =C79-D79 -> -15 | F79: 70782 | G79: 60193 | H79: =F79-G79 -> 10589
B80: https://opengoaaalusa.com/blogs/news/how-to-punt-a-soccer-ball | C80: 39 | D80: 141 | E80: =C80-D80 -> -102 | F80: 8158 | G80: 23448 | H80: =F80-G80 -> -15290
B81: https://opengoaaalusa.com/blogs/news/1v1-soccer-drills | C81: 39 | D81: 321 | E81: =C81-D81 -> -282 | F81: 4335 | G81: 15110 | H81: =F81-G81 -> -10775
B82: https://opengoaaalusa.com/blogs/news/toe-tap-soccer | C82: 38 | D82: 78 | E82: =C82-D82 -> -40 | F82: 13676 | G82: 15965 | H82: =F82-G82 -> -2289
C83: 38 | D83: 6 | F83: 1805 | G83: 416
B84: https://opengoaaalusa.com/blogs/news/when-is-soccer-season | C84: 37 | D84: 259 | E84: =C84-D84 -> -222 | F84: 76534 | G84: 216297 | H84: =F84-G84 -> -139763
C85: 37 | D85: 3 | F85: 11625 | G85: 1512
B86: https://opengoaaalusa.com/blogs/news/the-best-female-american-soccer-players | C86: 37 | D86: 87 | E86: =C86-D86 -> -50 | F86: 8278 | G86: 30625 | H86: =F86-G86 -> -22347
C87: 37 | D87: 3 | F87: 6421 | G87: 1771
C88: 35 | D88: 70 | F88: 3162 | G88: 4211
C89: 34 | D89: 8 | F89: 8983 | G89: 5471
B90: https://opengoaaalusa.com/blogs/news/ronaldo-dribbling | C90: 34 | D90: 13 | E90: =C90-D90 -> 21 | F90: 5638 | G90: 5554 | H90: =F90-G90 -> 84
B91: https://opengoaaalusa.com/blogs/news/what-is-a-brace-in-soccer | C91: 33 | D91: 180 | E91: =C91-D91 -> -147 | F91: 71463 | G91: 182542 | H91: =F91-G91 -> -111079
C92: 33 | D92: 6 | F92: 6335 | G92: 2289
C93: 33 | D93: 13 | F93: 3780 | G93: 1287
C94: 33 | D94: 0 | F94: 1849 | G94: 0
C95: 32 | D95: 0 | F95: 6205 | G95: 361
B96: https://opengoaaalusa.com/blogs/news/the-best-bicycle-kicks-in-history | C96: 31 | D96: 62 | E96: =C96-D96 -> -31 | F96: 15474 | G96: 19689 | H96: =F96-G96 -> -4215
C97: 31 | D97: 5 | F97: 13770 | G97: 7000
C98: 31 | D98: 25 | F98: 12634 | G98: 10282
B99: https://opengoaaalusa.com/blogs/news/sharks-and-minnows | C99: 31 | D99: 171 | E99: =C99-D99 -> -140 | F99: 8142 | G99: 24466 | H99: =F99-G99 -> -16324
C100: 31 | D100: 7 | F100: 3845 | G100: 883
C101: 31 | D101: 14 | F101: 1779 | G101: 1234
B102: https://opengoaaalusa.com/blogs/news/goals-and-glories-tracing-the-origins-of-english-football-club-names | C102: 30 | D102: 161 | E102: =C102-D102 -> -131 | F102: 36944 | G102: 147561 | H102: =F102-G102 -> -110617
B103: https://opengoaaalusa.com/blogs/news/best-soccer-backpacks | C103: 30 | D103: 107 | E103: =C103-D103 -> -77 | F103: 7780 | G103: 31276 | H103: =F103-G103 -> -23496
B104: https://opengoaaalusa.com/blogs/news/rondo-soccer | C104: 30 | D104: 139 | E104: =C104-D104 -> -109 | F104: 5390 | G104: 16021 | H104: =F104-G104 -> -10631
B105: https://opengoaaalusa.com/blogs/news/what-is-the-best-soccer-rebounder | C105: 30 | D105: 60 | E105: =C105-D105 -> -30 | F105: 3640 | G105: 7967 | H105: =F105-G105 -> -4327
B106: https://opengoaaalusa.com/blogs/news/handball-in-soccer | C106: 29 | D106: 117 | E106: =C106-D106 -> -88 | F106: 47608 | G106: 70694 | H106: =F106-G106 -> -23086
C107: 29 | D107: 10 | F107: 42144 | G107: 35455
...

Sheet OGU_Countries
A1: Country | B1: Last 6 months Clicks | C1: Previous 6 months Clicks | D1: Last 6 months Impressions | E1: Previous 6 months Impressions | F1: Last 6 months CTR | G1: Previous 6 months CTR | H1: Last 6 months Position | I1: Previous 6 months Position | K1: =HYPERLINK("#'Master Overview'!A1","<< Master Overview") -> << Master Overview
A2: United States | B2: 4302 | C2: 10359 | D2: 1087843 | E2: 1748564 | F2: 0.004 | G2: 0.0059 | H2: 13.55 | I2: 11.95 | K2: Source: opengoaaalusa.com - Blog Content_.xlsx / Countries
A3: Canada | B3: 625 | C3: 1050 | D3: 131857 | E3: 120419 | F3: 0.0047 | G3: 0.0087 | H3: 14.93 | I3: 15.07
A4: United Kingdom | B4: 262 | C4: 525 | D4: 108616 | E4: 129549 | F4: 0.0024 | G4: 0.0041 | H4: 18.83 | I4: 18.73
A5: Australia | B5: 195 | C5: 300 | D5: 46767 | E5: 62536 | F5: 0.0042 | G5: 0.0048 | H5: 26.81 | I5: 22.3
A6: Mexico | B6: 62 | C6: 41 | D6: 42187 | E6: 63779 | F6: 0.0015 | G6: 0.0006 | H6: 14.62 | I6: 12.21
A7: Brazil | B7: 58 | C7: 38 | D7: 32578 | E7: 36144 | F7: 0.0018 | G7: 0.0011 | H7: 14.14 | I7: 11.9
A8: Spain | B8: 44 | C8: 85 | D8: 29574 | E8: 28355 | F8: 0.0015 | G8: 0.003 | H8: 25.98 | I8: 24.85
A9: Kenya | B9: 41 | C9: 95 | D9: 4205 | E9: 12086 | F9: 0.0098 | G9: 0.0079 | H9: 10.79 | I9: 10.34
A10: Colombia | B10: 36 | C10: 22 | D10: 22996 | E10: 30872 | F10: 0.0016 | G10: 0.0007 | H10: 11.08 | I10: 11.42
A11: Nigeria | B11: 36 | C11: 61 | D11: 20066 | E11: 38329 | F11: 0.0018 | G11: 0.0016 | H11: 36.22 | I11: 25.91
A12: India | B12: 30 | C12: 52 | D12: 41892 | E12: 63793 | F12: 0.0007 | G12: 0.0008 | H12: 25.5 | I12: 21.02
A13: Portugal | B13: 29 | C13: 10 | D13: 3960 | E13: 2515 | F13: 0.0073 | G13: 0.004 | H13: 11.97 | I13: 12.77
A14: Ecuador | B14: 28 | C14: 35 | D14: 11419 | E14: 12323 | F14: 0.0025 | G14: 0.0028 | H14: 11.65 | I14: 11.01
... A237: Svalbard & Jan Mayen | B237: 0 | C237: 0 | D237: 0 | E237: 1 | F237: 0 | G237: 0 | H237: 0 | I237: 22

Sheet OGU_Filters
A1: Filter | B1: Value | D1: =HYPERLINK("#'Master Overview'!A1","<< Master Overview") -> << Master Overview
A2: Search type | B2: Web | D2: Source: opengoaaalusa.com - Blog Content_.xlsx / Filters
A3: Date | B3: Last 6 months
A4: Page | B4: +/blogs/news/

Sheet SV_4xx
I1: =HYPERLINK("#'Master Overview'!A1","<< Master Overview") -> << Master Overview
I2: Source: striking-viking - Issues.xlsx / 4xx
A3: 4xx Pages
A4: Sr. no | B4: First fount at | C4: Source HTTP status code | D4: Target URL | E4: Target HTTP status code | F4: Anchor | G4: Status
A5: 1 | B5: https://striking-viking.com/products/striking-viking-hybrid-beard-growth-bundle-with-sandalwood-unscented-beard-oils-and-derma-roller | C5: 200 | D5: https://account.striking-viking.com/?locale=en&buyer_flags=eyJhbGciOiJIUzI1NiJ9.eyJpc3MiOiJzdHJpa2luZy12aWtpbmcubXlzaG9waWZ5LmNvbSIsImZsYWdzIjpbXSwiZXhwIjoxNzkxMjkzMDA1LCJuYmYiOjE3OTA2ODgyMDV9.ekRgv3Rn4dJGKJKXV0HPH6qN8mfdRQsvmnxv_GsNPOQ | E5: 406 | F5: Create account
A6: 2 | B6: https://striking-viking.com/products/charlemagne-carbon-wide-tooth-comb-for-men-heat-resistant-carbon-fiber-hair-comb | C6: 200 | D6: https://account.striking-viking.com/?locale=en&buyer_flags=eyJhbGciOiJIUzI1NiJ9.eyJpc3MiOiJzdHJpa2luZy12aWtpbmcubXlzaG9waWZ5LmNvbSIsImZsYWdzIjpbXSwiZXhwIjoxNzkxMjkyNTU3LCJuYmYiOjE3OTA2ODc3NTd9.AuzQ5WktWnMKf0rqSUIlmpQ8aNTqxQgV3bP3dg8iYrU | E6: 406 | F6: Create account
A7: 3 | B7: https://striking-viking.com/products/shipping-protection | C7: 200 | D7: https://account.striking-viking.com/?locale=en&buyer_flags=eyJhbGciOiJIUzI1NiJ9.eyJpc3MiOiJzdHJpa2luZy12aWtpbmcubXlzaG9waWZ5LmNvbSIsImZsYWdzIjpbXSwiZXhwIjoxNzkxMjkyNzY3LCJuYmYiOjE3OTA2ODc5Njd9.QZ1__YzzSDI4MgTpeCVO_jRprB2AFk0lWxdG3VFBKRk | E7: 406 | F7: Create account
A8: 4 | B8: https://striking-viking.com/products/gift-wrapping | C8: 200 | D8: https://account.striking-viking.com/?locale=en&buyer_flags=eyJhbGciOiJIUzI1NiJ9.eyJpc3MiOiJzdHJpa2luZy12aWtpbmcubXlzaG9waWZ5LmNvbSIsImZsYWdzIjpbXSwiZXhwIjoxNzkxMjkyNzM1LCJuYmYiOjE3OTA2ODc5MzV9.uHZaFad2ROSZt8QKOQgsV1moHcoUmAgLhu2E28GNXBI | E8: 406 | F8: Create account
A9: 5 | B9: https://striking-viking.com/products/ontaki-hair-thinning-shears-kit-7-inch-professional-hair-cutting-texturizing-set | C9: 200 | D9: https://account.striking-viking.com/?locale=en&buyer_flags=eyJhbGciOiJIUzI1NiJ9.eyJpc3MiOiJzdHJpa2luZy12aWtpbmcubXlzaG9waWZ5LmNvbSIsImZsYWdzIjpbXSwiZXhwIjoxNzkxMjkyMTY1LCJuYmYiOjE3OTA2ODczNjV9.gXiAFPzHSDRucSMV_UA_hPSdDlnTCiSPXfvkcsgzLeM | E9: 406 | F9: Create account
A10: 6 | B10: https://striking-viking.com/products/striking-viking-blue-ocean-beard-oil-for-men-natural-beard-growth-oil-with-argan-jojoba | C10: 200 | D10: https://account.striking-viking.com/?locale=en&buyer_flags=eyJhbGciOiJIUzI1NiJ9.eyJpc3MiOiJzdHJpa2luZy12aWtpbmcubXlzaG9waWZ5LmNvbSIsImZsYWdzIjpbXSwiZXhwIjoxNzkxMjkyMzc1LCJuYmYiOjE3OTA2ODc1NzV9.GTAuVtfBTUYi0xI_OohkoUPCIhbtZt9vJJOHK2tIWls | E10: 406 | F10: Create account
A11: 7 | B11: https://striking-viking.com/products/striking-viking-beard-oil-variety-4-pack-citrus-vanilla-cedarwood-sandalwood | C11: 200 | D11: https://account.striking-viking.com/?locale=en&buyer_flags=eyJhbGciOiJIUzI1NiJ9.eyJpc3MiOiJzdHJpa2luZy12aWtpbmcubXlzaG9waWZ5LmNvbSIsImZsYWdzIjpbXSwiZXhwIjoxNzkxMjkxMzg1LCJuYmYiOjE3OTA2ODY1ODV9.DY84dwmJuY18KPeqicT0qbvqeZ422HDfMbFvUxKf2LM | E11: 406 | F11: Create account
A12: 8 | B12: https://striking-viking.com/products/striking-viking-vanilla-beard-growth-kit-with-biotin-oil-0-25mm-derma-roller | C12: 200 | D12: https://account.striking-viking.com/?locale=en&buyer_flags=eyJhbGciOiJIUzI1NiJ9.eyJpc3MiOiJzdHJpa2luZy12aWtpbmcubXlzaG9waWZ5LmNvbSIsImZsYWdzIjpbXSwiZXhwIjoxNzkxMjkzMjQ1LCJuYmYiOjE3OTA2ODg0NDV9.-lSCQZQFHe_PyDYdQYofF7-jjwR8zLNNTPf9Zzz80jg | E12: 406 | F12: Create account
A13: 9 | B13: https://striking-viking.com/products/striking-viking-sandalwood-beard-shampoo-for-clean-healthy-soft-beard-care-for-men | C13: 200 | D13: https://account.striking-viking.com/?locale=en&buyer_flags=eyJhbGciOiJIUzI1NiJ9.eyJpc3MiOiJzdHJpa2luZy12aWtpbmcubXlzaG9waWZ5LmNvbSIsImZsYWdzIjpbXSwiZXhwIjoxNzkxMjkzNDg2LCJuYmYiOjE3OTA2ODg2ODZ9.mpPvaj-Xi1DKC4TqFU-hxsHNGg_b0bpQuSVMKwhahwE | E13: 406 | F13: Create account
A14: 10 | B14: https://striking-viking.com/products/striking-viking-vanilla-beard-balm-2-pack-with-natural-organic-ingredients-for-beard-styling | C14: 200 | D14: https://account.striking-viking.com/?locale=en&buyer_flags=eyJhbGciOiJIUzI1NiJ9.eyJpc3MiOiJzdHJpa2luZy12aWtpbmcubXlzaG9waWZ5LmNvbSIsImZsYWdzIjpbXSwiZXhwIjoxNzkxMjkzMTU1LCJuYmYiOjE3OTA2ODgzNTV9.GYvHjVcAIZWYN9ZNrzhtH5L9MlK825xpTNADCnuQfgI | E14: 406 | F14: Create account
A15: 11 | B15: https://striking-viking.com/products/striking-viking-bergamot-thunder-beard-balm-for-men-natural-beard-balm-with-shea-butter | C15: 200 | D15: https://account.striking-viking.com/?locale=en&buyer_flags=eyJhbGciOiJIUzI1NiJ9.eyJpc3MiOiJzdHJpa2luZy12aWtpbmcubXlzaG9waWZ5LmNvbSIsImZsYWdzIjpbXSwiZXhwIjoxNzkxMjkyNDA2LCJuYmYiOjE3OTA2ODc2MDZ9.5w8Kx2GzJtt38gy4iEkREyH8Id9rTzOh4so_-Li6s_8 | E15: 406 | F15: Create account
A16: 12 | B16: https://striking-viking.com/products/ontaki-professional-thinning-texturizing-scissors-set-6-5-inch-japanese-alloy-steel | C16: 200 | D16: https://account.striking-viking.com/?locale=en&buyer_flags=eyJhbGciOiJIUzI1NiJ9.eyJpc3MiOiJzdHJpa2luZy12aWtpbmcubXlzaG9waWZ5LmNvbSIsImZsYWdzIjpbXSwiZXhwIjoxNzkxMjkxODk1LCJuYmYiOjE3OTA2ODcwOTV9.1qoG6NVao39HmrSQk9gfHXdGZhuXwhYUypkxeUmBhkc | E16: 406 | F16: Create account
... A85: 81 | B85: https://striking-viking.com/products/ontaki-japanese-steel-beard-hair-scissors-5-5-inch-professional-grooming-shears | C85: 200 | D85: https://account.striking-viking.com/?locale=en&buyer_flags=eyJhbGciOiJIUzI1NiJ9.eyJpc3MiOiJzdHJpa2luZy12aWtpbmcubXlzaG9waWZ5LmNvbSIsImZsYWdzIjpbXSwiZXhwIjoxNzkxMjkxOTI1LCJuYmYiOjE3OTA2ODcxMjV9.dgUtVhkwWoUbGmNeE0FNtKnVpxh0RCKkGH3Ui2NNwBE | E85: 406 | F85: Create account

Sheet SV_3xx Redirection
I1: =HYPERLINK("#'Master Overview'!A1","<< Master Overview") -> << Master Overview
I2: Source: striking-viking - Issues.xlsx / 3xx Redirection
A4: 3xx Redirection
A5: Source URL | B5: Source HTTP status code | C5: Target URL | D5: Target HTTP status code | E5: Anchor | F5: Target final redirect URL | G5: Status
A6: https://striking-viking.com/products/striking-viking-beard-filler-pen-2-pack-waterproof-beard-pen-for-filling-gaps-covering-patches | B6: 200 | C6: https://striking-viking.com/customer_authentication/redirect?locale=en&region_country=US | D6: 302 | E6: Log in | F6: https://account.striking-viking.com/?buyer_flags=eyJhbGciOiJIUzI1NiJ9.eyJpc3MiOiJzdHJpa2luZy12aWtpbmcubXlzaG9waWZ5LmNvbSIsImZsYWdzIjpbXSwiZXhwIjoxNzkxMzU0NjI4LCJuYmYiOjE3OTA3NDk4Mjh9.W_JgIDP8DFSrhQ1ojmPBXziPlPpbfbt33v3WuNh9GNc&locale=en&region_country=US
A7: https://striking-viking.com/blogs/learn/combs-vs-brushes-the-beard-war-and-why-you-might-want-both | B7: 200 | C7: https://striking-viking.com/customer_authentication/redirect?locale=en&region_country=US | D7: 302 | E7: Log in | F7: https://account.striking-viking.com/?buyer_flags=eyJhbGciOiJIUzI1NiJ9.eyJpc3MiOiJzdHJpa2luZy12aWtpbmcubXlzaG9waWZ5LmNvbSIsImZsYWdzIjpbXSwiZXhwIjoxNzkxMzU0NjI4LCJuYmYiOjE3OTA3NDk4Mjh9.W_JgIDP8DFSrhQ1ojmPBXziPlPpbfbt33v3WuNh9GNc&locale=en&region_country=US
A8: https://striking-viking.com/products/beard-growth-balm-with-biotin-2-oz-blue-ocean | B8: 200 | C8: https://striking-viking.com/customer_authentication/redirect?locale=en&region_country=US | D8: 302 | E8: Log in | F8: https://account.striking-viking.com/?buyer_flags=eyJhbGciOiJIUzI1NiJ9.eyJpc3MiOiJzdHJpa2luZy12aWtpbmcubXlzaG9waWZ5LmNvbSIsImZsYWdzIjpbXSwiZXhwIjoxNzkxMzU0NjI4LCJuYmYiOjE3OTA3NDk4Mjh9.W_JgIDP8DFSrhQ1ojmPBXziPlPpbfbt33v3WuNh9GNc&locale=en&region_country=US
A9: https://striking-viking.com/products/striking-viking-bergamot-thunder-beard-oil-for-men-natural-beard-growth-oil-with-argan-jojoba | B9: 200 | C9: https://striking-viking.com/customer_authentication/redirect?locale=en&region_country=US | D9: 302 | E9: Log in | F9: https://account.striking-viking.com/?buyer_flags=eyJhbGciOiJIUzI1NiJ9.eyJpc3MiOiJzdHJpa2luZy12aWtpbmcubXlzaG9waWZ5LmNvbSIsImZsYWdzIjpbXSwiZXhwIjoxNzkxMzU0NjI4LCJuYmYiOjE3OTA3NDk4Mjh9.W_JgIDP8DFSrhQ1ojmPBXziPlPpbfbt33v3WuNh9GNc&locale=en&region_country=US
A10: https://striking-viking.com/collections/bundles | B10: 200 | C10: https://striking-viking.com/customer_authentication/redirect?locale=en&region_country=US | D10: 302 | E10: Log in | F10: https://account.striking-viking.com/?buyer_flags=eyJhbGciOiJIUzI1NiJ9.eyJpc3MiOiJzdHJpa2luZy12aWtpbmcubXlzaG9waWZ5LmNvbSIsImZsYWdzIjpbXSwiZXhwIjoxNzkxMzU0NjI4LCJuYmYiOjE3OTA3NDk4Mjh9.W_JgIDP8DFSrhQ1ojmPBXziPlPpbfbt33v3WuNh9GNc&locale=en&region_country=US
A11: https://striking-viking.com/products/striking-viking-beard-filler-pen-2-pack-dual-tip-waterproof-beard-pen-for-natural-beard-filling | B11: 200 | C11: https://striking-viking.com/customer_authentication/redirect?locale=en&region_country=US | D11: 302 | E11: Log in | F11: https://account.striking-viking.com/?buyer_flags=eyJhbGciOiJIUzI1NiJ9.eyJpc3MiOiJzdHJpa2luZy12aWtpbmcubXlzaG9waWZ5LmNvbSIsImZsYWdzIjpbXSwiZXhwIjoxNzkxMzU0NjI4LCJuYmYiOjE3OTA3NDk4Mjh9.W_JgIDP8DFSrhQ1ojmPBXziPlPpbfbt33v3WuNh9GNc&locale=en&region_country=US
A12: https://striking-viking.com/blogs/learn/46928577-tips-to-protect-your-beard-from-the-cold | B12: 200 | C12: https://striking-viking.com/customer_authentication/redirect?locale=en&region_country=US | D12: 302 | E12: Log in | F12: https://account.striking-viking.com/?buyer_flags=eyJhbGciOiJIUzI1NiJ9.eyJpc3MiOiJzdHJpa2luZy12aWtpbmcubXlzaG9waWZ5LmNvbSIsImZsYWdzIjpbXSwiZXhwIjoxNzkxMzU0NjI4LCJuYmYiOjE3OTA3NDk4Mjh9.W_JgIDP8DFSrhQ1ojmPBXziPlPpbfbt33v3WuNh9GNc&locale=en&region_country=US
A13: https://striking-viking.com/products/beard-butter-bergamot-thunder | B13: 200 | C13: https://striking-viking.com/customer_authentication/redirect?locale=en&region_country=US | D13: 302 | E13: Log in | F13: https://account.striking-viking.com/?buyer_flags=eyJhbGciOiJIUzI1NiJ9.eyJpc3MiOiJzdHJpa2luZy12aWtpbmcubXlzaG9waWZ5LmNvbSIsImZsYWdzIjpbXSwiZXhwIjoxNzkxMzU0NjI4LCJuYmYiOjE3OTA3NDk4Mjh9.W_JgIDP8DFSrhQ1ojmPBXziPlPpbfbt33v3WuNh9GNc&locale=en&region_country=US
A14: https://striking-viking.com/products/striking-viking-matte-hair-pomade-for-men-linen-scent-water-based-medium-strong-hold | B14: 200 | C14: https://striking-viking.com/customer_authentication/redirect?locale=en&region_country=US | D14: 302 | E14: Log in | F14: https://account.striking-viking.com/?buyer_flags=eyJhbGciOiJIUzI1NiJ9.eyJpc3MiOiJzdHJpa2luZy12aWtpbmcubXlzaG9waWZ5LmNvbSIsImZsYWdzIjpbXSwiZXhwIjoxNzkxMzU0NjI4LCJuYmYiOjE3OTA3NDk4Mjh9.W_JgIDP8DFSrhQ1ojmPBXziPlPpbfbt33v3WuNh9GNc&locale=en&region_country=US
A15: https://striking-viking.com/pages/spurit-invoices-cancelled | B15: 200 | C15: https://striking-viking.com/customer_authentication/redirect?locale=en&region_country=US | D15: 302 | E15: Log in | F15: https://account.striking-viking.com/?buyer_flags=eyJhbGciOiJIUzI1NiJ9.eyJpc3MiOiJzdHJpa2luZy12aWtpbmcubXlzaG9waWZ5LmNvbSIsImZsYWdzIjpbXSwiZXhwIjoxNzkxMzU0NjI4LCJuYmYiOjE3OTA3NDk4Mjh9.W_JgIDP8DFSrhQ1ojmPBXziPlPpbfbt33v3WuNh9GNc&locale=en&region_country=US
A16: https://striking-viking.com/collections/face-body | B16: 200 | C16: https://striking-viking.com/customer_authentication/redirect?locale=en&region_country=US | D16: 302 | E16: Log in | F16: https://account.striking-viking.com/?buyer_flags=eyJhbGciOiJIUzI1NiJ9.eyJpc3MiOiJzdHJpa2luZy12aWtpbmcubXlzaG9waWZ5LmNvbSIsImZsYWdzIjpbXSwiZXhwIjoxNzkxMzU0NjI4LCJuYmYiOjE3OTA3NDk4Mjh9.W_JgIDP8DFSrhQ1ojmPBXziPlPpbfbt33v3WuNh9GNc&locale=en&region_country=US
A17: https://striking-viking.com/products/striking-viking-folding-wooden-beard-comb-for-men-anti-static-sandalwood-grooming-comb | B17: 200 | C17: https://striking-viking.com/customer_authentication/redirect?locale=en&region_country=US | D17: 302 | E17: Log in | F17: https://account.striking-viking.com/?buyer_flags=eyJhbGciOiJIUzI1NiJ9.eyJpc3MiOiJzdHJpa2luZy12aWtpbmcubXlzaG9waWZ5LmNvbSIsImZsYWdzIjpbXSwiZXhwIjoxNzkxMzU0NjI4LCJuYmYiOjE3OTA3NDk4Mjh9.W_JgIDP8DFSrhQ1ojmPBXziPlPpbfbt33v3WuNh9GNc&locale=en&region_country=US
... A215: https://striking-viking.com/products/striking-viking-beard-filler-pen-2-pack-dual-tip-waterproof-beard-pen-for-natural-beard-filling?variant=52771991126358 | B215: 200 | C215: https://striking-viking.com/customer_authentication/redirect?locale=en&region_country=US | D215: 302 | E215: Log in | F215: https://account.striking-viking.com/?buyer_flags=eyJhbGciOiJIUzI1NiJ9.eyJpc3MiOiJzdHJpa2luZy12aWtpbmcubXlzaG9waWZ5LmNvbSIsImZsYWdzIjpbXSwiZXhwIjoxNzkxMzU0NjI4LCJuYmYiOjE3OTA3NDk4Mjh9.W_JgIDP8DFSrhQ1ojmPBXziPlPpbfbt33v3WuNh9GNc&locale=en&region_country=US

Sheet SV_Page has links to broken pag
K1: =HYPERLINK("#'Master Overview'!A1","<< Master Overview") -> << Master Overview
K2: Source: striking-viking - Issues.xlsx / Page has links to broken page
A3: Page has links to broken page
A4: Sr. no | B4: Source URL | C4: Source HTTP status code | D4: Target URL | E4: Target HTTP status code | F4: Anchor | G4: Target final redirect URL | H4: Target final redirect HTTP status code | I4: Status
A5: 1 | B5: https://striking-viking.com/de/blogs/learn/beard-grooming-quintessential-regime-for-the-modern-man | C5: 200 | D5: https://vikingbeardgear.com/collections/all/products/striking-viking-wooden-beard-comb | E5: 404 | F5: hölzerne Bartkamm
A6: 2 | B6: https://striking-viking.com/fr/blogs/learn/heads-shoulders-knees-and-toes-but-why-forget-the-beard | C6: 200 | D6: https://vikingbeardgear.com/collections/all/products/striking-viking-beard-grooming-kit-for-men | E6: 301 | F6: kits d'entretien de barbe | G6: https://vikingbeardgear.com/collections/viking-beard-kits/products/striking-viking-ultimate-beard-grooming-kit | H6: 404
A7: 3 | B7: https://striking-viking.com/de/blogs/learn/why-your-beard-needs-more-than-just-a-comb | C7: 200 | D7: https://vikingbeardgear.com/collections/beard-and-hair-care/products/beard-wash-shampoo-beard-conditioner-set?variant=31075723673654 | E7: 404 | F7: unparfümierte Bartbalsam
A8: 4 | B8: https://striking-viking.com/de/blogs/learn/heads-shoulders-knees-and-toes-but-why-forget-the-beard | C8: 200 | D8: https://vikingbeardgear.com/collections/all/products/striking-viking-beard-grooming-kit-for-men | E8: 301 | F8: Bartpflegesets | G8: https://vikingbeardgear.com/collections/viking-beard-kits/products/striking-viking-ultimate-beard-grooming-kit | H8: 404
A9: 5 | B9: https://striking-viking.com/en-gb/blogs/learn/beard-grooming-quintessential-regime-for-the-modern-man | C9: 200 | D9: https://vikingbeardgear.com/collections/all/products/striking-viking-wooden-beard-comb | E9: 404 | F9: wooden beard comb
A10: 6 | B10: https://striking-viking.com/sv/blogs/learn/why-your-beard-needs-more-than-just-a-comb | C10: 200 | D10: https://vikingbeardgear.com/collections/beard-and-hair-care/products/beard-wash-shampoo-beard-conditioner-set?variant=31075723673654 | E10: 404 | F10: Oparfymerade Skäggbalsam
A11: 7 | B11: https://striking-viking.com/fi/blogs/learn/grooming-products-to-pamper-your-beard-flyaway | C11: 200 | D11: https://vikingbeardgear.com/collections/beard-and-hair-care/products/beard-wash-shampoo-beard-conditioner-set?variant=31075723673654 | E11: 404 | F11: Partavoide
A12: 8 | B12: https://striking-viking.com/sv/blogs/learn/beard-grooming-quintessential-regime-for-the-modern-man | C12: 200 | D12: https://vikingbeardgear.com/collections/all/products/striking-viking-wooden-beard-comb | E12: 404 | F12: träkam för skägg
A13: 9 | B13: https://striking-viking.com/it/blogs/learn/beard-grooming-quintessential-regime-for-the-modern-man | C13: 200 | D13: https://vikingbeardgear.com/collections/all/products/striking-viking-wooden-beard-comb | E13: 404 | F13: pettine per barba in legno
A14: 10 | B14: https://striking-viking.com/en-ca/blogs/learn/grooming-kit-a-perfect-gift-for-the-modern-man | C14: 200 | D14: https://vikingbeardgear.com/collections/viking-beard-kits/products/striking-viking-ultimate-beard-grooming-kit | E14: 404 | F14: Beard Scissors
A15: 11 | B15: https://striking-viking.com/fi/blogs/learn/grooming-kit-a-perfect-gift-for-the-modern-man | C15: 200 | D15: https://vikingbeardgear.com/collections/viking-beard-kits/products/striking-viking-ultimate-beard-grooming-kit | E15: 404 | F15: Partasakset
A16: 12 | B16: https://striking-viking.com/fr-ca/blogs/learn/grooming-kit-a-perfect-gift-for-the-modern-man | C16: 200 | D16: https://vikingbeardgear.com/collections/viking-beard-kits/products/striking-viking-ultimate-beard-grooming-kit | E16: 404 | F16: Ciseaux à barbe
A17: 13 | B17: https://striking-viking.com/blogs/learn/heads-shoulders-knees-and-toes-but-why-forget-the-beard | C17: 200 | D17: https://vikingbeardgear.com/collections/all/products/striking-viking-beard-grooming-kit-for-men | E17: 301 | F17: beard grooming kits | G17: https://vikingbeardgear.com/collections/viking-beard-kits/products/striking-viking-ultimate-beard-grooming-kit | H17: 404
A18: 14 | B18: https://striking-viking.com/fr-ca/blogs/learn/heads-shoulders-knees-and-toes-but-why-forget-the-beard | C18: 200 | D18: https://vikingbeardgear.com/collections/all/products/striking-viking-beard-grooming-kit-for-men | E18: 301 | F18: kits d'entretien de barbe | G18: https://vikingbeardgear.com/collections/viking-beard-kits/products/striking-viking-ultimate-beard-grooming-kit | H18: 404
A19: 15 | B19: https://striking-viking.com/fr/blogs/learn/grooming-kit-a-perfect-gift-for-the-modern-man | C19: 200 | D19: https://vikingbeardgear.com/collections/viking-beard-kits/products/striking-viking-ultimate-beard-grooming-kit | E19: 404 | F19: Ciseaux à barbe
A20: 16 | B20: https://striking-viking.com/no/blogs/learn/beard-grooming-quintessential-regime-for-the-modern-man | C20: 200 | D20: https://vikingbeardgear.com/collections/all/products/striking-viking-wooden-beard-comb | E20: 404 | F20: kam i tre for skjegget
A21: 17 | B21: https://striking-viking.com/blogs/learn/grooming-products-to-pamper-your-beard-flyaway | C21: 200 | D21: https://vikingbeardgear.com/collections/beard-and-hair-care/products/beard-wash-shampoo-beard-conditioner-set?variant=31075723673654 | E21: 404 | F21: beard balm
A22: 18 | B22: https://striking-viking.com/es/blogs/learn/why-your-beard-needs-more-than-just-a-comb | C22: 200 | D22: https://vikingbeardgear.com/collections/beard-and-hair-care/products/beard-wash-shampoo-beard-conditioner-set?variant=31075723673654 | E22: 404 | F22: Bálsamo para Barba Sin Aroma
A23: 19 | B23: https://striking-viking.com/sv/blogs/learn/heads-shoulders-knees-and-toes-but-why-forget-the-beard | C23: 200 | D23: https://vikingbeardgear.com/collections/all/products/striking-viking-ultimate-beard-grooming-kit | E23: 404 | F23: bästa skäggvårdskitet
A24: 20 | B24: https://striking-viking.com/en-ca/blogs/learn/heads-shoulders-knees-and-toes-but-why-forget-the-beard | C24: 200 | D24: https://vikingbeardgear.com/collections/all/products/striking-viking-beard-grooming-kit-for-men | E24: 301 | F24: beard grooming kits | G24: https://vikingbeardgear.com/collections/viking-beard-kits/products/striking-viking-ultimate-beard-grooming-kit | H24: 404
A25: 21 | B25: https://striking-viking.com/es/blogs/learn/grooming-kit-a-perfect-gift-for-the-modern-man | C25: 200 | D25: https://vikingbeardgear.com/collections/viking-beard-kits/products/striking-viking-ultimate-beard-grooming-kit | E25: 404 | F25: Tijeras para Barba
A26: 22 | B26: https://striking-viking.com/fr/blogs/learn/beard-grooming-quintessential-regime-for-the-modern-man | C26: 200 | D26: https://vikingbeardgear.com/collections/all/products/striking-viking-wooden-beard-comb | E26: 404 | F26: peigne à barbe en bois
A27: 23 | B27: https://striking-viking.com/en-gb/blogs/learn/grooming-products-to-pamper-your-beard-flyaway | C27: 200 | D27: https://vikingbeardgear.com/collections/beard-and-hair-care/products/beard-wash-shampoo-beard-conditioner-set?variant=31075723673654 | E27: 404 | F27: beard balm
A28: 24 | B28: https://striking-viking.com/blogs/learn/why-your-beard-needs-more-than-just-a-comb | C28: 200 | D28: https://vikingbeardgear.com/collections/beard-and-hair-care/products/beard-wash-shampoo-beard-conditioner-set?variant=31075723673654 | E28: 404 | F28: Unscented Beard Balm
A29: 25 | B29: https://striking-viking.com/fr-ca/blogs/learn/heads-shoulders-knees-and-toes-but-why-forget-the-beard | C29: 200 | D29: https://vikingbeardgear.com/collections/all/products/striking-viking-ultimate-beard-grooming-kit | E29: 404 | F29: meilleur kit d'entretien de barbe
A30: 26 | B30: https://striking-viking.com/en-gb/blogs/learn/grooming-kit-a-perfect-gift-for-the-modern-man | C30: 200 | D30: https://vikingbeardgear.com/collections/viking-beard-kits/products/striking-viking-ultimate-beard-grooming-kit | E30: 404 | F30: Beard Scissors
A31: 27 | B31: https://striking-viking.com/fi/blogs/learn/heads-shoulders-knees-and-toes-but-why-forget-the-beard | C31: 200 | D31: https://vikingbeardgear.com/collections/all/products/striking-viking-ultimate-beard-grooming-kit | E31: 404 | F31: paras partahoidon sarja
A32: 28 | B32: https://striking-viking.com/es/blogs/learn/beard-grooming-quintessential-regime-for-the-modern-man | C32: 200 | D32: https://vikingbeardgear.com/collections/all/products/striking-viking-wooden-beard-comb | E32: 404 | F32: peine de barba de madera
A33: 29 | B33: https://striking-viking.com/en-ca/blogs/learn/grooming-products-to-pamper-your-beard-flyaway | C33: 200 | D33: https://vikingbeardgear.com/collections/beard-and-hair-care/products/beard-wash-shampoo-beard-conditioner-set?variant=31075723673654 | E33: 404 | F33: beard balm
A34: 30 | B34: https://striking-viking.com/en-ca/blogs/learn/heads-shoulders-knees-and-toes-but-why-forget-the-beard | C34: 200 | D34: https://vikingbeardgear.com/collections/all/products/striking-viking-ultimate-beard-grooming-kit | E34: 404 | F34: best beard grooming kit
A35: 31 | B35: https://striking-viking.com/it/blogs/learn/grooming-kit-a-perfect-gift-for-the-modern-man | C35: 200 | D35: https://vikingbeardgear.com/collections/viking-beard-kits/products/striking-viking-ultimate-beard-grooming-kit | E35: 404 | F35: Forbici per barba
A36: 32 | B36: https://striking-viking.com/de/blogs/learn/grooming-kit-a-perfect-gift-for-the-modern-man | C36: 200 | D36: https://vikingbeardgear.com/collections/viking-beard-kits/products/striking-viking-ultimate-beard-grooming-kit | E36: 404 | F36: Bartschere
... A39: 35 | B39: https://striking-viking.com/es/blogs/learn/heads-shoulders-knees-and-toes-but-why-forget-the-beard | C39: 200 | D39: https://vikingbeardgear.com/collections/all/products/striking-viking-ultimate-beard-grooming-kit | E39: 404 | F39: mejor kit para el cuidado de la barba
A40: 36 | B40: https://striking-viking.com/it/blogs/learn/heads-shoulders-knees-and-toes-but-why-forget-the-beard | C40: 200 | D40: https://vikingbeardgear.com/collections/all/products/striking-viking-beard-grooming-kit-for-men | E40: 301 | F40: realizzati naturalmente | G40: https://vikingbeardgear.com/collections/viking-beard-kits/products/striking-viking-ultimate-beard-grooming-kit | H40: 404
A41: 37 | B41: https://striking-viking.com/fi/blogs/learn/heads-shoulders-knees-and-toes-but-why-forget-the-beard | C41: 200 | D41: https://vikingbeardgear.com/collections/all/products/striking-viking-beard-grooming-kit-for-men | E41: 301 | F41: partahoidon sarjoilla | G41: https://vikingbeardgear.com/collections/viking-beard-kits/products/striking-viking-ultimate-beard-grooming-kit | H41: 404
A42: 38 | B42: https://striking-viking.com/fr/blogs/learn/why-your-beard-needs-more-than-just-a-comb | C42: 200 | D42: https://vikingbeardgear.com/collections/beard-and-hair-care/products/beard-wash-shampoo-beard-conditioner-set?variant=31075723673654 | E42: 404 | F42: baume à barbe sans parfum
A43: 39 | B43: https://striking-viking.com/en-gb/blogs/learn/heads-shoulders-knees-and-toes-but-why-forget-the-beard | C43: 200 | D43: https://vikingbeardgear.com/collections/all/products/striking-viking-ultimate-beard-grooming-kit | E43: 404 | F43: best beard grooming kit
A44: 40 | B44: https://striking-viking.com/no/blogs/learn/why-your-beard-needs-more-than-just-a-comb | C44: 200 | D44: https://vikingbeardgear.com/collections/beard-and-hair-care/products/beard-wash-shampoo-beard-conditioner-set?variant=31075723673654 | E44: 404 | F44: Uparfymerte Skjeggbalmen
A45: 41 | B45: https://striking-viking.com/no/blogs/learn/grooming-kit-a-perfect-gift-for-the-modern-man | C45: 200 | D45: https://vikingbeardgear.com/collections/viking-beard-kits/products/striking-viking-ultimate-beard-grooming-kit | E45: 404 | F45: Skjeggsaks
A46: 42 | B46: https://striking-viking.com/no/blogs/learn/grooming-products-to-pamper-your-beard-flyaway | C46: 200 | D46: https://vikingbeardgear.com/collections/beard-and-hair-care/products/beard-wash-shampoo-beard-conditioner-set?variant=31075723673654 | E46: 404 | F46: Skjeggbalm
A47: 43 | B47: https://striking-viking.com/es/blogs/learn/heads-shoulders-knees-and-toes-but-why-forget-the-beard | C47: 200 | D47: https://vikingbeardgear.com/collections/all/products/striking-viking-beard-grooming-kit-for-men | E47: 301 | F47: elaborados de manera natural | G47: https://vikingbeardgear.com/collections/viking-beard-kits/products/striking-viking-ultimate-beard-grooming-kit | H47: 404
A48: 44 | B48: https://striking-viking.com/en-ca/blogs/learn/why-your-beard-needs-more-than-just-a-comb | C48: 200 | D48: https://vikingbeardgear.com/collections/beard-and-hair-care/products/beard-wash-shampoo-beard-conditioner-set?variant=31075723673654 | E48: 404 | F48: Unscented Beard Balm
A49: 45 | B49: https://striking-viking.com/it/blogs/learn/heads-shoulders-knees-and-toes-but-why-forget-the-beard | C49: 200 | D49: https://vikingbeardgear.com/collections/all/products/striking-viking-ultimate-beard-grooming-kit | E49: 404 | F49: miglior kit per la cura della barba
A50: 46 | B50: https://striking-viking.com/fi/blogs/learn/beard-grooming-quintessential-regime-for-the-modern-man | C50: 200 | D50: https://vikingbeardgear.com/collections/all/products/striking-viking-wooden-beard-comb | E50: 404 | F50: puiset partakampa
A51: 47 | B51: https://striking-viking.com/it/blogs/learn/why-your-beard-needs-more-than-just-a-comb | C51: 200 | D51: https://vikingbeardgear.com/collections/beard-and-hair-care/products/beard-wash-shampoo-beard-conditioner-set?variant=31075723673654 | E51: 404 | F51: Balsamo Barba Senza Profumo
A52: 48 | B52: https://striking-viking.com/en-gb/blogs/learn/heads-shoulders-knees-and-toes-but-why-forget-the-beard | C52: 200 | D52: https://vikingbeardgear.com/collections/all/products/striking-viking-beard-grooming-kit-for-men | E52: 301 | F52: beard grooming kits | G52: https://vikingbeardgear.com/collections/viking-beard-kits/products/striking-viking-ultimate-beard-grooming-kit | H52: 404
A53: 49 | B53: https://striking-viking.com/sv/blogs/learn/heads-shoulders-knees-and-toes-but-why-forget-the-beard | C53: 200 | D53: https://vikingbeardgear.com/collections/all/products/striking-viking-beard-grooming-kit-for-men | E53: 301 | F53: skäggvårdskit | G53: https://vikingbeardgear.com/collections/viking-beard-kits/products/striking-viking-ultimate-beard-grooming-kit | H53: 404
A54: 50 | B54: https://striking-viking.com/fr-ca/blogs/learn/beard-grooming-quintessential-regime-for-the-modern-man | C54: 200 | D54: https://vikingbeardgear.com/collections/all/products/striking-viking-wooden-beard-comb | E54: 404 | F54: peigne à barbe en bois
A55: 51 | B55: https://striking-viking.com/de/blogs/learn/grooming-products-to-pamper-your-beard-flyaway | C55: 200 | D55: https://vikingbeardgear.com/collections/beard-and-hair-care/products/beard-wash-shampoo-beard-conditioner-set?variant=31075723673654 | E55: 404 | F55: Bartbalsam
A56: 52 | B56: https://striking-viking.com/fr/blogs/learn/heads-shoulders-knees-and-toes-but-why-forget-the-beard | C56: 200 | D56: https://vikingbeardgear.com/collections/all/products/striking-viking-ultimate-beard-grooming-kit | E56: 404 | F56: meilleur kit d'entretien de barbe
A57: 53 | B57: https://striking-viking.com/blogs/learn/grooming-kit-a-perfect-gift-for-the-modern-man | C57: 200 | D57: https://vikingbeardgear.com/collections/viking-beard-kits/products/striking-viking-ultimate-beard-grooming-kit | E57: 404 | F57: Beard Scissors
A58: 54 | B58: https://striking-viking.com/it/blogs/learn/grooming-products-to-pamper-your-beard-flyaway | C58: 200 | D58: https://vikingbeardgear.com/collections/beard-and-hair-care/products/beard-wash-shampoo-beard-conditioner-set?variant=31075723673654 | E58: 404 | F58: balsamo per barba
A59: 55 | B59: https://striking-viking.com/fr/blogs/learn/grooming-products-to-pamper-your-beard-flyaway | C59: 200 | D59: https://vikingbeardgear.com/collections/beard-and-hair-care/products/beard-wash-shampoo-beard-conditioner-set?variant=31075723673654 | E59: 404 | F59: baume à barbe
A60: 56 | B60: https://striking-viking.com/de/blogs/learn/heads-shoulders-knees-and-toes-but-why-forget-the-beard | C60: 200 | D60: https://vikingbeardgear.com/collections/all/products/striking-viking-ultimate-beard-grooming-kit | E60: 404 | F60: beste Bartpflegeset
A61: 57 | B61: https://striking-viking.com/fr-ca/blogs/learn/why-your-beard-needs-more-than-just-a-comb | C61: 200 | D61: https://vikingbeardgear.com/collections/beard-and-hair-care/products/beard-wash-shampoo-beard-conditioner-set?variant=31075723673654 | E61: 404 | F61: baume à barbe sans parfum
A62: 58 | B62: https://striking-viking.com/en-gb/blogs/learn/why-your-beard-needs-more-than-just-a-comb | C62: 200 | D62: https://vikingbeardgear.com/collections/beard-and-hair-care/products/beard-wash-shampoo-beard-conditioner-set?variant=31075723673654 | E62: 404 | F62: Unscented Beard Balm
A63: 59 | B63: https://striking-viking.com/sv/blogs/learn/grooming-kit-a-perfect-gift-for-the-modern-man | C63: 200 | D63: https://vikingbeardgear.com/collections/viking-beard-kits/products/striking-viking-ultimate-beard-grooming-kit | E63: 404 | F63: Skäggsax
A64: 60 | B64: https://striking-viking.com/fi/blogs/learn/why-your-beard-needs-more-than-just-a-comb | C64: 200 | D64: https://vikingbeardgear.com/collections/beard-and-hair-care/products/beard-wash-shampoo-beard-conditioner-set?variant=31075723673654 | E64: 404 | F64: Tuoksuton partabalsami
A65: 61 | B65: https://striking-viking.com/sv/blogs/learn/grooming-products-to-pamper-your-beard-flyaway | C65: 200 | D65: https://vikingbeardgear.com/collections/beard-and-hair-care/products/beard-wash-shampoo-beard-conditioner-set?variant=31075723673654 | E65: 404 | F65: Skäggbalsam
A66: 62 | B66: https://striking-viking.com/no/blogs/learn/heads-shoulders-knees-and-toes-but-why-forget-the-beard | C66: 200 | D66: https://vikingbeardgear.com/collections/all/products/striking-viking-ultimate-beard-grooming-kit | E66: 404 | F66: beste skjeggpleiesettet
A67: 63 | B67: https://striking-viking.com/no/blogs/learn/heads-shoulders-knees-and-toes-but-why-forget-the-beard | C67: 200 | D67: https://vikingbeardgear.com/collections/all/products/striking-viking-beard-grooming-kit-for-men | E67: 301 | F67: skjeggpleiesettene | G67: https://vikingbeardgear.com/collections/viking-beard-kits/products/striking-viking-ultimate-beard-grooming-kit | H67: 404
A68: 64 | B68: https://striking-viking.com/fr-ca/blogs/learn/grooming-products-to-pamper-your-beard-flyaway | C68: 200 | D68: https://vikingbeardgear.com/collections/beard-and-hair-care/products/beard-wash-shampoo-beard-conditioner-set?variant=31075723673654 | E68: 404 | F68: baume à barbe
A69: 65 | B69: https://striking-viking.com/en-ca/blogs/learn/beard-grooming-quintessential-regime-for-the-modern-man | C69: 200 | D69: https://vikingbeardgear.com/collections/all/products/striking-viking-wooden-beard-comb | E69: 404 | F69: wooden beard comb
A70: 66 | B70: https://striking-viking.com/es/blogs/learn/grooming-products-to-pamper-your-beard-flyaway | C70: 200 | D70: https://vikingbeardgear.com/collections/beard-and-hair-care/products/beard-wash-shampoo-beard-conditioner-set?variant=31075723673654 | E70: 404 | F70: bálsamo para barba

Sheet SV_Meta description too long
H1: =HYPERLINK("#'Master Overview'!A1","<< Master Overview") -> << Master Overview
H2: Source: striking-viking - Issues.xlsx / Meta description too long
B3: Meta description too long
B4: Sr. no | C4: URL | D4: Meta description | E4: Meta description length | F4: Status
B5: 1 | C5: https://striking-viking.com/pages/contact-us | D5: Thank-you for visiting Striking Viking! Have a question or concern? We're eager to address any question you may have, so please fill out the form below and we will be in contact with you by the next business day! Email: service@vikingbeardgear.com | E5: 247
B6: 2 | C6: https://striking-viking.com/pages/become-a-reseller | D6: Become a reseller and elevate your retail with premium men's grooming products from Striking Viking. Join us today for exclusive support, packaging, and sales growth. | E6: 166
B7: 3 | C7: https://striking-viking.com/collections/sprays | D7: Shop Striking Viking men's grooming sprays — sea salt hair sprays for texture & hold, available in Blue Ocean and Citrus scents. Lightweight, fresh, and fast-styling. | E7: 166
B8: 4 | C8: https://striking-viking.com/collections/after-shave-balm | D8: Shop Striking Viking after shave balm — alcohol-free, soothing post-shave balm for men. Reduces razor burn & redness. Available in Vanilla, Sandalwood & Unscented. | E8: 163
B9: 5 | C9: https://striking-viking.com/collections/scissors-ontaki | D9: Discover Scissors Ontaki, crafted from premium Japanese steel for clean, controlled grooming. Perfect for professionals and home use, bringing barbershop quality to your routine. | E9: 178
B10: 6 | C10: https://striking-viking.com/pages/about-us | D10: Striking Viking beard care products are handcrafted with all natural and 100% organic ingredients leaving your beard and mustache full and healthy. Our unique blends of oils and balms are formulated to promote beard growth while our beard combs showcase fashion, functionality and leave your beard looking its best. | E10: 315
B11: 7 | C11: https://striking-viking.com/collections/combs | D11: Shop Striking Viking wooden beard combs — folding pocket combs, full-size beard combs & anti-static hair combs. Snag-free grooming for beard & hair. Free US shipping over $60. | E11: 175
B12: 8 | C12: https://striking-viking.com/products/beard-growth-butter-with-biotin-4-oz-blue-ocean | D12: This beard growth butter with biotin is crafted to support a fuller-looking beard while delivering intense hydration and improved texture. It helps soften coarse hair, reduce the appearance of dryness, and enhance overall beard manageability. The lightweight, non-greasy formula absorbs quickly, while the fresh Blue Oce | E12: 320
B13: 9 | C13: https://striking-viking.com/products/striking-viking-boar-bristle-beard-brush-for-men-natural-beech-wood-grooming-brush | D13: Groom and style your beard with the Striking Viking Boar Bristle Beard Brush. Natural beech wood handle, premium boar bristles, reduces frizz, and distributes natural oils. | E13: 172
B14: 10 | C14: https://striking-viking.com/products/striking-viking-beard-filler-pencil-with-dual-tip-pen-brush-for-natural-beard-styling | D14: Create a fuller-looking beard instantly with the Striking Viking Beard Filler Pencil. Dual-tip design with blending brush for natural coverage, shaping, and beard styling. | E14: 171
B15: 11 | C15: https://striking-viking.com/es/collections/beard-care | D15: Todo lo que necesitas para una barba bien cuidada. Aceites, bálsamos, mantecas, jabones, peines y kits. Más de 23,000 reseñas de 5 estrellas. Envío gratis en EE. UU. en compras superiores a $60. | E15: 194
B16: 12 | C16: https://striking-viking.com/de/collections/2026-deals | D16: Bartpflege-Angebot bei Striking Viking. Spare bei Bartpflege, Pflegewerkzeugen und Styling-Essentials, die für täglichen Komfort und Selbstbewusstsein entwickelt wurden. | E16: 169
... B1220: 1216 | C1220: https://striking-viking.com/es/products/striking-viking-sandalwood-beard-growth-kit-with-biotin-oil-0-25mm-derma-roller | D1220: Kit de Crecimiento de Barba Striking Viking con Aceite de Biotina y Sándalo y Derma Roller. Promueve el crecimiento natural de una barba más densa y abundante. Fórmula fácil de usar y sin dolor. | E1220: 194

Sheet SV_Title too long
G1: =HYPERLINK("#'Master Overview'!A1","<< Master Overview") -> << Master Overview
B2: Title too long | G2: Source: striking-viking - Issues.xlsx / Title too long
B3: URL | C3: Title | D3: Title length | E3: Status
B4: https://striking-viking.com/collections/best-sellers-grooming-kit | C4: Best Selling Beard Products for Men | Top-Rated Grooming | Striking Viking | D4: 74
B5: https://striking-viking.com/pages/become-a-reseller | C5: Become a Reseller | Join Striking Viking Wholesale Men's Grooming Brand | D5: 71
B6: https://striking-viking.com/collections/combs-and-brushes | C6: Beard Combs & Brushes | Wooden, Boar Bristle & Styling Tools | Striking Viking | D6: 78
B7: https://striking-viking.com/collections/sprays | C7: Men's Grooming Sprays – Sea Salt Hair Spray & Beard Spray | Striking Viking | D7: 75
B8: https://striking-viking.com/collections/beard-care | C8: Men's Beard Care Products – Oils, Balms, Combs & More | Striking Viking | D8: 71
B9: https://striking-viking.com/collections/beard-oil | C9: Best Beard Oil for Men | Natural & Organic Beard Oils | Striking Viking | D9: 71
B10: https://striking-viking.com/collections/after-shave-balm | C10: After Shave Balm for Men – Soothing Post-Shave Skin Care | Striking Viking | D10: 74
B11: https://striking-viking.com/collections/face-body | C11: Men's Face & Body Care – Pre Shave, Shaving Cream & More | Striking Viking | D11: 74
B12: https://striking-viking.com/collections/beard-filler-pens | C12: Beard Filler Pen | Instant Coverage for Patchy Beards | Striking Viking | D12: 71
B13: https://striking-viking.com/collections/tattoo-aftercare | C13: Tattoo Aftercare: Premium Balm Collection for Healing – Striking Viking | D13: 71
B14: https://striking-viking.com/collections/scissors-ontaki | C14: Scissors Ontaki - Premium Japanese Grooming Scissors for Precision Cuts – Striking Viking | D14: 89
B15: https://striking-viking.com/collections/shaving | C15: Men's Shaving Products – Creams, Oils & After Shave Balm | Striking Viking | D15: 74
... B775: https://striking-viking.com/es/products/striking-viking-sandalwood-beard-growth-kit-with-biotin-oil-0-25mm-derma-roller | C775: Kit de Crecimiento de Barba Sándalo | Aceite de Biotina y Roller | Striking Viking | D775: 82

Sheet SV_Missing H1
H1: =HYPERLINK("#'Master Overview'!A1","<< Master Overview") -> << Master Overview
B2: Missing H1 | H2: Source: striking-viking - Issues.xlsx / Missing H1
B3: Sr.no. | C3: URL | D3: H1 | E3: H1 length | F3: Status
B4: 1 | C4: https://striking-viking.com/pages/contact-us | D4: Missing
B5: 2 | C5: https://striking-viking.com/pages/faqs | D5: Missing
B6: 3 | C6: https://striking-viking.com/pages/sign-up | D6: Missing
B7: 4 | C7: https://striking-viking.com/collections/2026-deals | D7: Missing
B8: 5 | C8: https://striking-viking.com/de/collections/2026-deals | D8: Missing
B9: 6 | C9: https://striking-viking.com/en-ca/pages/contact-us | D9: Missing
B10: 7 | C10: https://striking-viking.com/fr/pages/faqs | D10: Missing
B11: 8 | C11: https://striking-viking.com/it/pages/faqs | D11: Missing
B12: 9 | C12: https://striking-viking.com/it/pages/contact-us | D12: Missing
B13: 10 | C13: https://striking-viking.com/fr/collections/2026-deals | D13: Missing
B14: 11 | C14: https://striking-viking.com/no/pages/contact-us | D14: Missing
B15: 12 | C15: https://striking-viking.com/sv/pages/faqs | D15: Missing
... B91: 88 | C91: https://striking-viking.com/fr-ca/pages/ilm-2025-sign-up | D91: Missing

Sheet SV_Meta description too short
H1: =HYPERLINK("#'Master Overview'!A1","<< Master Overview") -> << Master Overview
H2: Source: striking-viking - Issues.xlsx / Meta description too short
C3: Meta description too short
C4: URL | D4: Meta description | E4: Meta description length | F4: Status
C5: https://striking-viking.com/de/blogs/learn/ride-the-wave-striking-viking-sea-salt-spray-for-effortless-men-s-style | D5: Entdecke das Striking Viking Meersalzspray für mühelosen Style, der das Wesen des Ozeans einfängt. | E5: 98
C6: https://striking-viking.com/fi/blogs/learn/ride-the-wave-striking-viking-sea-salt-spray-for-effortless-men-s-style | D6: Löydä Striking Viking merisuolasuihke vaivattomaan tyyliin, joka vangitsee meren olemuksen. | E6: 91
C7: https://striking-viking.com/no/blogs/learn/ride-the-wave-striking-viking-sea-salt-spray-for-effortless-men-s-style | D7: Oppdag Striking Viking havsalt-spray for en uanstrengt stil som fanger essensen av havet. | E7: 89
C8: https://striking-viking.com/sv/blogs/learn/ride-the-wave-striking-viking-sea-salt-spray-for-effortless-men-s-style | D8: Upptäck Striking Viking havssaltspray för en avslappnad stil som fångar havets essens. | E8: 86
C9: https://striking-viking.com/sv/blogs/learn/the-ultimate-guide-to-grooming-with-ontaki-scissors | D9: Upptäck de bästa groomingteknikerna med Ontaki-saxar från Striking Viking. Höj din stil idag! | E9: 93
C10: https://striking-viking.com/es/pages/spurit-reminders-cancelled | D10: Cancelación exitosa de los recordatorios de factura | E10: 51
C11: https://striking-viking.com/en-ca/pages/spurit-notifications-cancelled | D11: Receiving these notifications successfully cancelled | E11: 52
C12: https://striking-viking.com/fr/products/shipping-protection | D12: Protégez votre commande contre les dommages, la perte ou le vol pendant la livraison. | E12: 85
C13: https://striking-viking.com/no/pages/spurit-notifications-cancelled | D13: Mottak av disse varslene ble vellykket kansellert | E13: 49
C14: https://striking-viking.com/es/products/shipping-protection | D14: Protege tu pedido contra daños, pérdida o robo durante el envío. | E14: 64
C15: https://striking-viking.com/no/pages/spurit-merchant-notifications-cancelled | D15: Motta disse varslingene ble vellykket kansellert Du kan gjenoppta det når som helst i appen | E15: 91
C16: https://striking-viking.com/pages/spurit-reminders-cancelled | D16: Receiving invoice reminders successfully cancelled | E16: 50
... C48: https://striking-viking.com/fr-ca/products/shipping-protection | D48: Protégez votre commande contre les dommages, la perte ou le vol pendant la livraison. | E48: 85

Sheet SV_Meta description tag missing
G1: =HYPERLINK("#'Master Overview'!A1","<< Master Overview") -> << Master Overview
G2: Source: striking-viking - Issues.xlsx / Meta description tag missing or
B4: Meta description tag missing or empty
B5: Sr. no | C5: URL | D5: Meta description | E5: Status
B6: 1 | C6: https://striking-viking.com/pages/spurit-subscriptions | D6: Missing
B7: 2 | C7: https://striking-viking.com/en-gb/pages/spurit-subscriptions | D7: Missing
B8: 3 | C8: https://striking-viking.com/no/pages/spurit-subscriptions | D8: Missing
B9: 4 | C9: https://striking-viking.com/fr-ca/pages/spurit-subscriptions | D9: Missing
B10: 5 | C10: https://striking-viking.com/es/pages/spurit-subscriptions | D10: Missing
B11: 6 | C11: https://striking-viking.com/it/pages/spurit-subscriptions | D11: Missing
B12: 7 | C12: https://striking-viking.com/en-ca/pages/spurit-subscriptions | D12: Missing
B13: 8 | C13: https://striking-viking.com/fr/pages/spurit-subscriptions | D13: Missing
B14: 9 | C14: https://striking-viking.com/de/pages/spurit-subscriptions | D14: Missing
B15: 10 | C15: https://striking-viking.com/sv/pages/spurit-subscriptions | D15: Missing

Sheet SV_Multiple H1 tags
I1: =HYPERLINK("#'Master Overview'!A1","<< Master Overview") -> << Master Overview
B2: Multiple H1 tags | I2: Source: striking-viking - Issues.xlsx / Multiple H1 tags
B3: Sr. no. | C3: URL | D3: H1 | E3: H1 length | F3: No. of H1 | G3: Status
B4: 1 | C4: https://striking-viking.com/collections/beard-balm | D4: Beard Balm Beard Balm | E4: 10 10 | F4: 2
B5: 2 | C5: https://striking-viking.com/collections/beard-care | D5: Beard & Hair Care Beard Care | E5: 17 10 | F5: 2
B6: 3 | C6: https://striking-viking.com/collections/beard-oil | D6: Beard Oils Beard Oil | E6: 10 9 | F6: 2
B7: 4 | C7: https://striking-viking.com/ | D7: Striking Viking – Premium Beard & Hair Grooming Products for Men Striking Viking Vanilla Beard Growth Oil with Biotin & Castor Oil for Fuller Beard Growth Striking Viking Mustache Wax and Comb Kit Striking Viking Cedarwood Beard Oil Striking Viking Folding Wooden Comb – Sandalwood Beard & Hair Comb | E7: 64 89 41 35 66 | F7: 5
B8: 5 | C8: https://striking-viking.com/collections/beard-filler-pens | D8: Beard Filler Pens for Men Beard Filler Pens for Men | E8: 25 25 | F8: 2
B9: 6 | C9: https://striking-viking.com/collections/beard-butter | D9: Beard Butter Beard Butter | E9: 12 12 | F9: 2
B10: 7 | C10: https://striking-viking.com/collections/beard-wash | D10: Beard Wash Beard Shampoo & Wash | E10: 10 20 | F10: 2
B11: 8 | C11: https://striking-viking.com/blogs/learn/ride-the-wave-striking-viking-sea-salt-spray-for-effortless-men-s-style | D11: Ride the Wave: Striking Viking Sea Salt Spray for Effortless Men’s Style Ride the Wave: Striking Viking Sea Salt Spray for Effortless Men’s Style | E11: 72 72 | F11: 2
B12: 9 | C12: https://striking-viking.com/products/striking-viking-beard-filler-pencil-with-dual-tip-pen-brush-for-natural-beard-styling | D12: Striking Viking Beard Filler Pencil with Dual-Tip Pen & Brush for Natural Beard Styling Benefits | E12: 87 8 | F12: 2
B13: 10 | C13: https://striking-viking.com/es/collections/beard-care | D13: Cuidado de barba y cabello Cuidado de la barba | E13: 26 19 | F13: 2
B14: 11 | C14: https://striking-viking.com/fr/collections/beard-balm | D14: Baume à barbe Baume à barbe | E14: 13 13 | F14: 2
B15: 12 | C15: https://striking-viking.com/en-ca/collections/beard-balm | D15: Beard Balm Beard Balm | E15: 10 10 | F15: 2
... B255: 252 | C255: https://striking-viking.com/es/products/striking-viking-sandalwood-beard-growth-kit-with-biotin-oil-0-25mm-derma-roller | D255: Kit para Crecimiento de Barba - Aceite de Biotina para Barba con Sándalo y Derma Roller Kit de Crecimiento de Barba con Rodillo Derma y Sérum de Biotina | E255: 87 64 | F255: 2

Sheet SV_Pages have high AI content l
K1: =HYPERLINK("#'Master Overview'!A1","<< Master Overview") -> << Master Overview
K2: Source: striking-viking - Issues.xlsx / Pages have high AI content leve
B3: Pages have high AI content levels
B4: Sr.no | C4: URL | D4: AI content level | E4: AI content status | F4: No. of content words | G4: Meta description | H4: H1 | I4: Status
B5: 1 | C5: https://striking-viking.com/products/sandalwood-wooden-beard-comb-black-striking-viking | D5: High | E5: Success | F5: 4388 | G5: Striking Viking Black Sandalwood Beard Comb with fine and coarse teeth for detangling, smoothing, styling, and grooming. Includes protective carry case. | H5: Sandalwood Wooden Beard Comb - Black | Striking Viking | I5: Need to Fixed

Sheet SV_Missing alt text
G1: =HYPERLINK("#'Master Overview'!A1","<< Master Overview") -> << Master Overview
C2: Missing alt text | G2: Source: striking-viking - Issues.xlsx / Missing alt text
C3: URL | D3: Linked images without alt attribute | E3: Missing alt text
C4: https://striking-viking.com/ | D4: https://striking-viking.com/cdn/shop/files/preview_images/06fa7414903d4ace94cbe4e096befa28.thumbnail.0000000000_1024x1024.jpg?v=1786601229 https://striking-viking.com/cdn/shop/files/preview_images/3b2d1290045c417e8b589a319a2e2fbf.thumbnail.0000000000_1024x1024.jpg?v=1786616279 https://striking-viking.com/cdn/shop/files/preview_images/bbf7ac2d6bcb4e9781033073d3e04183.thumbnail.0000000000_1024x1024.jpg?v=1786599449
C5: https://striking-viking.com/products/striking-viking-mustache-wax-and-comb-kit | D5: https://striking-viking.com/cdn/shop/files/preview_images/bbf7ac2d6bcb4e9781033073d3e04183.thumbnail.0000000000_1024x1024.jpg?v=1786599449
C6: https://striking-viking.com/es/products/striking-viking-beard-filler-pen-2-pack-waterproof-beard-pen-for-filling-gaps-covering-patches | D6: https://striking-viking.com/cdn/shop/files/preview_images/49129432d5d543f2b09f1e3faab28f4a.thumbnail.0000000000_1024x1024.jpg?v=1786599719
C7: https://striking-viking.com/no/products/striking-viking-mustache-wax-and-comb-kit | D7: https://striking-viking.com/cdn/shop/files/preview_images/bbf7ac2d6bcb4e9781033073d3e04183.thumbnail.0000000000_1024x1024.jpg?v=1786599449
C8: https://striking-viking.com/fi/products/striking-viking-beard-filler-pen-2-pack-waterproof-beard-pen-for-filling-gaps-covering-patches | D8: https://striking-viking.com/cdn/shop/files/preview_images/49129432d5d543f2b09f1e3faab28f4a.thumbnail.0000000000_1024x1024.jpg?v=1786599719
C9: https://striking-viking.com/de | D9: https://striking-viking.com/cdn/shop/files/preview_images/06fa7414903d4ace94cbe4e096befa28.thumbnail.0000000000_1024x1024.jpg?v=1786601229 https://striking-viking.com/cdn/shop/files/preview_images/3b2d1290045c417e8b589a319a2e2fbf.thumbnail.0000000000_1024x1024.jpg?v=1786616279 https://striking-viking.com/cdn/shop/files/preview_images/bbf7ac2d6bcb4e9781033073d3e04183.thumbnail.0000000000_1024x1024.jpg?v=1786599449
C10: https://striking-viking.com/it/products/striking-viking-beard-filler-pen-2-pack-waterproof-beard-pen-for-filling-gaps-covering-patches | D10: https://striking-viking.com/cdn/shop/files/preview_images/49129432d5d543f2b09f1e3faab28f4a.thumbnail.0000000000_1024x1024.jpg?v=1786599719
C11: https://striking-viking.com/es | D11: https://striking-viking.com/cdn/shop/files/preview_images/06fa7414903d4ace94cbe4e096befa28.thumbnail.0000000000_1024x1024.jpg?v=1786601229 https://striking-viking.com/cdn/shop/files/preview_images/3b2d1290045c417e8b589a319a2e2fbf.thumbnail.0000000000_1024x1024.jpg?v=1786616279 https://striking-viking.com/cdn/shop/files/preview_images/bbf7ac2d6bcb4e9781033073d3e04183.thumbnail.0000000000_1024x1024.jpg?v=1786599449
C12: https://striking-viking.com/en-gb/products/striking-viking-mustache-wax-and-comb-kit | D12: https://striking-viking.com/cdn/shop/files/preview_images/bbf7ac2d6bcb4e9781033073d3e04183.thumbnail.0000000000_1024x1024.jpg?v=1786599449
C13: https://striking-viking.com/it | D13: https://striking-viking.com/cdn/shop/files/preview_images/06fa7414903d4ace94cbe4e096befa28.thumbnail.0000000000_1024x1024.jpg?v=1786601229 https://striking-viking.com/cdn/shop/files/preview_images/3b2d1290045c417e8b589a319a2e2fbf.thumbnail.0000000000_1024x1024.jpg?v=1786616279 https://striking-viking.com/cdn/shop/files/preview_images/bbf7ac2d6bcb4e9781033073d3e04183.thumbnail.0000000000_1024x1024.jpg?v=1786599449
C14: https://striking-viking.com/it/products/striking-viking-beard-kit-caddy-complete-beard-grooming-kit | D14: https://striking-viking.com/cdn/shop/files/preview_images/ba5feb9f783d4fa1adb23a394602c871.thumbnail.0000000000_1024x1024.jpg?v=1786599826
C15: https://striking-viking.com/en-ca/products/striking-viking-beard-kit-caddy-complete-beard-grooming-kit | D15: https://striking-viking.com/cdn/shop/files/preview_images/ba5feb9f783d4fa1adb23a394602c871.thumbnail.0000000000_1024x1024.jpg?v=1786599826
... C324: https://striking-viking.com/en-ca/products/striking-viking-citrus-beard-oil | D324: https://striking-viking.com/cdn/shop/files/preview_images/59360cd09ea240a0b2661030d5829c72.thumbnail.0000000000_1024x1024.jpg?v=1786601332

Sheet SV_External 4XX
I1: =HYPERLINK("#'Master Overview'!A1","<< Master Overview") -> << Master Overview
I2: Source: striking-viking - Issues.xlsx / External 4XX
B4: External 4XX
B5: Source URL | C5: Source HTTP status code | D5: Target URL | E5: Target HTTP status code | F5: Anchor | G5: Status
B6: https://striking-viking.com/de/blogs/learn/beard-grooming-quintessential-regime-for-the-modern-man | C6: 200 | D6: https://vikingbeardgear.com/collections/all/products/striking-viking-wooden-beard-comb | E6: 404 | F6: hölzerne Bartkamm
B7: https://striking-viking.com/fr/blogs/learn/heads-shoulders-knees-and-toes-but-why-forget-the-beard | C7: 200 | D7: https://vikingbeardgear.com/collections/all/products/striking-viking-beard-grooming-kit-for-men | E7: 301 | F7: kits d'entretien de barbe
B8: https://striking-viking.com/de/blogs/learn/why-your-beard-needs-more-than-just-a-comb | C8: 200 | D8: https://vikingbeardgear.com/collections/beard-and-hair-care/products/beard-wash-shampoo-beard-conditioner-set?variant=31075723673654 | E8: 404 | F8: unparfümierte Bartbalsam
B9: https://striking-viking.com/de/blogs/learn/heads-shoulders-knees-and-toes-but-why-forget-the-beard | C9: 200 | D9: https://vikingbeardgear.com/collections/all/products/striking-viking-beard-grooming-kit-for-men | E9: 301 | F9: Bartpflegesets
B10: https://striking-viking.com/en-gb/blogs/learn/beard-grooming-quintessential-regime-for-the-modern-man | C10: 200 | D10: https://vikingbeardgear.com/collections/all/products/striking-viking-wooden-beard-comb | E10: 404 | F10: wooden beard comb
B11: https://striking-viking.com/sv/blogs/learn/why-your-beard-needs-more-than-just-a-comb | C11: 200 | D11: https://vikingbeardgear.com/collections/beard-and-hair-care/products/beard-wash-shampoo-beard-conditioner-set?variant=31075723673654 | E11: 404 | F11: Oparfymerade Skäggbalsam
B12: https://striking-viking.com/fi/blogs/learn/grooming-products-to-pamper-your-beard-flyaway | C12: 200 | D12: https://vikingbeardgear.com/collections/beard-and-hair-care/products/beard-wash-shampoo-beard-conditioner-set?variant=31075723673654 | E12: 404 | F12: Partavoide
B13: https://striking-viking.com/sv/blogs/learn/beard-grooming-quintessential-regime-for-the-modern-man | C13: 200 | D13: https://vikingbeardgear.com/collections/all/products/striking-viking-wooden-beard-comb | E13: 404 | F13: träkam för skägg
B14: https://striking-viking.com/it/blogs/learn/beard-grooming-quintessential-regime-for-the-modern-man | C14: 200 | D14: https://vikingbeardgear.com/collections/all/products/striking-viking-wooden-beard-comb | E14: 404 | F14: pettine per barba in legno
B15: https://striking-viking.com/en-ca/blogs/learn/grooming-kit-a-perfect-gift-for-the-modern-man | C15: 200 | D15: https://vikingbeardgear.com/collections/viking-beard-kits/products/striking-viking-ultimate-beard-grooming-kit | E15: 404 | F15: Beard Scissors
B16: https://striking-viking.com/fi/blogs/learn/grooming-kit-a-perfect-gift-for-the-modern-man | C16: 200 | D16: https://vikingbeardgear.com/collections/viking-beard-kits/products/striking-viking-ultimate-beard-grooming-kit | E16: 404 | F16: Partasakset
B17: https://striking-viking.com/fr-ca/blogs/learn/grooming-kit-a-perfect-gift-for-the-modern-man | C17: 200 | D17: https://vikingbeardgear.com/collections/viking-beard-kits/products/striking-viking-ultimate-beard-grooming-kit | E17: 404 | F17: Ciseaux à barbe
... B71: https://striking-viking.com/es/blogs/learn/grooming-products-to-pamper-your-beard-flyaway | C71: 200 | D71: https://vikingbeardgear.com/collections/beard-and-hair-care/products/beard-wash-shampoo-beard-conditioner-set?variant=31075723673654 | E71: 404 | F71: bálsamo para barba
