Workbook

Sheet harlingenglass.com
B1: Week | C1: Planned Date | D1: Day | E1: Category | F1: Post Title | G1: GBP Post Copy | H1: CTA | I1: Landing Page | J1: Tracked CTA URL | K1: Banner | L1: Banner Overlay Text | M1: Banner File | N1: Banner Photo Source | O1: Offer Dates / Terms | P1: Publishing Status
B2: 1 | C2: 46328 | D2: =TEXT(C2,"ddd") -> Mon | E2: Service | F2: Cracked or Foggy Window? Residential Glass Repair in Harlingen | G2: Cracked pane, a window hit by a stray ball, or glass that looks foggy between the panes? Harlingen Glass & Mirror repairs and replaces residential glass across Harlingen and the Rio Grande Valley. We work on single and double-pane windows, sliding and swinging glass doors, tabletops and shelves. If it is made of glass, our team can fix it, replace it or install it. Family-owned since 1978, we measure on site and give you a clear quote before any work starts. Tap Learn more to request your free estimate. | H2: Learn more | I2: https://harlingenglass.com/service/residential/ | J2: =I2&"?utm_source="&Settings!$C$5&"&utm_medium="&Settings!$C$6&"&utm_campaign="&Settings!$C$7&"&utm_content="&Settings!C13 -> https://harlingenglass.com/service/residential/?utm_source=google&utm_medium=organic&utm_campaign=gbp-posts-nov-2026&utm_content=nov26-01-window-repair | L2: Tag: Residential Glass Repair Headline: Cracked Window? We'll Make It Clear Again. Sub-line: Repair and replacement for Valley homes Button: Free Estimate | M2: 2026-11-02_gbp-post-01_1200x900.png | N2: https://harlingenglass.com/wp-content/uploads/2024/01/image00008.jpg | P2: Not Published
B3: 1 | C3: 46329 | D3: =TEXT(C3,"ddd") -> Tue | E3: Promotional | F3: Buy 3 Windows, Get the 4th Window Free | G3: Old or drafty windows can push your energy bills up and leave hot and cold spots around the house. This season, upgrade to energy-efficient windows with Harlingen Glass & Mirror. Buy 3 windows and get the 4th window free. Every project starts with a free window inspection, expert advice and a clear quote, with no pressure. Serving Harlingen and the Rio Grande Valley for over 40 years. Tap View offer to book your free inspection. | H3: View offer | I3: https://harlingenglass.com/service/residential-window-replacement/ | J3: =I3&"?utm_source="&Settings!$C$5&"&utm_medium="&Settings!$C$6&"&utm_campaign="&Settings!$C$7&"&utm_content="&Settings!C14 -> https://harlingenglass.com/service/residential-window-replacement/?utm_source=google&utm_medium=organic&utm_campaign=gbp-posts-nov-2026&utm_content=nov26-02-buy3-get1 | L3: Tag: Limited-Time Offer Headline: Buy 3 Windows Get the 4th FREE Sub-line: Energy-efficient window replacement Button: Book a Free Inspection | M3: 2026-11-03_gbp-post-02_1200x900.png | N3: https://harlingenglass.com/wp-content/uploads/2024/01/image00005.jpg | O3: Offer dates: Nov 3 to Nov 30, 2026 (confirm). Terms: confirm eligible window types, minimum order and whether it combines with financing. | P3: Not Published
B4: 1 | C4: 46330 | D4: =TEXT(C4,"ddd") -> Wed | E4: FAQ | F4: FAQ: Why Is My Double-Pane Window Foggy? | G4: FAQ: Why is my double-pane window foggy, and can it be fixed? Fog or moisture trapped between the two panes usually means the seal on the insulated glass unit has failed. Once that happens, the window loses much of its insulating value and cleaning will not clear it. In many cases the glass unit can be replaced without replacing the whole window frame. Our team will look at the window, explain your options and give you a clear quote. Tap Learn more to book a free assessment with Harlingen Glass & Mirror. | H4: Learn more | I4: https://harlingenglass.com/service/residential/ | J4: =I4&"?utm_source="&Settings!$C$5&"&utm_medium="&Settings!$C$6&"&utm_campaign="&Settings!$C$7&"&utm_content="&Settings!C15 -> https://harlingenglass.com/service/residential/?utm_source=google&utm_medium=organic&utm_campaign=gbp-posts-nov-2026&utm_content=nov26-03-faq-foggy-glass | L4: Tag: Glass FAQ Headline: Why Is My Window Foggy Inside the Glass? Sub-line: A failed seal is usually the cause, and it can often be fixed without a new frame. Button: Ask Our Team | M4: 2026-11-04_gbp-post-03_1200x900.png | N4: https://harlingenglass.com/wp-content/uploads/2024/01/IMG_20200117_133159154-scaled.jpg | P4: Not Published
B5: 1 | C5: 46331 | D5: =TEXT(C5,"ddd") -> Thu | E5: Local | F5: Family-Owned in Harlingen Since 1978 | G5: Harlingen Glass & Mirror has been part of the Harlingen community since 1978. Today the Shull family leads our team, and we still treat every customer like family. From homeowners and realtors to contractors and local businesses, the Valley has trusted us for more than 45 years with glass repair, shower enclosures, mirrors, windows and commercial glazing. Visit us at 1905 E. Harrison Ave. in Harlingen, Monday to Friday. Tap Learn more to meet the team. | H5: Learn more | I5: https://harlingenglass.com/company/ | J5: =I5&"?utm_source="&Settings!$C$5&"&utm_medium="&Settings!$C$6&"&utm_campaign="&Settings!$C$7&"&utm_content="&Settings!C16 -> https://harlingenglass.com/company/?utm_source=google&utm_medium=organic&utm_campaign=gbp-posts-nov-2026&utm_content=nov26-04-local-since-1978 | L5: Tag: Harlingen, TX Headline: Family-Owned Since 1978 Sub-line: 45+ years of glass work across the Rio Grande Valley Button: Meet the Team | M5: 2026-11-05_gbp-post-04_1200x900.png | N5: https://harlingenglass.com/wp-content/uploads/2024/01/McAllen-District-Office-12-04-08-001.jpg | P5: Not Published
B6: 1 | C6: 46332 | D6: =TEXT(C6,"ddd") -> Fri | E6: Service | F6: Custom Frameless Shower Enclosures | G6: Ready to replace that old shower curtain? A custom glass enclosure opens up your bathroom, is easy to keep clean and adds value to your home. Harlingen Glass & Mirror designs and installs frameless, semi-frameless and framed shower enclosures, sliding doors and glass partitions, made to fit your space. Book a free bathroom consultation. We will measure, show you the options and give you a clear quote. Financing is available. | H6: Book | I6: https://harlingenglass.com/service/bathroom-enclosures/ | J6: =I6&"?utm_source="&Settings!$C$5&"&utm_medium="&Settings!$C$6&"&utm_campaign="&Settings!$C$7&"&utm_content="&Settings!C17 -> https://harlingenglass.com/service/bathroom-enclosures/?utm_source=google&utm_medium=organic&utm_campaign=gbp-posts-nov-2026&utm_content=nov26-05-shower-enclosures | L6: Tag: Bathroom Glass Headline: Say Goodbye to the Shower Curtain Sub-line: Custom frameless, semi-frameless and framed enclosures Button: Free Bathroom Consultation | M6: 2026-11-06_gbp-post-05_1200x900.png | N6: https://harlingenglass.com/wp-content/uploads/2024/01/IMG_20231208_134141.jpg | P6: Not Published
B7: 2 | C7: 46335 | D7: =TEXT(C7,"ddd") -> Mon | E7: FAQ | F7: FAQ: Frameless vs Semi-Frameless vs Framed Shower Doors | G7: FAQ: Frameless, semi-frameless or framed: which shower enclosure is right for me? Framed enclosures use metal around the glass and are usually the most budget-friendly. Semi-frameless enclosures use less metal for a cleaner look. Frameless enclosures use thicker glass with minimal hardware for the most open, modern feel. Sliding and hinged doors are available, with clear, frosted or patterned glass depending on the privacy you want. Tap Learn more and our team will help you choose the best fit for your bathroom. | H7: Learn more | I7: https://harlingenglass.com/service/bathroom-enclosures/ | J7: =I7&"?utm_source="&Settings!$C$5&"&utm_medium="&Settings!$C$6&"&utm_campaign="&Settings!$C$7&"&utm_content="&Settings!C18 -> https://harlingenglass.com/service/bathroom-enclosures/?utm_source=google&utm_medium=organic&utm_campaign=gbp-posts-nov-2026&utm_content=nov26-06-faq-shower-types | L7: Tag: Glass FAQ Headline: Which Shower Door Is Right for You? Labels: Frameless, Sliding, Semi-Frameless Button: Compare Styles | M7: 2026-11-09_gbp-post-06_1200x900.png | N7: https://harlingenglass.com/wp-content/uploads/2024/01/ShowerDoor-scaled.jpg https://harlingenglass.com/wp-content/uploads/2024/01/image00004.jpg https://harlingenglass.com/wp-content/uploads/2024/01/IMG_20231208_134144.jpg | P7: Not Published
B8: 2 | C8: 46336 | D8: =TEXT(C8,"ddd") -> Tue | E8: Service | F8: 3M Security Window Film for Texas Schools | G8: Is your campus ready for Texas Education Agency safety requirements? Harlingen Glass & Mirror installs 3M Security Window Film to strengthen school windows and glass doors. The film helps hold broken glass together and slows forced entry, giving staff valuable response time. Work with a 3M authorized team so your film is installed correctly and meets requirements. Tap Book to schedule a free campus walkthrough. | H8: Book | I8: https://harlingenglass.com/service/3m-security-film/ | J8: =I8&"?utm_source="&Settings!$C$5&"&utm_medium="&Settings!$C$6&"&utm_campaign="&Settings!$C$7&"&utm_content="&Settings!C19 -> https://harlingenglass.com/service/3m-security-film/?utm_source=google&utm_medium=organic&utm_campaign=gbp-posts-nov-2026&utm_content=nov26-07-3m-security-film | L8: Tag: 3M Security Window Film Headline: Stronger Glass. Safer Campuses. Sub-line: TEA-focused installs by a 3M authorized team Button: Book a Campus Walkthrough | M8: 2026-11-10_gbp-post-07_1200x900.png | N8: https://harlingenglass.com/wp-content/uploads/2024/01/Rio-Hondo-Middle-School-3.jpg | P8: Not Published
B9: 2 | C9: 46337 | D9: =TEXT(C9,"ddd") -> Wed | E9: Local | F9: Cold Front Season: Check Your Window Seals | G9: Cold fronts in the Rio Grande Valley are a good reminder to check your windows and doors. If you feel a draft, see gaps around the frame or notice fog between the panes, your windows may not be sealing properly. Fixing them now keeps your home comfortable and helps before the summer heat returns. Harlingen Glass & Mirror serves homeowners across Harlingen and the Valley. Tap Learn more to book a free assessment. | H9: Learn more | I9: https://harlingenglass.com/service/residential/ | J9: =I9&"?utm_source="&Settings!$C$5&"&utm_medium="&Settings!$C$6&"&utm_campaign="&Settings!$C$7&"&utm_content="&Settings!C20 -> https://harlingenglass.com/service/residential/?utm_source=google&utm_medium=organic&utm_campaign=gbp-posts-nov-2026&utm_content=nov26-08-cold-front-check | L9: Tag: Rio Grande Valley Headline: Feel a Draft? Check Your Seals. Sub-line: Cold front season is the time to catch leaky windows Button: Free Assessment | M9: 2026-11-11_gbp-post-08_1200x900.png | N9: https://harlingenglass.com/wp-content/uploads/2024/01/image00003.jpg | P9: Not Published
B10: 2 | C10: 46338 | D10: =TEXT(C10,"ddd") -> Thu | E10: FAQ | F10: FAQ: Does Any Security Film Meet School Requirements? | G10: FAQ: Does any security window film meet school safety requirements? Not always. Schools sometimes discover their film does not meet requirements after it has been installed, which can mean paying twice. The film product, how it is attached and who installs it all matter. Harlingen Glass & Mirror installs 3M Security Window Film as a 3M authorized team and can walk your campus to check vulnerable entry points. Tap Learn more to request your free security film assessment. | H10: Learn more | I10: https://harlingenglass.com/service/3m-security-film/ | J10: =I10&"?utm_source="&Settings!$C$5&"&utm_medium="&Settings!$C$6&"&utm_campaign="&Settings!$C$7&"&utm_content="&Settings!C21 -> https://harlingenglass.com/service/3m-security-film/?utm_source=google&utm_medium=organic&utm_campaign=gbp-posts-nov-2026&utm_content=nov26-09-faq-security-film | L10: Tag: Security Film FAQ Headline: Is All Security Film Compliant? Sub-line: Not always. The film, how it's attached and who installs it all matter. Button: Free Film Assessment | M10: 2026-11-12_gbp-post-09_1200x900.png | N10: https://harlingenglass.com/wp-content/uploads/2024/01/Harlingen-Middle-School-Screw-Locations-Ext-Doors-011.jpg | P10: Not Published
B11: 2 | C11: 46339 | D11: =TEXT(C11,"ddd") -> Fri | E11: Service | F11: Commercial Storefront Glass Repair and Replacement | G11: A broken storefront window or door is a security risk and the first thing customers notice. Harlingen Glass & Mirror repairs and replaces commercial glass for businesses across the Rio Grande Valley, including storefront glass, entry doors, fire-rated glass, thermal glazing and multi-story projects. With more than 45 years in commercial glazing, our team works to meet safety standards while keeping your property looking professional. Tap Learn more to request a free assessment. | H11: Learn more | I11: https://harlingenglass.com/service/commercial-glass/ | J11: =I11&"?utm_source="&Settings!$C$5&"&utm_medium="&Settings!$C$6&"&utm_campaign="&Settings!$C$7&"&utm_content="&Settings!C22 -> https://harlingenglass.com/service/commercial-glass/?utm_source=google&utm_medium=organic&utm_campaign=gbp-posts-nov-2026&utm_content=nov26-10-commercial-storefront | L11: Tag: Commercial Glazing Headline: Your Storefront Is Your First Impression Sub-line: Storefronts, entry doors and multi-story glazing Button: Request an Assessment | M11: 2026-11-13_gbp-post-10_1200x900.png | N11: https://harlingenglass.com/wp-content/uploads/2024/01/IMG_0499-scaled.jpg | P11: Not Published
B12: 3 | C12: 46342 | D12: =TEXT(C12,"ddd") -> Mon | E12: Promotional | F12: Financing Available for Glass Upgrades | G12: Planning a new shower enclosure, window upgrade or mirror project but want to spread the cost? Harlingen Glass & Mirror has partnered with Synchrony Bank to offer financing options for home remodeling and upgrade projects. Ask about financing when you request your quote. Our team will measure, recommend the right glass for your project and give you a clear price before any work begins. Tap Learn more to get started. | H12: Learn more | I12: https://harlingenglass.com/contact/ | J12: =I12&"?utm_source="&Settings!$C$5&"&utm_medium="&Settings!$C$6&"&utm_campaign="&Settings!$C$7&"&utm_content="&Settings!C23 -> https://harlingenglass.com/contact/?utm_source=google&utm_medium=organic&utm_campaign=gbp-posts-nov-2026&utm_content=nov26-11-financing | L12: Tag: Financing Available Headline: Upgrade Now, Pay Over Time Sub-line: Financing options through Synchrony Bank Button: Ask About Financing | M12: 2026-11-16_gbp-post-11_1200x900.png | N12: https://harlingenglass.com/wp-content/uploads/2024/01/IMG_20231208_134139.jpg | P12: Not Published
B13: 3 | C13: 46343 | D13: =TEXT(C13,"ddd") -> Tue | E13: Service | F13: Custom Mirrors for Homes, Gyms and Studios | G13: A custom mirror can make a bathroom feel bigger, brighten a bedroom or finish off an entryway. Harlingen Glass & Mirror cuts and installs custom mirrors for homes and businesses across the Rio Grande Valley. We help you choose the size, edge and placement, then handle the full installation. We also install glass tabletops, shelves and custom shower doors. Tap Learn more to get a free quote. | H13: Learn more | I13: https://harlingenglass.com/service/interior/ | J13: =I13&"?utm_source="&Settings!$C$5&"&utm_medium="&Settings!$C$6&"&utm_campaign="&Settings!$C$7&"&utm_content="&Settings!C24 -> https://harlingenglass.com/service/interior/?utm_source=google&utm_medium=organic&utm_campaign=gbp-posts-nov-2026&utm_content=nov26-12-custom-mirrors | L13: Tag: Custom Mirrors Headline: Make Any Room Feel Bigger Sub-line: Cut to size and installed for homes and businesses Button: Get a Free Quote | M13: 2026-11-17_gbp-post-12_1200x900.png | N13: https://harlingenglass.com/wp-content/uploads/2024/01/IMG_20231208_134148.jpg | P13: Not Published
B14: 3 | C14: 46344 | D14: =TEXT(C14,"ddd") -> Wed | E14: FAQ | F14: FAQ: What Warranty Does Harlingen Glass Offer? | G14: FAQ: Does Harlingen Glass & Mirror offer a warranty? Yes. Many of the products we install carry a manufacturer warranty of up to 3 years, and we provide a 1-year installation warranty on specific products. Our team will explain the coverage that applies to your project before we start. We hold ourselves to a high standard, from sales and service to installation and warranty. Tap Learn more to see why the Valley has trusted us since 1978. | H14: Learn more | I14: https://harlingenglass.com/company/ | J14: =I14&"?utm_source="&Settings!$C$5&"&utm_medium="&Settings!$C$6&"&utm_campaign="&Settings!$C$7&"&utm_content="&Settings!C25 -> https://harlingenglass.com/company/?utm_source=google&utm_medium=organic&utm_campaign=gbp-posts-nov-2026&utm_content=nov26-13-faq-warranty | L14: Tag: Glass FAQ Headline: Is Your Glass Work Under Warranty? Sub-line: Up to 3-year manufacturer warranty and a 1-year install warranty on specific products. Button: See Coverage | M14: 2026-11-18_gbp-post-13_1200x900.png | N14: https://harlingenglass.com/wp-content/uploads/2024/01/IMG_20231208_134144.jpg | P14: Not Published
B15: 3 | C15: 46345 | D15: =TEXT(C15,"ddd") -> Thu | E15: Local | F15: Get Your Glass Guest-Ready for Thanksgiving | G15: Getting your home ready for Thanksgiving guests in the Valley? Take a quick walk around: check for chipped tabletops, cracked mirrors, sliding glass doors that stick, and windows that do not seal properly. Small issues are usually faster and less expensive to fix before they spread. Harlingen Glass & Mirror has helped Harlingen families get their homes ready for the holidays for more than 45 years. Tap Learn more to book a repair. | H15: Learn more | I15: https://harlingenglass.com/service/residential/ | J15: =I15&"?utm_source="&Settings!$C$5&"&utm_medium="&Settings!$C$6&"&utm_campaign="&Settings!$C$7&"&utm_content="&Settings!C26 -> https://harlingenglass.com/service/residential/?utm_source=google&utm_medium=organic&utm_campaign=gbp-posts-nov-2026&utm_content=nov26-14-holiday-glass-check | L15: Tag: Holiday Ready Headline: Guest-Ready Glass for Thanksgiving Sub-line: Fix chipped tabletops, cracked mirrors and sticky doors Button: Book a Repair | M15: 2026-11-19_gbp-post-14_1200x900.png | N15: https://harlingenglass.com/wp-content/uploads/2024/01/IMG_20231208_134134.jpg | P15: Not Published
B16: 3 | C16: 46346 | D16: =TEXT(C16,"ddd") -> Fri | E16: Service | F16: Energy-Efficient Low-E Window Replacement | G16: Old or poorly sealed windows let cool air out in summer and warm air out in winter, which makes your AC and heater work harder all year in the Valley. Harlingen Glass & Mirror installs energy-efficient replacement windows, including Low-E glass that helps reduce heat and UV coming into your home without blocking natural light. Book a free window inspection and we will show you where you can save. Tap Learn more to get started. | H16: Learn more | I16: https://harlingenglass.com/service/residential-window-replacement/ | J16: =I16&"?utm_source="&Settings!$C$5&"&utm_medium="&Settings!$C$6&"&utm_campaign="&Settings!$C$7&"&utm_content="&Settings!C27 -> https://harlingenglass.com/service/residential-window-replacement/?utm_source=google&utm_medium=organic&utm_campaign=gbp-posts-nov-2026&utm_content=nov26-15-low-e-windows | L16: Tag: Energy-Efficient Windows Headline: Lower Bills. Cooler Rooms. Sub-line: Low-E glass that cuts heat without blocking light Button: Free Window Inspection | M16: 2026-11-20_gbp-post-15_1200x900.png | N16: https://harlingenglass.com/wp-content/uploads/2024/01/IMG_20200123_141554436-scaled.jpg | P16: Not Published
B17: 4 | C17: 46349 | D17: =TEXT(C17,"ddd") -> Mon | E17: Promotional | F17: Free Security Film Assessment Before Winter Break | G17: Winter break is one of the best times to upgrade campus glass with less disruption for students and staff. Book a free security film assessment with Harlingen Glass & Mirror. We will walk your campus, check windows and glass doors, and recommend the right 3M Security Window Film for each entry point. Book early to plan installs during the break. Tap View offer to schedule your walkthrough. | H17: View offer | I17: https://harlingenglass.com/service/3m-security-film/ | J17: =I17&"?utm_source="&Settings!$C$5&"&utm_medium="&Settings!$C$6&"&utm_campaign="&Settings!$C$7&"&utm_content="&Settings!C28 -> https://harlingenglass.com/service/3m-security-film/?utm_source=google&utm_medium=organic&utm_campaign=gbp-posts-nov-2026&utm_content=nov26-16-winter-break-assessment | L17: Tag: For Schools Headline: Free Security Film Assessment Sub-line: Plan installs during winter break Button: Schedule a Walkthrough | M17: 2026-11-23_gbp-post-16_1200x900.png | N17: https://harlingenglass.com/wp-content/uploads/2024/01/IDEA-Toros-College-Prep.jpg | O17: Offer dates: Nov 23 to Dec 18, 2026 (confirm). Terms: assessment is free; installation quoted separately. | P17: Not Published
B18: 4 | C18: 46350 | D18: =TEXT(C18,"ddd") -> Tue | E18: Service | F18: Fire-Rated and Bullet-Resistant Commercial Glass | G18: Some businesses need more than standard glass. Banks, clinics, offices and government buildings often require fire-rated or bullet-resistant glass to meet safety standards. Harlingen Glass & Mirror supplies and installs fire-rated glass, bullet-resistant glass barriers, thermal glazing and glass railing systems for commercial projects across South Texas. Tap Learn more to talk to our commercial team about your project. | H18: Learn more | I18: https://harlingenglass.com/service/commercial-glass/ | J18: =I18&"?utm_source="&Settings!$C$5&"&utm_medium="&Settings!$C$6&"&utm_campaign="&Settings!$C$7&"&utm_content="&Settings!C29 -> https://harlingenglass.com/service/commercial-glass/?utm_source=google&utm_medium=organic&utm_campaign=gbp-posts-nov-2026&utm_content=nov26-17-fire-bullet-resistant | L18: Tag: Commercial Safety Glass Headline: Glass Built for Safety Standards Sub-line: Fire-rated, bullet-resistant and thermal glazing Button: Talk to Our Commercial Team | M18: 2026-11-24_gbp-post-17_1200x900.png | N18: https://harlingenglass.com/wp-content/uploads/2024/01/McAllen-District-Office-12-04-08-002.jpg | P18: Not Published
B19: 4 | C19: 46351 | D19: =TEXT(C19,"ddd") -> Wed | E19: FAQ | F19: FAQ: Repair or Replace a Cracked Window? | G19: FAQ: Should I repair a small crack in my window or replace the glass? A small crack can spread with temperature changes, wind and everyday use, and it can weaken the whole pane. In most cases, replacing the damaged glass is the safer long-term fix, and it is often quicker than people expect. Our team will look at the damage and tell you honestly what makes sense. Tap Learn more to read our guide and book a visit. | H19: Learn more | I19: https://harlingenglass.com/blog/dont-let-a-small-crack-turn-into-a-big-problem/ | J19: =I19&"?utm_source="&Settings!$C$5&"&utm_medium="&Settings!$C$6&"&utm_campaign="&Settings!$C$7&"&utm_content="&Settings!C30 -> https://harlingenglass.com/blog/dont-let-a-small-crack-turn-into-a-big-problem/?utm_source=google&utm_medium=organic&utm_campaign=gbp-posts-nov-2026&utm_content=nov26-18-faq-cracked-window | L19: Tag: Glass FAQ Headline: Small Crack Today, Big Problem Tomorrow? Sub-line: Cracks spread with heat, wind and daily use. Here's when to replace the pane. Button: Book a Visit | M19: 2026-11-25_gbp-post-18_1200x900.png | N19: https://unsplash.com/photos/_enXmoXudAk (Unsplash licence) | P19: Not Published
B20: 4 | C20: 46352 | D20: =TEXT(C20,"ddd") -> Thu | E20: Local | F20: Happy Thanksgiving from Harlingen Glass & Mirror | G20: Happy Thanksgiving from all of us at Harlingen Glass & Mirror. Thank you to the homeowners, realtors, contractors and businesses across Harlingen and the Rio Grande Valley who have trusted our family-owned shop for more than 45 years. Every project you send our way means a lot to our team. Hosting family this week? If a cracked mirror or a sticky glass door needs attention after the holiday, we are here to help. Tap Learn more to reach our team. | H20: Learn more | I20: https://harlingenglass.com/contact/ | J20: =I20&"?utm_source="&Settings!$C$5&"&utm_medium="&Settings!$C$6&"&utm_campaign="&Settings!$C$7&"&utm_content="&Settings!C31 -> https://harlingenglass.com/contact/?utm_source=google&utm_medium=organic&utm_campaign=gbp-posts-nov-2026&utm_content=nov26-19-thanksgiving | L20: Tag: Happy Thanksgiving Headline: Thankful for Our Valley Sub-line: From our family to yours Button: | M20: 2026-11-26_gbp-post-19_1200x900.png | N20: https://harlingenglass.com/wp-content/uploads/2025/01/fbinfoo-scaled.jpg (cropped) | P20: Not Published
B21: 4 | C21: 46353 | D21: =TEXT(C21,"ddd") -> Fri | E21: Promotional | F21: Free Bathroom Glass Consultation | G21: Thinking about a bathroom refresh before the new year? See what a custom glass enclosure can do. Book a free bathroom consultation with Harlingen Glass & Mirror. We will measure your space, show you frameless, semi-frameless and framed options, and give you a clear quote with no pressure. Financing is available. Tap View offer to book your free consultation. | H21: View offer | I21: https://harlingenglass.com/service/bathroom-enclosures/ | J21: =I21&"?utm_source="&Settings!$C$5&"&utm_medium="&Settings!$C$6&"&utm_campaign="&Settings!$C$7&"&utm_content="&Settings!C32 -> https://harlingenglass.com/service/bathroom-enclosures/?utm_source=google&utm_medium=organic&utm_campaign=gbp-posts-nov-2026&utm_content=nov26-20-free-bath-consult | L21: Tag: Free Consultation Headline: Before & After Sub-line: Book a free bathroom glass consultation Button: Book Free Consultation | M21: 2026-11-27_gbp-post-20_1200x900.png | N21: https://harlingenglass.com/wp-content/uploads/2024/01/before.jpg https://harlingenglass.com/wp-content/uploads/2024/01/after.jpg | O21: Offer dates: Nov 27 to Dec 31, 2026 (confirm). Terms: free in-home consultation and quote; no obligation. | P21: Not Published
B22: 5 | C22: 46356 | D22: =TEXT(C22,"ddd") -> Mon | E22: Service | F22: Custom Glass Tabletops and Shelves | G22: Protect your wood furniture or update a room with a custom glass tabletop or glass shelves. Harlingen Glass & Mirror cuts glass to your exact size and shape, with clean, polished edges for homes, offices and restaurants. We also replace broken tabletops and shelves. Tap Learn more to get a free quote from your local one-stop custom glass shop. | H22: Learn more | I22: https://harlingenglass.com/service/interior/ | J22: =I22&"?utm_source="&Settings!$C$5&"&utm_medium="&Settings!$C$6&"&utm_campaign="&Settings!$C$7&"&utm_content="&Settings!C33 -> https://harlingenglass.com/service/interior/?utm_source=google&utm_medium=organic&utm_campaign=gbp-posts-nov-2026&utm_content=nov26-21-glass-tabletops | L22: Tag: Custom Glass Headline: Cut to Your Size, Polished to Perfection Sub-line: Glass tabletops and shelves for homes and offices Button: Get a Free Quote | M22: 2026-11-30_gbp-post-21_1200x900.png | N22: https://harlingenglass.com/wp-content/uploads/2024/01/image00009.jpg | P22: Not Published
B23: 5 | C23: 46357 | D23: =TEXT(C23,"ddd") -> Tue | E23: Local | F23: Project Spotlight: Glass Across the Rio Grande Valley | G23: From school campuses and clinics to fire stations and public buildings, Harlingen Glass & Mirror has helped build and protect properties across the Rio Grande Valley. Our commercial team handles storefronts, curtain walls, entry systems, fire-rated glass and multi-story glazing, with the same care we bring to every home project. Planning a commercial project in the Valley? Tap Learn more to see our work. | H23: Learn more | I23: https://harlingenglass.com/service/commercial-glass/ | J23: =I23&"?utm_source="&Settings!$C$5&"&utm_medium="&Settings!$C$6&"&utm_campaign="&Settings!$C$7&"&utm_content="&Settings!C34 -> https://harlingenglass.com/service/commercial-glass/?utm_source=google&utm_medium=organic&utm_campaign=gbp-posts-nov-2026&utm_content=nov26-22-project-spotlight | L23: Tag: Project Spotlight Headline: Built Across the Valley Sub-line: Schools, clinics and public buildings Button: See Our Projects | M23: 2026-12-01_gbp-post-22_1200x900.png | N23: https://harlingenglass.com/wp-content/uploads/2024/01/45130555_1967058790260758_3379670728264646656_n.jpg https://harlingenglass.com/wp-content/uploads/2024/01/Rio-Hondo-Middle-School-2.jpg https://harlingenglass.com/wp-content/uploads/2024/01/Spi-Fire-Station-No-1.jpg | P23: Not Published

Sheet Settings
A1: Tracking settings
A2: Edit values in column C. Every Tracked CTA URL on the calendar tab updates automatically.
B4: Setting | C4: Value | D4: Note
B5: UTM source | C5: google | D5: Keep as google
B6: UTM medium | C6: organic | D6: Keep as organic
B7: UTM campaign | C7: gbp-posts-nov-2026 | D7: One campaign for this month
B8: Website domain | C8: harlingenglass.com | D8: QA checks every landing page stays on this domain
B11: UTM content per post (unique, so each post is tracked separately in Google Analytics)
B12: Post # | C12: utm_content | D12: Post Title
B13: 1 | C13: nov26-01-window-repair | D13: ='harlingenglass.com'!F2 -> Cracked or Foggy Window? Residential Glass Repair in Harlingen
B14: 2 | C14: nov26-02-buy3-get1 | D14: ='harlingenglass.com'!F3 -> Buy 3 Windows, Get the 4th Window Free
B15: 3 | C15: nov26-03-faq-foggy-glass | D15: ='harlingenglass.com'!F4 -> FAQ: Why Is My Double-Pane Window Foggy?
B16: 4 | C16: nov26-04-local-since-1978 | D16: ='harlingenglass.com'!F5 -> Family-Owned in Harlingen Since 1978
B17: 5 | C17: nov26-05-shower-enclosures | D17: ='harlingenglass.com'!F6 -> Custom Frameless Shower Enclosures
B18: 6 | C18: nov26-06-faq-shower-types | D18: ='harlingenglass.com'!F7 -> FAQ: Frameless vs Semi-Frameless vs Framed Shower Doors
B19: 7 | C19: nov26-07-3m-security-film | D19: ='harlingenglass.com'!F8 -> 3M Security Window Film for Texas Schools
B20: 8 | C20: nov26-08-cold-front-check | D20: ='harlingenglass.com'!F9 -> Cold Front Season: Check Your Window Seals
B21: 9 | C21: nov26-09-faq-security-film | D21: ='harlingenglass.com'!F10 -> FAQ: Does Any Security Film Meet School Requirements?
B22: 10 | C22: nov26-10-commercial-storefront | D22: ='harlingenglass.com'!F11 -> Commercial Storefront Glass Repair and Replacement
B23: 11 | C23: nov26-11-financing | D23: ='harlingenglass.com'!F12 -> Financing Available for Glass Upgrades
B24: 12 | C24: nov26-12-custom-mirrors | D24: ='harlingenglass.com'!F13 -> Custom Mirrors for Homes, Gyms and Studios
... B34: 22 | C34: nov26-22-project-spotlight | D34: ='harlingenglass.com'!F23 -> Project Spotlight: Glass Across the Rio Grande Valley

Sheet Banner & Brand Kit
A1: Banner and brand kit
A2: Every banner uses the website's own logo, colours and fonts. Size 1200 x 900 px (4:3), the ratio GBP displays best.
B4: Item | C4: Value | D4: Note
B5: Logo source (website) | C5: https://harlingenglass.com/wp-content/uploads/2024/11/LOGO-1.jpg | D5: Full logo on a white rounded chip, top left of every banner.
B6: Banner size | C6: 1200 x 900 px PNG | D6: 4:3 ratio. Files are in deliverables/gbp-calendars/banners/harlingen-glass/
B7: Brand motif | C7: Slanted translucent glass panes taken from the logo mark. | D7: Gives the series a consistent, premium look
B8: Photos | C8: Real project photos from harlingenglass.com | D8: Source URL for every banner is on the calendar tab
B9: Font: Headings | C9: Metrophobic | D9: Same as website H1 to H3
B10: Font: Body / labels | C10: Roboto | D10: Same as website body text
B12: Colour palette (matched to the website)
B13: Colour | C13: Hex | D13: Where it comes from | E13: Used on banners for | F13: Swatch
B14: Primary navy | C14: #004D71 | D14: Logo wordmark and panes | E14: Background panels, offer highlight
B15: Charcoal | C15: #2C353D | D15: Website navigation and text | E15: Dark overlays
B16: Accent cyan | C16: #38C6F4 | D16: Logo glass panes, website buttons | E16: Headline accent word, button chips
B17: Aqua | C17: #75CDD7 | D17: Logo glass panes | E17: Glass pane motif
B18: Light blue | C18: #ABDFEA | D18: Logo glass panes | E18: Soft tints
B19: White | C19: #FFFFFF | D19: Website background | E19: Text on dark, logo chip
B21: Overlay text rules (GBP safe)
B22: Rule | C22: Detail
B23: Length | C23: Tag 2 to 4 words, headline 3 to 7 words, one sub-line, one button label.
B24: Contact details | C24: No phone numbers, emails, web addresses or social handles on any banner.
B25: Claims | C25: Only facts stated on the website (years in business, warranties, services, offers).
B26: Offers | C26: Offer banners match the GBP Offer title. Dates and terms live in the post, not on the image.
B27: Safe area | C27: Text and logo stay inside the centre 1000 x 750 px so the GBP thumbnail crop never cuts them.
B28: Templates used | C28: Split photo, offer card, FAQ question, local spotlight, glass panel, 3-up compare, diagonal, frame, before/after, project spotlight, seasonal thank-you.

Sheet GBP Guidelines
A1: Google Business Profile post rules applied to this calendar
A2: Every post and banner was written and checked against these rules.
A4: # | B4: Rule | C4: How this calendar follows it | D4: Source
A5: 1 | B5: No phone numbers in post text. | C5: No post contains a phone number. Calls are tracked through the GBP Call button and Performance report instead. | D5: https://support.google.com/business/answer/7213077
A6: 2 | B6: Google may remove posts that contain unverified contact info such as email addresses or social media handles. | C6: No emails or social handles are written in any post. | D6: https://support.google.com/business/answer/7213077
A7: 3 | B7: Posts may not include links to websites not related to the business (Oct 2026 policy update). | C7: Every CTA links to a page on the business's own website. No links are written in the post text. | D7: https://www.relevantaudience.com/seo/google-business-profile-policy-bans-promotions-in-listings/ (reporting Google's Oct 6, 2026 update)
A8: 4 | B8: Offer posts need a title and start and end dates; coupon code, link and terms are optional. Offers get an automatic View offer button. | C8: All Offer posts have a title of 58 characters or fewer, dates and terms in the Offer Dates / Terms column. | D8: https://support.google.com/business/answer/7342169
A9: 5 | B9: Update posts can carry one action button with a link (book, order online, learn more and similar). | C9: Every Update post has one CTA button with a tracked link. | D9: https://support.google.com/business/answer/7342169
A10: 6 | B10: Post descriptions are limited to 1,500 characters. | C10: All posts are well under the limit; the QA tab checks this automatically. | D10: GBP post editor limit (Google Business Profile Manager)
A11: 7 | B11: Posts older than 6 months are archived unless a date range is set. | C11: Fresh posts go out twice a week so the profile always shows recent content. | D11: https://support.google.com/business/answer/7342169
A12: 8 | B12: Content must be relevant to the business and not low quality (no gibberish, misspellings or irrelevant content). | C12: Every post is about a real service, FAQ, local topic or offer taken from the website. | D12: https://support.google.com/business/answer/3038177
A13: 9 | B13: Promotions must clearly state their terms. | C13: Each offer lists dates and terms to confirm with the client before publishing. | D13: https://support.google.com/business/answer/3038177
A14: 10 | B14: Do not ask for personal or confidential information. | C14: CTAs send users to the website contact or booking pages; posts never ask for personal data. | D14: https://support.google.com/business/answer/3038177
A15: 11 | B15: You are responsible for making sure post content complies with applicable laws. | C15: Claims are limited to facts stated on the website. Items needing client confirmation are flagged in Notes. | D15: https://support.google.com/business/answer/7213077
A16: 12 | B16: Photos must follow the photo policy: real, relevant to the business, not misleading. | C16: Every banner uses a real photo from the business's own website (one HG post uses a licensed Unsplash photo). Overlay text is short (headline plus one line), with no phone numbers, emails, prices or claims that are not on the website. | D16: https://support.google.com/business/answer/7213077
A17: 13 | B17: Recommended post image: JPG or PNG, 10 KB to 5 MB, at least 400 x 300 px, 4:3 ratio displays best. | C17: Banners are 1200 x 900 px PNG (4:3). Key text sits inside the centre safe area so the GBP crop does not cut it. | D17: https://support.google.com/business/answer/7342169

Sheet QA Cross-Check
A1: QA cross-check (automatic)
A2: Formulas re-check every post when copy or links change. Every row should read Pass before scheduling.
A4: Post # | B4: Date | C4: Characters | D4: Max 1,500 chars | E4: No phone in text | F4: No email in text | G4: No link in text | H4: CTA set | I4: UTM on CTA link | J4: Link on business website | K4: Weekday (Mon to Fri) | L4: Banner file set | M4: Overall
A5: 1 | B5: ='harlingenglass.com'!C2 -> 46328 | C5: =LEN('harlingenglass.com'!G2) -> 510 | D5: =IF(LEN('harlingenglass.com'!G2)<=1500,"Pass","Fail") -> Pass | E5: =IF(SUMPRODUCT(--ISNUMBER(SEARCH({"956","428-6066","428.6066","4286066"},'harlingenglass.com'!G2)))=0,"Pass","Fail") -> Pass | F5: =IF(ISNUMBER(SEARCH("@",'harlingenglass.com'!G2)),"Fail","Pass") -> Pass | G5: =IF(OR(ISNUMBER(SEARCH("http",'harlingenglass.com'!G2)),ISNUMBER(SEARCH("www.",'harlingenglass.com'!G2)),ISNUMBER(SEARCH(".com",'harlingenglass.com'!G2))),"Fail","Pass") -> Pass | H5: =IF(LEN('harlingenglass.com'!H2)>0,"Pass","Fail") -> Pass | I5: =IF(AND(ISNUMBER(SEARCH("utm_source=google",'harlingenglass.com'!J2)),ISNUMBER(SEARCH("utm_content=",'harlingenglass.com'!J2))),"Pass","Fail") -> Pass | J5: =IF(ISNUMBER(SEARCH(Settings!$C$8,'harlingenglass.com'!I2)),"Pass","Fail") -> Pass | K5: =IF(WEEKDAY('harlingenglass.com'!C2,2)<=5,"Pass","Fail") -> Pass | L5: =IF(LEN('harlingenglass.com'!M2)>0,"Pass","Fail") -> Pass | M5: =IF(COUNTIF(D5:L5,"Fail")=0,"Pass","Fail") -> Pass
A6: 2 | B6: ='harlingenglass.com'!C3 -> 46329 | C6: =LEN('harlingenglass.com'!G3) -> 434 | D6: =IF(LEN('harlingenglass.com'!G3)<=1500,"Pass","Fail") -> Pass | E6: =IF(SUMPRODUCT(--ISNUMBER(SEARCH({"956","428-6066","428.6066","4286066"},'harlingenglass.com'!G3)))=0,"Pass","Fail") -> Pass | F6: =IF(ISNUMBER(SEARCH("@",'harlingenglass.com'!G3)),"Fail","Pass") -> Pass | G6: =IF(OR(ISNUMBER(SEARCH("http",'harlingenglass.com'!G3)),ISNUMBER(SEARCH("www.",'harlingenglass.com'!G3)),ISNUMBER(SEARCH(".com",'harlingenglass.com'!G3))),"Fail","Pass") -> Pass | H6: =IF(LEN('harlingenglass.com'!H3)>0,"Pass","Fail") -> Pass | I6: =IF(AND(ISNUMBER(SEARCH("utm_source=google",'harlingenglass.com'!J3)),ISNUMBER(SEARCH("utm_content=",'harlingenglass.com'!J3))),"Pass","Fail") -> Pass | J6: =IF(ISNUMBER(SEARCH(Settings!$C$8,'harlingenglass.com'!I3)),"Pass","Fail") -> Pass | K6: =IF(WEEKDAY('harlingenglass.com'!C3,2)<=5,"Pass","Fail") -> Pass | L6: =IF(LEN('harlingenglass.com'!M3)>0,"Pass","Fail") -> Pass | M6: =IF(COUNTIF(D6:L6,"Fail")=0,"Pass","Fail") -> Pass
A7: 3 | B7: ='harlingenglass.com'!C4 -> 46330 | C7: =LEN('harlingenglass.com'!G4) -> 512 | D7: =IF(LEN('harlingenglass.com'!G4)<=1500,"Pass","Fail") -> Pass | E7: =IF(SUMPRODUCT(--ISNUMBER(SEARCH({"956","428-6066","428.6066","4286066"},'harlingenglass.com'!G4)))=0,"Pass","Fail") -> Pass | F7: =IF(ISNUMBER(SEARCH("@",'harlingenglass.com'!G4)),"Fail","Pass") -> Pass | G7: =IF(OR(ISNUMBER(SEARCH("http",'harlingenglass.com'!G4)),ISNUMBER(SEARCH("www.",'harlingenglass.com'!G4)),ISNUMBER(SEARCH(".com",'harlingenglass.com'!G4))),"Fail","Pass") -> Pass | H7: =IF(LEN('harlingenglass.com'!H4)>0,"Pass","Fail") -> Pass | I7: =IF(AND(ISNUMBER(SEARCH("utm_source=google",'harlingenglass.com'!J4)),ISNUMBER(SEARCH("utm_content=",'harlingenglass.com'!J4))),"Pass","Fail") -> Pass | J7: =IF(ISNUMBER(SEARCH(Settings!$C$8,'harlingenglass.com'!I4)),"Pass","Fail") -> Pass | K7: =IF(WEEKDAY('harlingenglass.com'!C4,2)<=5,"Pass","Fail") -> Pass | L7: =IF(LEN('harlingenglass.com'!M4)>0,"Pass","Fail") -> Pass | M7: =IF(COUNTIF(D7:L7,"Fail")=0,"Pass","Fail") -> Pass
A8: 4 | B8: ='harlingenglass.com'!C5 -> 46331 | C8: =LEN('harlingenglass.com'!G5) -> 458 | D8: =IF(LEN('harlingenglass.com'!G5)<=1500,"Pass","Fail") -> Pass | E8: =IF(SUMPRODUCT(--ISNUMBER(SEARCH({"956","428-6066","428.6066","4286066"},'harlingenglass.com'!G5)))=0,"Pass","Fail") -> Pass | F8: =IF(ISNUMBER(SEARCH("@",'harlingenglass.com'!G5)),"Fail","Pass") -> Pass | G8: =IF(OR(ISNUMBER(SEARCH("http",'harlingenglass.com'!G5)),ISNUMBER(SEARCH("www.",'harlingenglass.com'!G5)),ISNUMBER(SEARCH(".com",'harlingenglass.com'!G5))),"Fail","Pass") -> Pass | H8: =IF(LEN('harlingenglass.com'!H5)>0,"Pass","Fail") -> Pass | I8: =IF(AND(ISNUMBER(SEARCH("utm_source=google",'harlingenglass.com'!J5)),ISNUMBER(SEARCH("utm_content=",'harlingenglass.com'!J5))),"Pass","Fail") -> Pass | J8: =IF(ISNUMBER(SEARCH(Settings!$C$8,'harlingenglass.com'!I5)),"Pass","Fail") -> Pass | K8: =IF(WEEKDAY('harlingenglass.com'!C5,2)<=5,"Pass","Fail") -> Pass | L8: =IF(LEN('harlingenglass.com'!M5)>0,"Pass","Fail") -> Pass | M8: =IF(COUNTIF(D8:L8,"Fail")=0,"Pass","Fail") -> Pass
A9: 5 | B9: ='harlingenglass.com'!C6 -> 46332 | C9: =LEN('harlingenglass.com'!G6) -> 430 | D9: =IF(LEN('harlingenglass.com'!G6)<=1500,"Pass","Fail") -> Pass | E9: =IF(SUMPRODUCT(--ISNUMBER(SEARCH({"956","428-6066","428.6066","4286066"},'harlingenglass.com'!G6)))=0,"Pass","Fail") -> Pass | F9: =IF(ISNUMBER(SEARCH("@",'harlingenglass.com'!G6)),"Fail","Pass") -> Pass | G9: =IF(OR(ISNUMBER(SEARCH("http",'harlingenglass.com'!G6)),ISNUMBER(SEARCH("www.",'harlingenglass.com'!G6)),ISNUMBER(SEARCH(".com",'harlingenglass.com'!G6))),"Fail","Pass") -> Pass | H9: =IF(LEN('harlingenglass.com'!H6)>0,"Pass","Fail") -> Pass | I9: =IF(AND(ISNUMBER(SEARCH("utm_source=google",'harlingenglass.com'!J6)),ISNUMBER(SEARCH("utm_content=",'harlingenglass.com'!J6))),"Pass","Fail") -> Pass | J9: =IF(ISNUMBER(SEARCH(Settings!$C$8,'harlingenglass.com'!I6)),"Pass","Fail") -> Pass | K9: =IF(WEEKDAY('harlingenglass.com'!C6,2)<=5,"Pass","Fail") -> Pass | L9: =IF(LEN('harlingenglass.com'!M6)>0,"Pass","Fail") -> Pass | M9: =IF(COUNTIF(D9:L9,"Fail")=0,"Pass","Fail") -> Pass
A10: 6 | B10: ='harlingenglass.com'!C7 -> 46335 | C10: =LEN('harlingenglass.com'!G7) -> 520 | D10: =IF(LEN('harlingenglass.com'!G7)<=1500,"Pass","Fail") -> Pass | E10: =IF(SUMPRODUCT(--ISNUMBER(SEARCH({"956","428-6066","428.6066","4286066"},'harlingenglass.com'!G7)))=0,"Pass","Fail") -> Pass | F10: =IF(ISNUMBER(SEARCH("@",'harlingenglass.com'!G7)),"Fail","Pass") -> Pass | G10: =IF(OR(ISNUMBER(SEARCH("http",'harlingenglass.com'!G7)),ISNUMBER(SEARCH("www.",'harlingenglass.com'!G7)),ISNUMBER(SEARCH(".com",'harlingenglass.com'!G7))),"Fail","Pass") -> Pass | H10: =IF(LEN('harlingenglass.com'!H7)>0,"Pass","Fail") -> Pass | I10: =IF(AND(ISNUMBER(SEARCH("utm_source=google",'harlingenglass.com'!J7)),ISNUMBER(SEARCH("utm_content=",'harlingenglass.com'!J7))),"Pass","Fail") -> Pass | J10: =IF(ISNUMBER(SEARCH(Settings!$C$8,'harlingenglass.com'!I7)),"Pass","Fail") -> Pass | K10: =IF(WEEKDAY('harlingenglass.com'!C7,2)<=5,"Pass","Fail") -> Pass | L10: =IF(LEN('harlingenglass.com'!M7)>0,"Pass","Fail") -> Pass | M10: =IF(COUNTIF(D10:L10,"Fail")=0,"Pass","Fail") -> Pass
A11: 7 | B11: ='harlingenglass.com'!C8 -> 46336 | C11: =LEN('harlingenglass.com'!G8) -> 416 | D11: =IF(LEN('harlingenglass.com'!G8)<=1500,"Pass","Fail") -> Pass | E11: =IF(SUMPRODUCT(--ISNUMBER(SEARCH({"956","428-6066","428.6066","4286066"},'harlingenglass.com'!G8)))=0,"Pass","Fail") -> Pass | F11: =IF(ISNUMBER(SEARCH("@",'harlingenglass.com'!G8)),"Fail","Pass") -> Pass | G11: =IF(OR(ISNUMBER(SEARCH("http",'harlingenglass.com'!G8)),ISNUMBER(SEARCH("www.",'harlingenglass.com'!G8)),ISNUMBER(SEARCH(".com",'harlingenglass.com'!G8))),"Fail","Pass") -> Pass | H11: =IF(LEN('harlingenglass.com'!H8)>0,"Pass","Fail") -> Pass | I11: =IF(AND(ISNUMBER(SEARCH("utm_source=google",'harlingenglass.com'!J8)),ISNUMBER(SEARCH("utm_content=",'harlingenglass.com'!J8))),"Pass","Fail") -> Pass | J11: =IF(ISNUMBER(SEARCH(Settings!$C$8,'harlingenglass.com'!I8)),"Pass","Fail") -> Pass | K11: =IF(WEEKDAY('harlingenglass.com'!C8,2)<=5,"Pass","Fail") -> Pass | L11: =IF(LEN('harlingenglass.com'!M8)>0,"Pass","Fail") -> Pass | M11: =IF(COUNTIF(D11:L11,"Fail")=0,"Pass","Fail") -> Pass
A12: 8 | B12: ='harlingenglass.com'!C9 -> 46337 | C12: =LEN('harlingenglass.com'!G9) -> 417 | D12: =IF(LEN('harlingenglass.com'!G9)<=1500,"Pass","Fail") -> Pass | E12: =IF(SUMPRODUCT(--ISNUMBER(SEARCH({"956","428-6066","428.6066","4286066"},'harlingenglass.com'!G9)))=0,"Pass","Fail") -> Pass | F12: =IF(ISNUMBER(SEARCH("@",'harlingenglass.com'!G9)),"Fail","Pass") -> Pass | G12: =IF(OR(ISNUMBER(SEARCH("http",'harlingenglass.com'!G9)),ISNUMBER(SEARCH("www.",'harlingenglass.com'!G9)),ISNUMBER(SEARCH(".com",'harlingenglass.com'!G9))),"Fail","Pass") -> Pass | H12: =IF(LEN('harlingenglass.com'!H9)>0,"Pass","Fail") -> Pass | I12: =IF(AND(ISNUMBER(SEARCH("utm_source=google",'harlingenglass.com'!J9)),ISNUMBER(SEARCH("utm_content=",'harlingenglass.com'!J9))),"Pass","Fail") -> Pass | J12: =IF(ISNUMBER(SEARCH(Settings!$C$8,'harlingenglass.com'!I9)),"Pass","Fail") -> Pass | K12: =IF(WEEKDAY('harlingenglass.com'!C9,2)<=5,"Pass","Fail") -> Pass | L12: =IF(LEN('harlingenglass.com'!M9)>0,"Pass","Fail") -> Pass | M12: =IF(COUNTIF(D12:L12,"Fail")=0,"Pass","Fail") -> Pass
A13: 9 | B13: ='harlingenglass.com'!C10 -> 46338 | C13: =LEN('harlingenglass.com'!G10) -> 477 | D13: =IF(LEN('harlingenglass.com'!G10)<=1500,"Pass","Fail") -> Pass | E13: =IF(SUMPRODUCT(--ISNUMBER(SEARCH({"956","428-6066","428.6066","4286066"},'harlingenglass.com'!G10)))=0,"Pass","Fail") -> Pass | F13: =IF(ISNUMBER(SEARCH("@",'harlingenglass.com'!G10)),"Fail","Pass") -> Pass | G13: =IF(OR(ISNUMBER(SEARCH("http",'harlingenglass.com'!G10)),ISNUMBER(SEARCH("www.",'harlingenglass.com'!G10)),ISNUMBER(SEARCH(".com",'harlingenglass.com'!G10))),"Fail","Pass") -> Pass | H13: =IF(LEN('harlingenglass.com'!H10)>0,"Pass","Fail") -> Pass | I13: =IF(AND(ISNUMBER(SEARCH("utm_source=google",'harlingenglass.com'!J10)),ISNUMBER(SEARCH("utm_content=",'harlingenglass.com'!J10))),"Pass","Fail") -> Pass | J13: =IF(ISNUMBER(SEARCH(Settings!$C$8,'harlingenglass.com'!I10)),"Pass","Fail") -> Pass | K13: =IF(WEEKDAY('harlingenglass.com'!C10,2)<=5,"Pass","Fail") -> Pass | L13: =IF(LEN('harlingenglass.com'!M10)>0,"Pass","Fail") -> Pass | M13: =IF(COUNTIF(D13:L13,"Fail")=0,"Pass","Fail") -> Pass
A14: 10 | B14: ='harlingenglass.com'!C11 -> 46339 | C14: =LEN('harlingenglass.com'!G11) -> 484 | D14: =IF(LEN('harlingenglass.com'!G11)<=1500,"Pass","Fail") -> Pass | E14: =IF(SUMPRODUCT(--ISNUMBER(SEARCH({"956","428-6066","428.6066","4286066"},'harlingenglass.com'!G11)))=0,"Pass","Fail") -> Pass | F14: =IF(ISNUMBER(SEARCH("@",'harlingenglass.com'!G11)),"Fail","Pass") -> Pass | G14: =IF(OR(ISNUMBER(SEARCH("http",'harlingenglass.com'!G11)),ISNUMBER(SEARCH("www.",'harlingenglass.com'!G11)),ISNUMBER(SEARCH(".com",'harlingenglass.com'!G11))),"Fail","Pass") -> Pass | H14: =IF(LEN('harlingenglass.com'!H11)>0,"Pass","Fail") -> Pass | I14: =IF(AND(ISNUMBER(SEARCH("utm_source=google",'harlingenglass.com'!J11)),ISNUMBER(SEARCH("utm_content=",'harlingenglass.com'!J11))),"Pass","Fail") -> Pass | J14: =IF(ISNUMBER(SEARCH(Settings!$C$8,'harlingenglass.com'!I11)),"Pass","Fail") -> Pass | K14: =IF(WEEKDAY('harlingenglass.com'!C11,2)<=5,"Pass","Fail") -> Pass | L14: =IF(LEN('harlingenglass.com'!M11)>0,"Pass","Fail") -> Pass | M14: =IF(COUNTIF(D14:L14,"Fail")=0,"Pass","Fail") -> Pass
A15: 11 | B15: ='harlingenglass.com'!C12 -> 46342 | C15: =LEN('harlingenglass.com'!G12) -> 421 | D15: =IF(LEN('harlingenglass.com'!G12)<=1500,"Pass","Fail") -> Pass | E15: =IF(SUMPRODUCT(--ISNUMBER(SEARCH({"956","428-6066","428.6066","4286066"},'harlingenglass.com'!G12)))=0,"Pass","Fail") -> Pass | F15: =IF(ISNUMBER(SEARCH("@",'harlingenglass.com'!G12)),"Fail","Pass") -> Pass | G15: =IF(OR(ISNUMBER(SEARCH("http",'harlingenglass.com'!G12)),ISNUMBER(SEARCH("www.",'harlingenglass.com'!G12)),ISNUMBER(SEARCH(".com",'harlingenglass.com'!G12))),"Fail","Pass") -> Pass | H15: =IF(LEN('harlingenglass.com'!H12)>0,"Pass","Fail") -> Pass | I15: =IF(AND(ISNUMBER(SEARCH("utm_source=google",'harlingenglass.com'!J12)),ISNUMBER(SEARCH("utm_content=",'harlingenglass.com'!J12))),"Pass","Fail") -> Pass | J15: =IF(ISNUMBER(SEARCH(Settings!$C$8,'harlingenglass.com'!I12)),"Pass","Fail") -> Pass | K15: =IF(WEEKDAY('harlingenglass.com'!C12,2)<=5,"Pass","Fail") -> Pass | L15: =IF(LEN('harlingenglass.com'!M12)>0,"Pass","Fail") -> Pass | M15: =IF(COUNTIF(D15:L15,"Fail")=0,"Pass","Fail") -> Pass
A16: 12 | B16: ='harlingenglass.com'!C13 -> 46343 | C16: =LEN('harlingenglass.com'!G13) -> 395 | D16: =IF(LEN('harlingenglass.com'!G13)<=1500,"Pass","Fail") -> Pass | E16: =IF(SUMPRODUCT(--ISNUMBER(SEARCH({"956","428-6066","428.6066","4286066"},'harlingenglass.com'!G13)))=0,"Pass","Fail") -> Pass | F16: =IF(ISNUMBER(SEARCH("@",'harlingenglass.com'!G13)),"Fail","Pass") -> Pass | G16: =IF(OR(ISNUMBER(SEARCH("http",'harlingenglass.com'!G13)),ISNUMBER(SEARCH("www.",'harlingenglass.com'!G13)),ISNUMBER(SEARCH(".com",'harlingenglass.com'!G13))),"Fail","Pass") -> Pass | H16: =IF(LEN('harlingenglass.com'!H13)>0,"Pass","Fail") -> Pass | I16: =IF(AND(ISNUMBER(SEARCH("utm_source=google",'harlingenglass.com'!J13)),ISNUMBER(SEARCH("utm_content=",'harlingenglass.com'!J13))),"Pass","Fail") -> Pass | J16: =IF(ISNUMBER(SEARCH(Settings!$C$8,'harlingenglass.com'!I13)),"Pass","Fail") -> Pass | K16: =IF(WEEKDAY('harlingenglass.com'!C13,2)<=5,"Pass","Fail") -> Pass | L16: =IF(LEN('harlingenglass.com'!M13)>0,"Pass","Fail") -> Pass | M16: =IF(COUNTIF(D16:L16,"Fail")=0,"Pass","Fail") -> Pass
... A26: 22 | B26: ='harlingenglass.com'!C23 -> 46357 | C26: =LEN('harlingenglass.com'!G23) -> 409 | D26: =IF(LEN('harlingenglass.com'!G23)<=1500,"Pass","Fail") -> Pass | E26: =IF(SUMPRODUCT(--ISNUMBER(SEARCH({"956","428-6066","428.6066","4286066"},'harlingenglass.com'!G23)))=0,"Pass","Fail") -> Pass | F26: =IF(ISNUMBER(SEARCH("@",'harlingenglass.com'!G23)),"Fail","Pass") -> Pass | G26: =IF(OR(ISNUMBER(SEARCH("http",'harlingenglass.com'!G23)),ISNUMBER(SEARCH("www.",'harlingenglass.com'!G23)),ISNUMBER(SEARCH(".com",'harlingenglass.com'!G23))),"Fail","Pass") -> Pass | H26: =IF(LEN('harlingenglass.com'!H23)>0,"Pass","Fail") -> Pass | I26: =IF(AND(ISNUMBER(SEARCH("utm_source=google",'harlingenglass.com'!J23)),ISNUMBER(SEARCH("utm_content=",'harlingenglass.com'!J23))),"Pass","Fail") -> Pass | J26: =IF(ISNUMBER(SEARCH(Settings!$C$8,'harlingenglass.com'!I23)),"Pass","Fail") -> Pass | K26: =IF(WEEKDAY('harlingenglass.com'!C23,2)<=5,"Pass","Fail") -> Pass | L26: =IF(LEN('harlingenglass.com'!M23)>0,"Pass","Fail") -> Pass | M26: =IF(COUNTIF(D26:L26,"Fail")=0,"Pass","Fail") -> Pass
A28: Posts passing | B28: =COUNTIF(M5:M26,"Pass")&" of "&COUNTA(A5:A26) -> 22 of 22
A30: Post mix
A31: Category | B31: Posts
A32: Service | B32: =COUNTIF('harlingenglass.com'!$E$2:$E$23,"Service") -> 8
A33: FAQ | B33: =COUNTIF('harlingenglass.com'!$E$2:$E$23,"FAQ") -> 5
A34: Local | B34: =COUNTIF('harlingenglass.com'!$E$2:$E$23,"Local") -> 5
A35: Promotional | B35: =COUNTIF('harlingenglass.com'!$E$2:$E$23,"Promotional") -> 4
A36: Total | B36: =SUM(B32:B35) -> 22
