Workbook

Sheet Overview
A1: Harlingen Glass & Mirror: GBP Content Calendar and Citations
A2: 22 Google Business Profile posts in 11 weekly batches, plus citation work. Prepared Oct 26, 2026.
A4: Business snapshot (from the website)
A5: Field | B5: Value | C5: Source / note
A6: Business name (website footer) | B6: Harlingen Glass & Mirror | C6: Footer, harlingenglass.com. Also shown as 'Harlingen Glass Company' in page titles.
A7: Address | B7: 1905 E. Harrison Ave., Harlingen, TX 78550 | C7: Website footer
A8: Phone | B8: 956.428.6066 | C8: Website header and footer
A9: Email | B9: mainoffice@harlingenglass.com | C9: Footer. Hiring page uses info@harlingenglass.com.
A10: Hours | B10: Mon to Fri 8 AM to 5 PM; Sat and Sun closed | C10: Website footer
A11: Founded | B11: 1978; family-owned (Shull family) | C11: Home and Company pages
A12: Service area | B12: Harlingen and the Rio Grande Valley (South Texas) | C12: Home, service pages
A13: Main services | B13: Residential glass repair and replacement; window replacement (Low-E, energy-efficient); custom frameless, semi-frameless and framed shower enclosures; steam enclosures; custom mirrors; glass tabletops and shelves; storefront and commercial glazing; fire-rated and bullet-resistant glass; thermal glazing; glass railings; 3M Security Window Film for schools | C13: Service pages
A14: Active offers | B14: Buy 3 windows, get the 4th free; free window inspection; free bathroom consultation; free 3M security film assessment; Synchrony financing | C14: Window replacement, bathroom enclosures, 3M film and Home pages
A15: Trust signals | B15: 45+ years; family-owned; up to 3-year manufacturer warranty and 1-year installation warranty on specific products; 4.8 stars from 52 Google reviews (site widget); 3M authorized for security film | C15: Home and landing pages
A16: Social profiles | B16: Facebook: facebook.com/HGMTX; YouTube linked in header. No Instagram found. | C16: Website header
A17: Posting window | B17: Nov 3, 2026 to Jan 21, 2027: 2 posts per week (Tue and Thu, with holiday adjustments) | C17: This plan
A19: Tracking settings (edit here, all CTA links update)
A20: Setting | B20: Value | C20: Note
A21: UTM source | B21: google | C21: Keep as google
A22: UTM medium | B22: organic | C22: Keep as organic
A23: UTM campaign | B23: gbp-posts-nov26-jan27 | C23: One campaign for this 22-post run
A24: Website domain | B24: harlingenglass.com | C24: Used by the QA check that every link stays on the business website
A26: Post mix (counts update from the calendar)
A27: Category | B27: Posts | C27: Share
A28: Service | B28: =COUNTIF('Content Calendar'!$E$5:$E$26,"Service") -> 8 | C28: =IFERROR(B28/B32,0) -> 0.36363636
A29: FAQ | B29: =COUNTIF('Content Calendar'!$E$5:$E$26,"FAQ") -> 5 | C29: =IFERROR(B29/B32,0) -> 0.22727273
A30: Local | B30: =COUNTIF('Content Calendar'!$E$5:$E$26,"Local") -> 5 | C30: =IFERROR(B30/B32,0) -> 0.22727273
A31: Promotional | B31: =COUNTIF('Content Calendar'!$E$5:$E$26,"Promotional") -> 4 | C31: =IFERROR(B31/B32,0) -> 0.18181818
A32: Total | B32: =SUM(B28:B31) -> 22 | C32: =SUM(C28:C31) -> 1
A34: How to use this workbook
A35: Tab / item | B35: What it is
A36: 1. Overview | B36: Business facts, tracking settings and the post mix.
A37: 2. Website & Profile Audit | B37: What we found on the website, socials and old GBP posts, with fixes to make before posting.
A38: 3. GBP Guidelines | B38: Google rules every post follows, with sources.
A39: 4. Content Calendar | B39: All 22 posts: date, type, copy, CTA button and tracked link. Edit only Post Copy, dates, Status and Notes.
A40: 5. Weekly Batches | B40: One batch per week (2 posts). Prep and schedule each batch on the Monday.
A41: 6. Citations | B41: NAP to use everywhere, plus the citation list with status tracking.
A42: 7. QA Cross-Check | B42: Automatic checks on every post (length, no phone or email in text, CTA, UTM, link domain). All rows should read Pass.
A43: Editable cells | B43: Status and Notes columns, post dates, post copy, citation Status / Date / Live URL. Tracked URLs, counts and QA cells are formulas: do not overwrite.
A44: Example row | B44: Row 5 of the Content Calendar (post 01) shows the expected format for every column.

Sheet Website & Profile Audit
A1: Website, social media and GBP audit
A2: Checked Oct 26, 2026. Fix High priority items before the first post goes live.
A4: # | B4: Area | C4: Finding | D4: Evidence (URL) | E4: Recommended action | F4: Priority
A5: 1 | B5: Old GBP posts | C5: Previous GBP posts could not be checked: posts are only visible inside the profile or on Google Search, and no manager access was available. | D5: Google Business Profile | E5: Share manager access or screenshots of the last 10 posts, so the new posts don't repeat topics and we can confirm when the last post went live. | F5: High
A6: 2 | B6: NAP consistency | C6: The Interior service page says the company is 'located in Brownsville, TX', but the address everywhere else is Harlingen. | D6: https://harlingenglass.com/service/interior/ | E6: Change 'Brownsville, TX' to 'Harlingen, TX' so the website matches the GBP address. | F6: High
A7: 3 | B7: Business name | C7: The name appears in four versions: Harlingen Glass & Mirror, Harlingen Glass and Mirror, Harlingen Glass Company, Harlingen Glass Properties. | D7: Footer, page titles and Home page | E7: Use the exact GBP name on the website footer, contact page and every citation. | F7: High
A8: 4 | B8: Page titles | C8: The 3M Security Film page has the title 'Residential Glass Replacement in Harlingen', copied from another page. | D8: https://harlingenglass.com/service/3m-security-film/ | E8: Retitle it, for example: '3M Security Window Film for Texas Schools | Harlingen Glass & Mirror'. | F8: Medium
A9: 5 | B9: Duplicate content | C9: Two blog URLs end in '-copy' (copied posts that were published). | D9: https://harlingenglass.com/blog/why-fall-is-the-perfect-time-for-glass-repair-and-replacement-copy/ ; https://harlingenglass.com/blog/prepare-your-glass-for-the-holiday-season-copy/ | E9: Rename the slugs or merge them into the originals with a 301 redirect. GBP posts in this plan avoid linking to them. | F9: Medium
A10: 6 | B10: Placeholder content | C10: The project pages show placeholder text ('Aenean massa. Cum sociis natoque...') and only 3 projects. | D10: https://harlingenglass.com/pro/ | E10: Replace with real project photos and short write-ups. The same photos can be reused in GBP posts. | F10: Medium
A11: 7 | B11: Email | C11: Two emails are in use: mainoffice@ (footer) and info@ (hiring page). | D11: Footer and https://harlingenglass.com/hiring-contact/ | E11: Pick one main email for citations. | F11: Low
A12: 8 | B12: Spelling | C12: 'Shower Enclosers' is used instead of 'Shower Enclosures' on service pages. | D12: https://harlingenglass.com/service/interior/ | E12: Fix the spelling: it is a keyword for this service. | F12: Low
A13: 9 | B13: Social media | C13: Facebook (HGMTX) and YouTube are linked. Page content can't be read without logging in, so recent social posts were not reviewed. | D13: https://www.facebook.com/HGMTX | E13: Reuse GBP post photos and copy on Facebook the same week. Consider adding Instagram for shower and mirror before/after photos. | F13: Low
A14: 10 | B14: Reviews | C14: The site shows 4.8 stars from 52 Google reviews. | D14: Window replacement landing page widget | E14: Year-end posts invite customer feedback (no incentives). Reply to every review within 48 hours. | F14: Medium
A15: 11 | B15: Blog cadence | C15: Monthly seasonal blogs (Apr to Dec 2025) give good landing pages for posts. | D15: https://harlingenglass.com/blog/ | E15: Link GBP FAQ posts to the matching blogs to build relevance. | F15: Low

Sheet GBP Guidelines
A1: Google Business Profile post rules applied to this calendar
A2: Every post in the calendar was written and checked against these rules.
A4: # | B4: Rule | C4: How this calendar follows it | D4: Source
A5: 1 | B5: No phone numbers in post text. | C5: No post contains a phone number. Calls are tracked through the GBP Call button and Performance report instead. | D5: https://support.google.com/business/answer/7213077
A6: 2 | B6: Google may remove posts that contain unverified contact info such as email addresses or social media handles. | C6: No emails or social handles are written in any post. | D6: https://support.google.com/business/answer/7213077
A7: 3 | B7: Posts may not include links to websites not related to the business (Oct 2026 policy update). | C7: Every CTA links to a page on the business's own website. No links are written in the post text. | D7: https://www.relevantaudience.com/seo/google-business-profile-policy-bans-promotions-in-listings/ (reporting Google's Oct 6, 2026 update)
A8: 4 | B8: Offer posts need a title and start and end dates; coupon code, link and terms are optional. Offers get an automatic View offer button. | C8: All Offer posts have a title of 58 characters or fewer, dates and terms in the Offer Dates / Terms column. | D8: https://support.google.com/business/answer/7342169
A9: 5 | B9: Update posts can carry one action button with a link (book, order online, learn more and similar). | C9: Every Update post has one CTA button with a tracked link. | D9: https://support.google.com/business/answer/7342169
A10: 6 | B10: Post descriptions are limited to 1,500 characters. | C10: All posts are well under the limit; the QA tab checks this automatically. | D10: GBP post editor limit (Google Business Profile Manager)
A11: 7 | B11: Posts older than 6 months are archived unless a date range is set. | C11: Fresh posts go out twice a week so the profile always shows recent content. | D11: https://support.google.com/business/answer/7342169
A12: 8 | B12: Content must be relevant to the business and not low quality (no gibberish, misspellings or irrelevant content). | C12: Every post is about a real service, FAQ, local topic or offer taken from the website. | D12: https://support.google.com/business/answer/3038177
A13: 9 | B13: Promotions must clearly state their terms. | C13: Each offer lists dates and terms to confirm with the client before publishing. | D13: https://support.google.com/business/answer/3038177
A14: 10 | B14: Do not ask for personal or confidential information. | C14: CTAs send users to the website contact or booking pages; posts never ask for personal data. | D14: https://support.google.com/business/answer/3038177
A15: 11 | B15: You are responsible for making sure post content complies with applicable laws. | C15: Claims are limited to facts stated on the website. Items needing client confirmation are flagged in Notes. | D15: https://support.google.com/business/answer/7213077
A16: 12 | B16: Photos must follow the photo and video policy (real, relevant, no added text-heavy overlays). | C16: Image briefs ask for real project photos, not stock images. | D16: https://support.google.com/business/answer/7213077

Sheet Content Calendar
A1: GBP Content Calendar: 22 posts
A2: Tracked CTA URL is built by formula from the landing page and the Overview tracking settings.
A4: Post ID | B4: Batch | C4: Publish Date | D4: Day | E4: Category | F4: GBP Post Type | G4: Topic | H4: Target Keyword | I4: Offer Title | J4: Post Copy | K4: Characters | L4: CTA Button | M4: Landing Page | N4: UTM Content | O4: Tracked CTA URL | P4: Offer Dates / Terms | Q4: Image Brief | R4: Status | S4: Notes / Confirm with Client
A5: HG-01 | B5: 1 | C5: 46329 | D5: =TEXT(C5,"ddd") -> Tue | E5: Service | F5: Update | G5: Residential window glass repair | H5: window glass repair Harlingen | J5: Cracked pane, a window hit by a stray ball, or glass that looks foggy between the panes? Harlingen Glass & Mirror repairs and replaces residential glass across Harlingen and the Rio Grande Valley. We work on single and double-pane windows, sliding and swinging glass doors, tabletops and shelves. If it is made of glass, our team can fix it, replace it or install it. Family-owned since 1978, we measure on site and give you a clear quote before any work starts. Tap Learn more to request your free estimate. | K5: =LEN(J5) -> 510 | L5: Learn more | M5: https://harlingenglass.com/service/residential/ | N5: hg01-window-repair | O5: =M5&"?utm_source="&Overview!$B$21&"&utm_medium="&Overview!$B$22&"&utm_campaign="&Overview!$B$23&"&utm_content="&N5 -> https://harlingenglass.com/service/residential/?utm_source=google&utm_medium=organic&utm_campaign=gbp-posts-nov26-jan27&utm_content=hg01-window-repair | Q5: Real photo: technician replacing a residential window pane (before/after if available). | R5: Draft
A6: HG-02 | B6: 1 | C6: 46331 | D6: =TEXT(C6,"ddd") -> Thu | E6: Promotional | F6: Offer | G6: Window replacement offer | H6: window replacement Harlingen | I6: Buy 3 Windows, Get the 4th Window Free | J6: Old or drafty windows can push your energy bills up and leave hot and cold spots around the house. This season, upgrade to energy-efficient windows with Harlingen Glass & Mirror. Buy 3 windows and get the 4th window free. Every project starts with a free window inspection, expert advice and a clear quote, with no pressure. Serving Harlingen and the Rio Grande Valley for over 40 years. Tap View offer to book your free inspection. | K6: =LEN(J6) -> 434 | L6: View offer | M6: https://harlingenglass.com/service/residential-window-replacement/ | N6: hg02-buy3-get1 | O6: =M6&"?utm_source="&Overview!$B$21&"&utm_medium="&Overview!$B$22&"&utm_campaign="&Overview!$B$23&"&utm_content="&N6 -> https://harlingenglass.com/service/residential-window-replacement/?utm_source=google&utm_medium=organic&utm_campaign=gbp-posts-nov26-jan27&utm_content=hg02-buy3-get1 | P6: Offer dates: Nov 5 to Nov 30, 2026 (confirm). Terms: confirm eligible window types, minimum order and whether it combines with financing. | Q6: Real photo: newly installed residential windows, exterior view. | R6: Draft | S6: Offer is live on the website. Confirm dates and terms with the client before publishing.
A7: HG-03 | B7: 2 | C7: 46336 | D7: =TEXT(C7,"ddd") -> Tue | E7: FAQ | F7: Update | G7: Foggy double-pane windows | H7: foggy window repair | J7: FAQ: Why is my double-pane window foggy, and can it be fixed? Fog or moisture trapped between the two panes usually means the seal on the insulated glass unit has failed. Once that happens, the window loses much of its insulating value and cleaning will not clear it. In many cases the glass unit can be replaced without replacing the whole window frame. Our team will look at the window, explain your options and give you a clear quote. Tap Learn more to book a free assessment with Harlingen Glass & Mirror. | K7: =LEN(J7) -> 512 | L7: Learn more | M7: https://harlingenglass.com/service/residential/ | N7: hg03-faq-foggy-glass | O7: =M7&"?utm_source="&Overview!$B$21&"&utm_medium="&Overview!$B$22&"&utm_campaign="&Overview!$B$23&"&utm_content="&N7 -> https://harlingenglass.com/service/residential/?utm_source=google&utm_medium=organic&utm_campaign=gbp-posts-nov26-jan27&utm_content=hg03-faq-foggy-glass | Q7: Close-up photo of a fogged double-pane window next to a clear replacement. | R7: Draft | S7: Confirm the team replaces sealed units (IGUs) only, not just full windows.
A8: HG-04 | B8: 2 | C8: 46338 | D8: =TEXT(C8,"ddd") -> Thu | E8: Local | F8: Update | G8: Family-owned since 1978 | H8: glass company Harlingen TX | J8: Harlingen Glass & Mirror has been part of the Harlingen community since 1978. Today the Shull family leads our team, and we still treat every customer like family. From homeowners and realtors to contractors and local businesses, the Valley has trusted us for more than 45 years with glass repair, shower enclosures, mirrors, windows and commercial glazing. Visit us at 1905 E. Harrison Ave. in Harlingen, Monday to Friday. Tap Learn more to meet the team. | K8: =LEN(J8) -> 458 | L8: Learn more | M8: https://harlingenglass.com/company/ | N8: hg04-local-since-1978 | O8: =M8&"?utm_source="&Overview!$B$21&"&utm_medium="&Overview!$B$22&"&utm_campaign="&Overview!$B$23&"&utm_content="&N8 -> https://harlingenglass.com/company/?utm_source=google&utm_medium=organic&utm_campaign=gbp-posts-nov26-jan27&utm_content=hg04-local-since-1978 | Q8: Team photo in front of the shop or the Shull family on site. | R8: Draft | S8: Address in post text is allowed. Do not add the phone number.
A9: HG-05 | B9: 3 | C9: 46343 | D9: =TEXT(C9,"ddd") -> Tue | E9: Service | F9: Update | G9: Custom frameless shower enclosures | H9: frameless shower doors Harlingen | J9: Ready to replace that old shower curtain? A custom glass enclosure opens up your bathroom, is easy to keep clean and adds value to your home. Harlingen Glass & Mirror designs and installs frameless, semi-frameless and framed shower enclosures, sliding doors and glass partitions, made to fit your space. Book a free bathroom consultation. We will measure, show you the options and give you a clear quote. Financing is available. | K9: =LEN(J9) -> 430 | L9: Book | M9: https://harlingenglass.com/service/bathroom-enclosures/ | N9: hg05-shower-enclosures | O9: =M9&"?utm_source="&Overview!$B$21&"&utm_medium="&Overview!$B$22&"&utm_campaign="&Overview!$B$23&"&utm_content="&N9 -> https://harlingenglass.com/service/bathroom-enclosures/?utm_source=google&utm_medium=organic&utm_campaign=gbp-posts-nov26-jan27&utm_content=hg05-shower-enclosures | Q9: Real before/after photo of a frameless shower enclosure installed by the team. | R9: Draft
A10: HG-06 | B10: 3 | C10: 46345 | D10: =TEXT(C10,"ddd") -> Thu | E10: FAQ | F10: Update | G10: Frameless vs semi-frameless vs framed | H10: shower enclosure types | J10: FAQ: Frameless, semi-frameless or framed: which shower enclosure is right for me? Framed enclosures use metal around the glass and are usually the most budget-friendly. Semi-frameless enclosures use less metal for a cleaner look. Frameless enclosures use thicker glass with minimal hardware for the most open, modern feel. Sliding and hinged doors are available, with clear, frosted or patterned glass depending on the privacy you want. Tap Learn more and our team will help you choose the best fit for your bathroom. | K10: =LEN(J10) -> 520 | L10: Learn more | M10: https://harlingenglass.com/service/bathroom-enclosures/ | N10: hg06-faq-shower-types | O10: =M10&"?utm_source="&Overview!$B$21&"&utm_medium="&Overview!$B$22&"&utm_campaign="&Overview!$B$23&"&utm_content="&N10 -> https://harlingenglass.com/service/bathroom-enclosures/?utm_source=google&utm_medium=organic&utm_campaign=gbp-posts-nov26-jan27&utm_content=hg06-faq-shower-types | Q10: Side-by-side photos of a framed, a semi-frameless and a frameless enclosure. | R10: Draft
A11: HG-07 | B11: 4 | C11: 46350 | D11: =TEXT(C11,"ddd") -> Tue | E11: Promotional | F11: Update | G11: Financing with Synchrony | H11: glass financing Harlingen | J11: Planning a new shower enclosure, window upgrade or mirror project but want to spread the cost? Harlingen Glass & Mirror has partnered with Synchrony Bank to offer financing options for home remodeling and upgrade projects. Ask about financing when you request your quote. Our team will measure, recommend the right glass for your project and give you a clear price before any work begins. Tap Learn more to get started. | K11: =LEN(J11) -> 421 | L11: Learn more | M11: https://harlingenglass.com/contact/ | N11: hg07-financing | O11: =M11&"?utm_source="&Overview!$B$21&"&utm_medium="&Overview!$B$22&"&utm_campaign="&Overview!$B$23&"&utm_content="&N11 -> https://harlingenglass.com/contact/?utm_source=google&utm_medium=organic&utm_campaign=gbp-posts-nov26-jan27&utm_content=hg07-financing | Q11: Clean photo of a finished bathroom or window project with a simple text-free layout. | R11: Draft | S11: Do not state rates or terms. Confirm the financing partnership is still active.
A12: HG-08 | B12: 4 | C12: 46351 | D12: =TEXT(C12,"ddd") -> Wed | E12: Local | F12: Update | G12: Thanksgiving thank you | H12: Harlingen glass company | J12: Happy Thanksgiving from all of us at Harlingen Glass & Mirror. Thank you to the homeowners, realtors, contractors and businesses across Harlingen and the Rio Grande Valley who have trusted our family-owned shop for more than 45 years. Every project you send our way means a lot to our team. Hosting family this week? If a cracked mirror or a sticky glass door needs attention after the holiday, we are here to help. Tap Learn more to reach our team. | K12: =LEN(J12) -> 451 | L12: Learn more | M12: https://harlingenglass.com/contact/ | N12: hg08-thanksgiving | O12: =M12&"?utm_source="&Overview!$B$21&"&utm_medium="&Overview!$B$22&"&utm_campaign="&Overview!$B$23&"&utm_content="&N12 -> https://harlingenglass.com/contact/?utm_source=google&utm_medium=organic&utm_campaign=gbp-posts-nov26-jan27&utm_content=hg08-thanksgiving | Q12: Team photo or a warm photo of the shop. No stock images. | R12: Draft | S12: Confirm holiday office hours and update GBP special hours.
A13: HG-09 | B13: 5 | C13: 46357 | D13: =TEXT(C13,"ddd") -> Tue | E13: Service | F13: Update | G13: 3M Security Window Film for schools | H13: 3M security film Texas schools | J13: Is your campus ready for Texas Education Agency safety requirements? Harlingen Glass & Mirror installs 3M Security Window Film to strengthen school windows and glass doors. The film helps hold broken glass together and slows forced entry, giving staff valuable response time. Work with a 3M authorized team so your film is installed correctly and meets requirements. Tap Book to schedule a free campus walkthrough. | K13: =LEN(J13) -> 416 | L13: Book | M13: https://harlingenglass.com/service/3m-security-film/ | N13: hg09-3m-security-film | O13: =M13&"?utm_source="&Overview!$B$21&"&utm_medium="&Overview!$B$22&"&utm_campaign="&Overview!$B$23&"&utm_content="&N13 -> https://harlingenglass.com/service/3m-security-film/?utm_source=google&utm_medium=organic&utm_campaign=gbp-posts-nov26-jan27&utm_content=hg09-3m-security-film | Q13: Real photo of security film being installed on school or commercial glass. | R13: Draft | S13: Confirm 3M authorization wording with the client.
A14: HG-10 | B14: 5 | C14: 46359 | D14: =TEXT(C14,"ddd") -> Thu | E14: FAQ | F14: Update | G14: Is all security film compliant? | H14: TEA compliant window film | J14: FAQ: Does any security window film meet school safety requirements? Not always. Schools sometimes discover their film does not meet requirements after it has been installed, which can mean paying twice. The film product, how it is attached and who installs it all matter. Harlingen Glass & Mirror installs 3M Security Window Film as a 3M authorized team and can walk your campus to check vulnerable entry points. Tap Learn more to request your free security film assessment. | K14: =LEN(J14) -> 477 | L14: Learn more | M14: https://harlingenglass.com/service/3m-security-film/ | N14: hg10-faq-security-film | O14: =M14&"?utm_source="&Overview!$B$21&"&utm_medium="&Overview!$B$22&"&utm_campaign="&Overview!$B$23&"&utm_content="&N14 -> https://harlingenglass.com/service/3m-security-film/?utm_source=google&utm_medium=organic&utm_campaign=gbp-posts-nov26-jan27&utm_content=hg10-faq-security-film | Q14: Photo of a school entrance with glass doors (own photo or client project). | R14: Draft | S14: Fact-check with the client before publishing.
A15: HG-11 | B15: 6 | C15: 46364 | D15: =TEXT(C15,"ddd") -> Tue | E15: Service | F15: Update | G15: Commercial storefront glass | H15: storefront glass repair Harlingen | J15: A broken storefront window or door is a security risk and the first thing customers notice. Harlingen Glass & Mirror repairs and replaces commercial glass for businesses across the Rio Grande Valley, including storefront glass, entry doors, fire-rated glass, thermal glazing and multi-story projects. With more than 45 years in commercial glazing, our team works to meet safety standards while keeping your property looking professional. Tap Learn more to request a free assessment. | K15: =LEN(J15) -> 484 | L15: Learn more | M15: https://harlingenglass.com/service/commercial-glass/ | N15: hg11-commercial-storefront | O15: =M15&"?utm_source="&Overview!$B$21&"&utm_medium="&Overview!$B$22&"&utm_campaign="&Overview!$B$23&"&utm_content="&N15 -> https://harlingenglass.com/service/commercial-glass/?utm_source=google&utm_medium=organic&utm_campaign=gbp-posts-nov26-jan27&utm_content=hg11-commercial-storefront | Q15: Real photo of a completed storefront installation. | R15: Draft
A16: HG-12 | B16: 6 | C16: 46366 | D16: =TEXT(C16,"ddd") -> Thu | E16: Promotional | F16: Offer | G16: Free security film assessment over winter break | H16: school window film installation | I16: Free Security Film Assessment for Schools | J16: Winter break is one of the best times to upgrade campus glass with less disruption for students and staff. Book a free security film assessment with Harlingen Glass & Mirror. We will walk your campus, check windows and glass doors, and recommend the right 3M Security Window Film for each entry point. Spots for break installations are limited. Tap View offer to schedule your walkthrough. | K16: =LEN(J16) -> 391 | L16: View offer | M16: https://harlingenglass.com/service/3m-security-film/ | N16: hg12-winter-break-assessment | O16: =M16&"?utm_source="&Overview!$B$21&"&utm_medium="&Overview!$B$22&"&utm_campaign="&Overview!$B$23&"&utm_content="&N16 -> https://harlingenglass.com/service/3m-security-film/?utm_source=google&utm_medium=organic&utm_campaign=gbp-posts-nov26-jan27&utm_content=hg12-winter-break-assessment | P16: Offer dates: Dec 10, 2026 to Jan 8, 2027 (confirm). Terms: assessment is free, installation quoted separately. | Q16: Photo of security film install on classroom or office windows. | R16: Draft | S16: Confirm the team has installer availability during winter break.
A17: HG-13 | B17: 7 | C17: 46371 | D17: =TEXT(C17,"ddd") -> Tue | E17: Service | F17: Update | G17: Custom mirrors | H17: custom mirrors Harlingen | J17: A custom mirror can make a bathroom feel bigger, brighten a bedroom or finish off an entryway. Harlingen Glass & Mirror cuts and installs custom mirrors for homes and businesses across the Rio Grande Valley. We help you choose the size, edge and placement, then handle the full installation. We also install glass tabletops, shelves and custom shower doors. Tap Learn more to get a free quote. | K17: =LEN(J17) -> 395 | L17: Learn more | M17: https://harlingenglass.com/service/interior/ | N17: hg13-custom-mirrors | O17: =M17&"?utm_source="&Overview!$B$21&"&utm_medium="&Overview!$B$22&"&utm_campaign="&Overview!$B$23&"&utm_content="&N17 -> https://harlingenglass.com/service/interior/?utm_source=google&utm_medium=organic&utm_campaign=gbp-posts-nov26-jan27&utm_content=hg13-custom-mirrors | Q17: Real photo of a large custom bathroom mirror installed by the team. | R17: Draft
A18: HG-14 | B18: 7 | C18: 46373 | D18: =TEXT(C18,"ddd") -> Thu | E18: Local | F18: Update | G18: Holiday glass check | H18: glass repair Rio Grande Valley | J18: Getting your home ready for holiday guests in the Valley? Take a quick walk around: check for chipped tabletops, cracked mirrors, sliding glass doors that stick, and windows that do not seal properly. Small issues are usually faster and less expensive to fix before they spread. Harlingen Glass & Mirror has helped Harlingen families get their homes ready for the holidays for more than 45 years. Tap Learn more to book a repair. | K18: =LEN(J18) -> 431 | L18: Learn more | M18: https://harlingenglass.com/service/residential/ | N18: hg14-holiday-glass-check | O18: =M18&"?utm_source="&Overview!$B$21&"&utm_medium="&Overview!$B$22&"&utm_campaign="&Overview!$B$23&"&utm_content="&N18 -> https://harlingenglass.com/service/residential/?utm_source=google&utm_medium=organic&utm_campaign=gbp-posts-nov26-jan27&utm_content=hg14-holiday-glass-check | Q18: Photo of a clean living room with a sliding glass door or a repaired tabletop. | R18: Draft
A19: HG-15 | B19: 8 | C19: 46378 | D19: =TEXT(C19,"ddd") -> Tue | E19: FAQ | F19: Update | G19: Warranty | H19: glass installation warranty | J19: FAQ: Does Harlingen Glass & Mirror offer a warranty? Yes. Many of the products we install carry a manufacturer warranty of up to 3 years, and we provide a 1-year installation warranty on specific products. Our team will explain the coverage that applies to your project before we start. We hold ourselves to a high standard, from sales and service to installation and warranty. Tap Learn more to see why the Valley has trusted us since 1978. | K19: =LEN(J19) -> 443 | L19: Learn more | M19: https://harlingenglass.com/company/ | N19: hg15-faq-warranty | O19: =M19&"?utm_source="&Overview!$B$21&"&utm_medium="&Overview!$B$22&"&utm_campaign="&Overview!$B$23&"&utm_content="&N19 -> https://harlingenglass.com/company/?utm_source=google&utm_medium=organic&utm_campaign=gbp-posts-nov26-jan27&utm_content=hg15-faq-warranty | Q19: Photo of an installer finishing a project, or a completed install close-up. | R19: Draft | S19: Confirm current warranty terms with the client.
A20: HG-16 | B20: 8 | C20: 46385 | D20: =TEXT(C20,"ddd") -> Tue | E20: Local | F20: Update | G20: Year-end thank you | H20: Harlingen Glass and Mirror | J20: As the year comes to a close, thank you to everyone in Harlingen and across the Rio Grande Valley who chose a family-owned local shop for their glass projects. From shower enclosures and window replacements to storefronts and school security film, it has been a busy year for our team. If we worked on your home or business this year, we would love to hear how it went. Your feedback helps your neighbors find a glass company they can trust. Tap Learn more to see our work. | K20: =LEN(J20) -> 475 | L20: Learn more | M20: https://harlingenglass.com/company/ | N20: hg16-year-end-thanks | O20: =M20&"?utm_source="&Overview!$B$21&"&utm_medium="&Overview!$B$22&"&utm_campaign="&Overview!$B$23&"&utm_content="&N20 -> https://harlingenglass.com/company/?utm_source=google&utm_medium=organic&utm_campaign=gbp-posts-nov26-jan27&utm_content=hg16-year-end-thanks | Q20: Collage of 3 to 4 real projects from the year. | R20: Draft | S20: Review request is allowed. Do not offer anything in return for reviews.
A21: HG-17 | B21: 9 | C21: 46392 | D21: =TEXT(C21,"ddd") -> Tue | E21: Service | F21: Update | G21: Energy-efficient Low-E windows | H21: energy efficient windows Harlingen | J21: New year, lower energy bills. Old or poorly sealed windows let cool air out in summer and warm air out in winter, which makes your AC work harder. Harlingen Glass & Mirror installs energy-efficient replacement windows, including Low-E glass that helps reduce heat and UV coming into your home without blocking natural light. Book a free window inspection and we will show you where you can save. Tap Learn more to get started. | K21: =LEN(J21) -> 428 | L21: Learn more | M21: https://harlingenglass.com/service/residential-window-replacement/ | N21: hg17-low-e-windows | O21: =M21&"?utm_source="&Overview!$B$21&"&utm_medium="&Overview!$B$22&"&utm_campaign="&Overview!$B$23&"&utm_content="&N21 -> https://harlingenglass.com/service/residential-window-replacement/?utm_source=google&utm_medium=organic&utm_campaign=gbp-posts-nov26-jan27&utm_content=hg17-low-e-windows | Q21: Real photo of new Low-E windows on a Valley home. | R21: Draft
A22: HG-18 | B22: 9 | C22: 46394 | D22: =TEXT(C22,"ddd") -> Thu | E22: Promotional | F22: Offer | G22: Window offer (New Year) | H22: window replacement deal | I22: New Year Window Offer: 4th Window Free | J22: Start the year with a home upgrade. Buy 3 windows and get the 4th window free from Harlingen Glass & Mirror. Energy-efficient windows can help lower your utility bills, make rooms more comfortable and boost curb appeal. Every project includes a free window inspection and a clear quote. Financing is available. Tap View offer to schedule your free inspection. | K22: =LEN(J22) -> 361 | L22: View offer | M22: https://harlingenglass.com/service/residential-window-replacement/ | N22: hg18-new-year-window-offer | O22: =M22&"?utm_source="&Overview!$B$21&"&utm_medium="&Overview!$B$22&"&utm_campaign="&Overview!$B$23&"&utm_content="&N22 -> https://harlingenglass.com/service/residential-window-replacement/?utm_source=google&utm_medium=organic&utm_campaign=gbp-posts-nov26-jan27&utm_content=hg18-new-year-window-offer | P22: Offer dates: Jan 7 to Jan 31, 2027 (confirm the offer is extended). Terms: same as HG-02. | Q22: Exterior photo of a home with new windows. | R22: Draft | S22: Only publish if the client extends the offer into January.
A23: HG-19 | B23: 10 | C23: 46399 | D23: =TEXT(C23,"ddd") -> Tue | E23: FAQ | F23: Update | G23: Repair or replace a cracked window | H23: cracked window repair | J23: FAQ: Should I repair a small crack in my window or replace the glass? A small crack can spread with temperature changes, wind and everyday use, and it can weaken the whole pane. In most cases, replacing the damaged glass is the safer long-term fix, and it is often quicker than people expect. Our team will look at the damage and tell you honestly what makes sense. Tap Learn more to read our guide and book a visit. | K23: =LEN(J23) -> 418 | L23: Learn more | M23: https://harlingenglass.com/blog/dont-let-a-small-crack-turn-into-a-big-problem/ | N23: hg19-faq-cracked-window | O23: =M23&"?utm_source="&Overview!$B$21&"&utm_medium="&Overview!$B$22&"&utm_campaign="&Overview!$B$23&"&utm_content="&N23 -> https://harlingenglass.com/blog/dont-let-a-small-crack-turn-into-a-big-problem/?utm_source=google&utm_medium=organic&utm_campaign=gbp-posts-nov26-jan27&utm_content=hg19-faq-cracked-window | Q23: Close-up of a cracked window pane (own photo). | R23: Draft
A24: HG-20 | B24: 10 | C24: 46401 | D24: =TEXT(C24,"ddd") -> Thu | E24: Service | F24: Update | G24: Fire-rated and bullet-resistant glass | H24: bullet resistant glass Texas | J24: Some businesses need more than standard glass. Banks, clinics, offices and government buildings often require fire-rated or bullet-resistant glass to meet safety standards. Harlingen Glass & Mirror supplies and installs fire-rated glass, bullet-resistant glass barriers, thermal glazing and glass railing systems for commercial projects across South Texas. Tap Learn more to talk to our commercial team about your project. | K24: =LEN(J24) -> 424 | L24: Learn more | M24: https://harlingenglass.com/service/commercial-glass/ | N24: hg20-fire-bullet-resistant | O24: =M24&"?utm_source="&Overview!$B$21&"&utm_medium="&Overview!$B$22&"&utm_campaign="&Overview!$B$23&"&utm_content="&N24 -> https://harlingenglass.com/service/commercial-glass/?utm_source=google&utm_medium=organic&utm_campaign=gbp-posts-nov26-jan27&utm_content=hg20-fire-bullet-resistant | Q24: Real photo of a commercial reception window or glass railing project. | R24: Draft | S24: Confirm the bullet-resistant ratings the team installs before adding specifics.
A25: HG-21 | B25: 11 | C25: 46406 | D25: =TEXT(C25,"ddd") -> Tue | E25: Local | F25: Update | G25: Cold fronts in the Valley | H25: window seal repair Harlingen | J25: Cold fronts in the Rio Grande Valley are a good reminder to check your windows and doors. If you feel a draft, see gaps around the frame or notice fog between the panes, your windows may not be sealing properly. Fixing them now keeps your home comfortable and helps before the summer heat returns. Harlingen Glass & Mirror serves homeowners across Harlingen and the Valley. Tap Learn more to book a free assessment. | K25: =LEN(J25) -> 417 | L25: Learn more | M25: https://harlingenglass.com/service/residential/ | N25: hg21-cold-front-check | O25: =M25&"?utm_source="&Overview!$B$21&"&utm_medium="&Overview!$B$22&"&utm_campaign="&Overview!$B$23&"&utm_content="&N25 -> https://harlingenglass.com/service/residential/?utm_source=google&utm_medium=organic&utm_campaign=gbp-posts-nov26-jan27&utm_content=hg21-cold-front-check | Q25: Photo of a technician checking a window frame. | R25: Draft
A26: HG-22 | B26: 11 | C26: 46408 | D26: =TEXT(C26,"ddd") -> Thu | E26: Service | F26: Update | G26: Glass tabletops and shelves | H26: glass tabletop Harlingen | J26: Protect your wood furniture or update a room with a custom glass tabletop or glass shelves. Harlingen Glass & Mirror cuts glass to your exact size and shape, with clean, polished edges for homes, offices and restaurants. We also replace broken tabletops and shelves. Tap Learn more to get a free quote from your local one-stop custom glass shop. | K26: =LEN(J26) -> 347 | L26: Learn more | M26: https://harlingenglass.com/service/interior/ | N26: hg22-glass-tabletops | O26: =M26&"?utm_source="&Overview!$B$21&"&utm_medium="&Overview!$B$22&"&utm_campaign="&Overview!$B$23&"&utm_content="&N26 -> https://harlingenglass.com/service/interior/?utm_source=google&utm_medium=organic&utm_campaign=gbp-posts-nov26-jan27&utm_content=hg22-glass-tabletops | Q26: Real photo of a custom glass tabletop on a dining table. | R26: Draft

Sheet Weekly Batches
A1: Weekly batch plan
A2: Each batch = 2 posts. Content goes to the client 2 working days before the batch week, then is scheduled on the Monday. Batch 8 covers the two holiday weeks (Dec 22 and Dec 29).
A4: Batch | B4: Week Of (Mon) | C4: Posts in Batch | D4: Posts | E4: Service | F4: FAQ | G4: Local | H4: Promotional | I4: Content Due to Client | J4: Batch Status
A5: 1 | B5: 46328 | C5: HG-01, HG-02 | D5: =COUNTIF('Content Calendar'!$B$5:$B$26,A5) -> 2 | E5: =COUNTIFS('Content Calendar'!$B$5:$B$26,A5,'Content Calendar'!$E$5:$E$26,"Service") -> 1 | F5: =COUNTIFS('Content Calendar'!$B$5:$B$26,A5,'Content Calendar'!$E$5:$E$26,"FAQ") -> 0 | G5: =COUNTIFS('Content Calendar'!$B$5:$B$26,A5,'Content Calendar'!$E$5:$E$26,"Local") -> 0 | H5: =COUNTIFS('Content Calendar'!$B$5:$B$26,A5,'Content Calendar'!$E$5:$E$26,"Promotional") -> 1 | I5: =WORKDAY(B5,-2) -> 46324 | J5: Not started
A6: 2 | B6: 46335 | C6: HG-03, HG-04 | D6: =COUNTIF('Content Calendar'!$B$5:$B$26,A6) -> 2 | E6: =COUNTIFS('Content Calendar'!$B$5:$B$26,A6,'Content Calendar'!$E$5:$E$26,"Service") -> 0 | F6: =COUNTIFS('Content Calendar'!$B$5:$B$26,A6,'Content Calendar'!$E$5:$E$26,"FAQ") -> 1 | G6: =COUNTIFS('Content Calendar'!$B$5:$B$26,A6,'Content Calendar'!$E$5:$E$26,"Local") -> 1 | H6: =COUNTIFS('Content Calendar'!$B$5:$B$26,A6,'Content Calendar'!$E$5:$E$26,"Promotional") -> 0 | I6: =WORKDAY(B6,-2) -> 46331 | J6: Not started
A7: 3 | B7: 46342 | C7: HG-05, HG-06 | D7: =COUNTIF('Content Calendar'!$B$5:$B$26,A7) -> 2 | E7: =COUNTIFS('Content Calendar'!$B$5:$B$26,A7,'Content Calendar'!$E$5:$E$26,"Service") -> 1 | F7: =COUNTIFS('Content Calendar'!$B$5:$B$26,A7,'Content Calendar'!$E$5:$E$26,"FAQ") -> 1 | G7: =COUNTIFS('Content Calendar'!$B$5:$B$26,A7,'Content Calendar'!$E$5:$E$26,"Local") -> 0 | H7: =COUNTIFS('Content Calendar'!$B$5:$B$26,A7,'Content Calendar'!$E$5:$E$26,"Promotional") -> 0 | I7: =WORKDAY(B7,-2) -> 46338 | J7: Not started
A8: 4 | B8: 46349 | C8: HG-07, HG-08 | D8: =COUNTIF('Content Calendar'!$B$5:$B$26,A8) -> 2 | E8: =COUNTIFS('Content Calendar'!$B$5:$B$26,A8,'Content Calendar'!$E$5:$E$26,"Service") -> 0 | F8: =COUNTIFS('Content Calendar'!$B$5:$B$26,A8,'Content Calendar'!$E$5:$E$26,"FAQ") -> 0 | G8: =COUNTIFS('Content Calendar'!$B$5:$B$26,A8,'Content Calendar'!$E$5:$E$26,"Local") -> 1 | H8: =COUNTIFS('Content Calendar'!$B$5:$B$26,A8,'Content Calendar'!$E$5:$E$26,"Promotional") -> 1 | I8: =WORKDAY(B8,-2) -> 46345 | J8: Not started
A9: 5 | B9: 46356 | C9: HG-09, HG-10 | D9: =COUNTIF('Content Calendar'!$B$5:$B$26,A9) -> 2 | E9: =COUNTIFS('Content Calendar'!$B$5:$B$26,A9,'Content Calendar'!$E$5:$E$26,"Service") -> 1 | F9: =COUNTIFS('Content Calendar'!$B$5:$B$26,A9,'Content Calendar'!$E$5:$E$26,"FAQ") -> 1 | G9: =COUNTIFS('Content Calendar'!$B$5:$B$26,A9,'Content Calendar'!$E$5:$E$26,"Local") -> 0 | H9: =COUNTIFS('Content Calendar'!$B$5:$B$26,A9,'Content Calendar'!$E$5:$E$26,"Promotional") -> 0 | I9: =WORKDAY(B9,-2) -> 46352 | J9: Not started
A10: 6 | B10: 46363 | C10: HG-11, HG-12 | D10: =COUNTIF('Content Calendar'!$B$5:$B$26,A10) -> 2 | E10: =COUNTIFS('Content Calendar'!$B$5:$B$26,A10,'Content Calendar'!$E$5:$E$26,"Service") -> 1 | F10: =COUNTIFS('Content Calendar'!$B$5:$B$26,A10,'Content Calendar'!$E$5:$E$26,"FAQ") -> 0 | G10: =COUNTIFS('Content Calendar'!$B$5:$B$26,A10,'Content Calendar'!$E$5:$E$26,"Local") -> 0 | H10: =COUNTIFS('Content Calendar'!$B$5:$B$26,A10,'Content Calendar'!$E$5:$E$26,"Promotional") -> 1 | I10: =WORKDAY(B10,-2) -> 46359 | J10: Not started
A11: 7 | B11: 46370 | C11: HG-13, HG-14 | D11: =COUNTIF('Content Calendar'!$B$5:$B$26,A11) -> 2 | E11: =COUNTIFS('Content Calendar'!$B$5:$B$26,A11,'Content Calendar'!$E$5:$E$26,"Service") -> 1 | F11: =COUNTIFS('Content Calendar'!$B$5:$B$26,A11,'Content Calendar'!$E$5:$E$26,"FAQ") -> 0 | G11: =COUNTIFS('Content Calendar'!$B$5:$B$26,A11,'Content Calendar'!$E$5:$E$26,"Local") -> 1 | H11: =COUNTIFS('Content Calendar'!$B$5:$B$26,A11,'Content Calendar'!$E$5:$E$26,"Promotional") -> 0 | I11: =WORKDAY(B11,-2) -> 46366 | J11: Not started
A12: 8 | B12: 46377 | C12: HG-15, HG-16 | D12: =COUNTIF('Content Calendar'!$B$5:$B$26,A12) -> 2 | E12: =COUNTIFS('Content Calendar'!$B$5:$B$26,A12,'Content Calendar'!$E$5:$E$26,"Service") -> 0 | F12: =COUNTIFS('Content Calendar'!$B$5:$B$26,A12,'Content Calendar'!$E$5:$E$26,"FAQ") -> 1 | G12: =COUNTIFS('Content Calendar'!$B$5:$B$26,A12,'Content Calendar'!$E$5:$E$26,"Local") -> 1 | H12: =COUNTIFS('Content Calendar'!$B$5:$B$26,A12,'Content Calendar'!$E$5:$E$26,"Promotional") -> 0 | I12: =WORKDAY(B12,-2) -> 46373 | J12: Not started
A13: 9 | B13: 46391 | C13: HG-17, HG-18 | D13: =COUNTIF('Content Calendar'!$B$5:$B$26,A13) -> 2 | E13: =COUNTIFS('Content Calendar'!$B$5:$B$26,A13,'Content Calendar'!$E$5:$E$26,"Service") -> 1 | F13: =COUNTIFS('Content Calendar'!$B$5:$B$26,A13,'Content Calendar'!$E$5:$E$26,"FAQ") -> 0 | G13: =COUNTIFS('Content Calendar'!$B$5:$B$26,A13,'Content Calendar'!$E$5:$E$26,"Local") -> 0 | H13: =COUNTIFS('Content Calendar'!$B$5:$B$26,A13,'Content Calendar'!$E$5:$E$26,"Promotional") -> 1 | I13: =WORKDAY(B13,-2) -> 46387 | J13: Not started
A14: 10 | B14: 46398 | C14: HG-19, HG-20 | D14: =COUNTIF('Content Calendar'!$B$5:$B$26,A14) -> 2 | E14: =COUNTIFS('Content Calendar'!$B$5:$B$26,A14,'Content Calendar'!$E$5:$E$26,"Service") -> 1 | F14: =COUNTIFS('Content Calendar'!$B$5:$B$26,A14,'Content Calendar'!$E$5:$E$26,"FAQ") -> 1 | G14: =COUNTIFS('Content Calendar'!$B$5:$B$26,A14,'Content Calendar'!$E$5:$E$26,"Local") -> 0 | H14: =COUNTIFS('Content Calendar'!$B$5:$B$26,A14,'Content Calendar'!$E$5:$E$26,"Promotional") -> 0 | I14: =WORKDAY(B14,-2) -> 46394 | J14: Not started
A15: 11 | B15: 46405 | C15: HG-21, HG-22 | D15: =COUNTIF('Content Calendar'!$B$5:$B$26,A15) -> 2 | E15: =COUNTIFS('Content Calendar'!$B$5:$B$26,A15,'Content Calendar'!$E$5:$E$26,"Service") -> 1 | F15: =COUNTIFS('Content Calendar'!$B$5:$B$26,A15,'Content Calendar'!$E$5:$E$26,"FAQ") -> 0 | G15: =COUNTIFS('Content Calendar'!$B$5:$B$26,A15,'Content Calendar'!$E$5:$E$26,"Local") -> 1 | H15: =COUNTIFS('Content Calendar'!$B$5:$B$26,A15,'Content Calendar'!$E$5:$E$26,"Promotional") -> 0 | I15: =WORKDAY(B15,-2) -> 46401 | J15: Not started
A16: Total | D16: =SUM(D5:D15) -> 22 | E16: =SUM(E5:E15) -> 8 | F16: =SUM(F5:F15) -> 5 | G16: =SUM(G5:G15) -> 5 | H16: =SUM(H5:H15) -> 4

Sheet Citations
A1: Citation work
A2: Use the NAP below exactly, character for character, on every listing.
B4: NAP field | C4: Use exactly
B5: Business name | C5: Harlingen Glass & Mirror (confirm this matches the GBP name exactly)
B6: Street address | C6: 1905 E. Harrison Ave.
B7: City, State ZIP | C7: Harlingen, TX 78550
B8: Primary phone | C8: (956) 428-6066
B9: Website | C9: https://harlingenglass.com/
B10: Email | C10: mainoffice@harlingenglass.com
B11: Hours | C11: Mon to Fri 8:00 AM to 5:00 PM; Sat and Sun closed
B12: Primary category (suggested) | C12: Glass repair service (confirm against current GBP category)
B13: Short description (for directories) | C13: Family-owned glass company in Harlingen, TX since 1978. Residential and commercial glass repair, window replacement, custom shower enclosures, mirrors, storefront glass and 3M security window film across the Rio Grande Valley.
B15: Citation list
A16: # | B16: Platform | C16: Type | D16: Priority | E16: Where to claim / submit | F16: Current Status (Oct 26) | G16: Issue / Note | H16: Action | I16: Work Status | J16: Date Done | K16: Live Listing URL
A17: 1 | B17: Google Business Profile | C17: Core | D17: High | E17: https://business.google.com | F17: Found (4.8, 52 reviews per website widget) | G17: Name must match the website footer | H17: Confirm name, categories, hours and services; add products/services; upload real photos | I17: Not started
A18: 2 | B18: Bing Places for Business | C18: Core | D18: High | E18: https://www.bingplaces.com | F18: To verify | H18: Import from GBP and verify | I18: Not started
A19: 3 | B19: Apple Business Connect | C19: Core | D19: High | E19: https://businessconnect.apple.com | F19: To verify | H19: Claim and verify for Apple Maps | I19: Not started
A20: 4 | B20: Facebook Page | C20: Core / Social | D20: High | E20: https://www.facebook.com/HGMTX | F20: Found | G20: Check that the About section NAP matches | H20: Update NAP, hours and website link | I20: Not started
A21: 5 | B21: Yelp | C21: Core | D21: High | E21: https://biz.yelp.com | F21: To verify | H21: Search 'Harlingen Glass Harlingen TX'; claim or create | I21: Not started
A22: 6 | B22: Better Business Bureau | C22: Core | D22: High | E22: https://www.bbb.org/get-listed | F22: To verify | H22: Claim or create a free listing | I22: Not started
A23: 7 | B23: Yellow Pages | C23: Directory | D23: Medium | E23: https://adsolutions.yp.com/free-listing | F23: To verify | H23: Claim free listing | I23: Not started
A24: 8 | B24: Nextdoor Business | C24: Local | D24: Medium | E24: https://business.nextdoor.com | F24: To verify | H24: Claim business page; useful for homeowner referrals | I24: Not started
A25: 9 | B25: Angi | C25: Home services | D25: Medium | E25: https://www.angi.com/pro | F25: To verify | H25: Create a pro profile for window and glass repair | I25: Not started
A26: 10 | B26: HomeAdvisor | C26: Home services | D26: Medium | E26: https://pro.homeadvisor.com | F26: To verify | H26: Optional paid leads; free profile at minimum | I26: Not started
A27: 11 | B27: Thumbtack | C27: Home services | D27: Medium | E27: https://www.thumbtack.com/pro | F27: To verify | H27: Create profile for shower door and window jobs | I27: Not started
A28: 12 | B28: Houzz | C28: Home services | D28: Medium | E28: https://www.houzz.com/pro | F28: To verify | H28: Good fit for shower enclosure and mirror portfolio | I28: Not started
A29: 13 | B29: Porch | C29: Home services | D29: Low | E29: https://pro.porch.com | F29: To verify | H29: Claim if a listing exists | I29: Not started
A30: 14 | B30: MapQuest | C30: Maps | D30: Medium | E30: https://www.mapquest.com | F30: To verify | H30: Fed by Yext/aggregators; check NAP | I30: Not started
A31: 15 | B31: Foursquare | C31: Data aggregator | D31: High | E31: https://foursquare.com/venue/claim | F31: To verify | G31: Feeds many apps and maps | H31: Claim and correct NAP | I31: Not started
A32: 16 | B32: Data Axle (Infogroup) | C32: Data aggregator | D32: High | E32: https://www.data-axle.com/our-data/business-data/business-listing/ | F32: To verify | G32: Feeds many directories | H32: Submit NAP | I32: Not started
A33: 17 | B33: Neustar Localeze | C33: Data aggregator | D33: High | E33: https://www.neustarlocaleze.biz | F33: To verify | G33: Feeds many directories | H33: Submit NAP | I33: Not started
A34: 18 | B34: Manta | C34: Directory | D34: Low | E34: https://www.manta.com | F34: To verify | H34: Claim free listing | I34: Not started
A35: 19 | B35: Hotfrog | C35: Directory | D35: Low | E35: https://www.hotfrog.com | F35: To verify | H35: Create free listing | I35: Not started
A36: 20 | B36: Brownbook | C36: Directory | D36: Low | E36: https://www.brownbook.net | F36: To verify | H36: Create free listing | I36: Not started
A37: 21 | B37: EZlocal | C37: Directory | D37: Low | E37: https://www.ezlocal.com | F37: To verify | H37: Create free listing | I37: Not started
A38: 22 | B38: Cylex | C38: Directory | D38: Low | E38: https://www.cylex.us.com | F38: To verify | H38: Create free listing | I38: Not started
A39: 23 | B39: MerchantCircle | C39: Directory | D39: Low | E39: https://www.merchantcircle.com | F39: To verify | H39: Create free listing | I39: Not started
A40: 24 | B40: Chamberofcommerce.com | C40: Directory | D40: Low | E40: https://www.chamberofcommerce.com | F40: To verify | H40: Create free listing | I40: Not started
A41: 25 | B41: Harlingen Area Chamber of Commerce | C41: Local | D41: Medium | E41: https://www.harlingen.com | F41: To verify | G41: Strong local relevance | H41: Check membership; ask for directory listing with website link | I41: Not started
A42: 26 | B42: YouTube channel | C42: Social | D42: Low | E42: Linked from website header | F42: Found | H42: Add NAP and website to the About section | I42: Not started
A43: 27 | B43: National Glass Association (directory) | C43: Industry | D43: Medium | E43: https://www.glass.org | F43: To verify | G43: Industry relevance | H43: Check membership and directory listing | I43: Not started
A44: 28 | B44: 3M Window Film dealer locator | C44: Industry / Brand | D44: High | E44: https://www.3m.com/3M/en_US/window-film-us/where-to-buy/ | F44: To verify | G44: Supports the 3M authorized claim | H44: Confirm the company appears in the 3M locator with the correct NAP | I44: Not started
A45: 29 | B45: Synchrony (CareCredit / Home) merchant locator | C45: Industry / Brand | D45: Low | E45: https://www.synchrony.com | F45: To verify | G45: Financing partner | H45: Check if a merchant locator listing exists and has correct NAP | I45: Not started
A46: 30 | B46: Alignable | C46: Local | D46: Low | E46: https://www.alignable.com | F46: To verify | H46: Create profile; network with RGV businesses | I46: Not started
B48: Summary
B49: Citations listed | C49: =COUNTA(B17:B46) -> 30
B50: High priority | C50: =COUNTIF(D17:D46,"High") -> 10
B51: Live | C51: =COUNTIF(I17:I46,"Live") -> 0
B52: Needs fix | C52: =COUNTIF(I17:I46,"Needs fix") -> 0
B53: Not started | C53: =COUNTIF(I17:I46,"Not started") -> 30

Sheet QA Cross-Check
A1: QA cross-check (automatic)
A2: Formulas re-check every post when copy or links change. Every row should read Pass before scheduling.
A4: Post ID | B4: Max 1,500 chars | C4: No phone number in text | D4: No email in text | E4: No link in text | F4: CTA button set | G4: UTM on CTA link | H4: Link on business website | I4: Offer title max 58 chars | J4: Category set | K4: Overall
A5: ='Content Calendar'!A5 -> HG-01 | B5: =IF(LEN('Content Calendar'!J5)<=1500,"Pass","Fail") -> Pass | C5: =IF(SUMPRODUCT(--ISNUMBER(SEARCH({"956","428-6066","428.6066","4286066"},'Content Calendar'!J5)))=0,"Pass","Fail") -> Pass | D5: =IF(ISNUMBER(SEARCH("@",'Content Calendar'!J5)),"Fail","Pass") -> Pass | E5: =IF(OR(ISNUMBER(SEARCH("http",'Content Calendar'!J5)),ISNUMBER(SEARCH("www.",'Content Calendar'!J5)),ISNUMBER(SEARCH(".com",'Content Calendar'!J5))),"Fail","Pass") -> Pass | F5: =IF(LEN('Content Calendar'!L5)>0,"Pass","Fail") -> Pass | G5: =IF(AND(ISNUMBER(SEARCH("utm_source=google",'Content Calendar'!O5)),ISNUMBER(SEARCH("utm_content=",'Content Calendar'!O5))),"Pass","Fail") -> Pass | H5: =IF(ISNUMBER(SEARCH(Overview!$B$24,'Content Calendar'!M5)),"Pass","Fail") -> Pass | I5: =IF('Content Calendar'!F5="Offer",IF(AND(LEN('Content Calendar'!I5)>0,LEN('Content Calendar'!I5)<=58),"Pass","Fail"),"N/A") -> N/A | J5: =IF(OR('Content Calendar'!E5="Service",'Content Calendar'!E5="FAQ",'Content Calendar'!E5="Local",'Content Calendar'!E5="Promotional"),"Pass","Fail") -> Pass | K5: =IF(COUNTIF(B5:J5,"Fail")=0,"Pass","Fail") -> Pass
A6: ='Content Calendar'!A6 -> HG-02 | B6: =IF(LEN('Content Calendar'!J6)<=1500,"Pass","Fail") -> Pass | C6: =IF(SUMPRODUCT(--ISNUMBER(SEARCH({"956","428-6066","428.6066","4286066"},'Content Calendar'!J6)))=0,"Pass","Fail") -> Pass | D6: =IF(ISNUMBER(SEARCH("@",'Content Calendar'!J6)),"Fail","Pass") -> Pass | E6: =IF(OR(ISNUMBER(SEARCH("http",'Content Calendar'!J6)),ISNUMBER(SEARCH("www.",'Content Calendar'!J6)),ISNUMBER(SEARCH(".com",'Content Calendar'!J6))),"Fail","Pass") -> Pass | F6: =IF(LEN('Content Calendar'!L6)>0,"Pass","Fail") -> Pass | G6: =IF(AND(ISNUMBER(SEARCH("utm_source=google",'Content Calendar'!O6)),ISNUMBER(SEARCH("utm_content=",'Content Calendar'!O6))),"Pass","Fail") -> Pass | H6: =IF(ISNUMBER(SEARCH(Overview!$B$24,'Content Calendar'!M6)),"Pass","Fail") -> Pass | I6: =IF('Content Calendar'!F6="Offer",IF(AND(LEN('Content Calendar'!I6)>0,LEN('Content Calendar'!I6)<=58),"Pass","Fail"),"N/A") -> Pass | J6: =IF(OR('Content Calendar'!E6="Service",'Content Calendar'!E6="FAQ",'Content Calendar'!E6="Local",'Content Calendar'!E6="Promotional"),"Pass","Fail") -> Pass | K6: =IF(COUNTIF(B6:J6,"Fail")=0,"Pass","Fail") -> Pass
A7: ='Content Calendar'!A7 -> HG-03 | B7: =IF(LEN('Content Calendar'!J7)<=1500,"Pass","Fail") -> Pass | C7: =IF(SUMPRODUCT(--ISNUMBER(SEARCH({"956","428-6066","428.6066","4286066"},'Content Calendar'!J7)))=0,"Pass","Fail") -> Pass | D7: =IF(ISNUMBER(SEARCH("@",'Content Calendar'!J7)),"Fail","Pass") -> Pass | E7: =IF(OR(ISNUMBER(SEARCH("http",'Content Calendar'!J7)),ISNUMBER(SEARCH("www.",'Content Calendar'!J7)),ISNUMBER(SEARCH(".com",'Content Calendar'!J7))),"Fail","Pass") -> Pass | F7: =IF(LEN('Content Calendar'!L7)>0,"Pass","Fail") -> Pass | G7: =IF(AND(ISNUMBER(SEARCH("utm_source=google",'Content Calendar'!O7)),ISNUMBER(SEARCH("utm_content=",'Content Calendar'!O7))),"Pass","Fail") -> Pass | H7: =IF(ISNUMBER(SEARCH(Overview!$B$24,'Content Calendar'!M7)),"Pass","Fail") -> Pass | I7: =IF('Content Calendar'!F7="Offer",IF(AND(LEN('Content Calendar'!I7)>0,LEN('Content Calendar'!I7)<=58),"Pass","Fail"),"N/A") -> N/A | J7: =IF(OR('Content Calendar'!E7="Service",'Content Calendar'!E7="FAQ",'Content Calendar'!E7="Local",'Content Calendar'!E7="Promotional"),"Pass","Fail") -> Pass | K7: =IF(COUNTIF(B7:J7,"Fail")=0,"Pass","Fail") -> Pass
A8: ='Content Calendar'!A8 -> HG-04 | B8: =IF(LEN('Content Calendar'!J8)<=1500,"Pass","Fail") -> Pass | C8: =IF(SUMPRODUCT(--ISNUMBER(SEARCH({"956","428-6066","428.6066","4286066"},'Content Calendar'!J8)))=0,"Pass","Fail") -> Pass | D8: =IF(ISNUMBER(SEARCH("@",'Content Calendar'!J8)),"Fail","Pass") -> Pass | E8: =IF(OR(ISNUMBER(SEARCH("http",'Content Calendar'!J8)),ISNUMBER(SEARCH("www.",'Content Calendar'!J8)),ISNUMBER(SEARCH(".com",'Content Calendar'!J8))),"Fail","Pass") -> Pass | F8: =IF(LEN('Content Calendar'!L8)>0,"Pass","Fail") -> Pass | G8: =IF(AND(ISNUMBER(SEARCH("utm_source=google",'Content Calendar'!O8)),ISNUMBER(SEARCH("utm_content=",'Content Calendar'!O8))),"Pass","Fail") -> Pass | H8: =IF(ISNUMBER(SEARCH(Overview!$B$24,'Content Calendar'!M8)),"Pass","Fail") -> Pass | I8: =IF('Content Calendar'!F8="Offer",IF(AND(LEN('Content Calendar'!I8)>0,LEN('Content Calendar'!I8)<=58),"Pass","Fail"),"N/A") -> N/A | J8: =IF(OR('Content Calendar'!E8="Service",'Content Calendar'!E8="FAQ",'Content Calendar'!E8="Local",'Content Calendar'!E8="Promotional"),"Pass","Fail") -> Pass | K8: =IF(COUNTIF(B8:J8,"Fail")=0,"Pass","Fail") -> Pass
A9: ='Content Calendar'!A9 -> HG-05 | B9: =IF(LEN('Content Calendar'!J9)<=1500,"Pass","Fail") -> Pass | C9: =IF(SUMPRODUCT(--ISNUMBER(SEARCH({"956","428-6066","428.6066","4286066"},'Content Calendar'!J9)))=0,"Pass","Fail") -> Pass | D9: =IF(ISNUMBER(SEARCH("@",'Content Calendar'!J9)),"Fail","Pass") -> Pass | E9: =IF(OR(ISNUMBER(SEARCH("http",'Content Calendar'!J9)),ISNUMBER(SEARCH("www.",'Content Calendar'!J9)),ISNUMBER(SEARCH(".com",'Content Calendar'!J9))),"Fail","Pass") -> Pass | F9: =IF(LEN('Content Calendar'!L9)>0,"Pass","Fail") -> Pass | G9: =IF(AND(ISNUMBER(SEARCH("utm_source=google",'Content Calendar'!O9)),ISNUMBER(SEARCH("utm_content=",'Content Calendar'!O9))),"Pass","Fail") -> Pass | H9: =IF(ISNUMBER(SEARCH(Overview!$B$24,'Content Calendar'!M9)),"Pass","Fail") -> Pass | I9: =IF('Content Calendar'!F9="Offer",IF(AND(LEN('Content Calendar'!I9)>0,LEN('Content Calendar'!I9)<=58),"Pass","Fail"),"N/A") -> N/A | J9: =IF(OR('Content Calendar'!E9="Service",'Content Calendar'!E9="FAQ",'Content Calendar'!E9="Local",'Content Calendar'!E9="Promotional"),"Pass","Fail") -> Pass | K9: =IF(COUNTIF(B9:J9,"Fail")=0,"Pass","Fail") -> Pass
A10: ='Content Calendar'!A10 -> HG-06 | B10: =IF(LEN('Content Calendar'!J10)<=1500,"Pass","Fail") -> Pass | C10: =IF(SUMPRODUCT(--ISNUMBER(SEARCH({"956","428-6066","428.6066","4286066"},'Content Calendar'!J10)))=0,"Pass","Fail") -> Pass | D10: =IF(ISNUMBER(SEARCH("@",'Content Calendar'!J10)),"Fail","Pass") -> Pass | E10: =IF(OR(ISNUMBER(SEARCH("http",'Content Calendar'!J10)),ISNUMBER(SEARCH("www.",'Content Calendar'!J10)),ISNUMBER(SEARCH(".com",'Content Calendar'!J10))),"Fail","Pass") -> Pass | F10: =IF(LEN('Content Calendar'!L10)>0,"Pass","Fail") -> Pass | G10: =IF(AND(ISNUMBER(SEARCH("utm_source=google",'Content Calendar'!O10)),ISNUMBER(SEARCH("utm_content=",'Content Calendar'!O10))),"Pass","Fail") -> Pass | H10: =IF(ISNUMBER(SEARCH(Overview!$B$24,'Content Calendar'!M10)),"Pass","Fail") -> Pass | I10: =IF('Content Calendar'!F10="Offer",IF(AND(LEN('Content Calendar'!I10)>0,LEN('Content Calendar'!I10)<=58),"Pass","Fail"),"N/A") -> N/A | J10: =IF(OR('Content Calendar'!E10="Service",'Content Calendar'!E10="FAQ",'Content Calendar'!E10="Local",'Content Calendar'!E10="Promotional"),"Pass","Fail") -> Pass | K10: =IF(COUNTIF(B10:J10,"Fail")=0,"Pass","Fail") -> Pass
A11: ='Content Calendar'!A11 -> HG-07 | B11: =IF(LEN('Content Calendar'!J11)<=1500,"Pass","Fail") -> Pass | C11: =IF(SUMPRODUCT(--ISNUMBER(SEARCH({"956","428-6066","428.6066","4286066"},'Content Calendar'!J11)))=0,"Pass","Fail") -> Pass | D11: =IF(ISNUMBER(SEARCH("@",'Content Calendar'!J11)),"Fail","Pass") -> Pass | E11: =IF(OR(ISNUMBER(SEARCH("http",'Content Calendar'!J11)),ISNUMBER(SEARCH("www.",'Content Calendar'!J11)),ISNUMBER(SEARCH(".com",'Content Calendar'!J11))),"Fail","Pass") -> Pass | F11: =IF(LEN('Content Calendar'!L11)>0,"Pass","Fail") -> Pass | G11: =IF(AND(ISNUMBER(SEARCH("utm_source=google",'Content Calendar'!O11)),ISNUMBER(SEARCH("utm_content=",'Content Calendar'!O11))),"Pass","Fail") -> Pass | H11: =IF(ISNUMBER(SEARCH(Overview!$B$24,'Content Calendar'!M11)),"Pass","Fail") -> Pass | I11: =IF('Content Calendar'!F11="Offer",IF(AND(LEN('Content Calendar'!I11)>0,LEN('Content Calendar'!I11)<=58),"Pass","Fail"),"N/A") -> N/A | J11: =IF(OR('Content Calendar'!E11="Service",'Content Calendar'!E11="FAQ",'Content Calendar'!E11="Local",'Content Calendar'!E11="Promotional"),"Pass","Fail") -> Pass | K11: =IF(COUNTIF(B11:J11,"Fail")=0,"Pass","Fail") -> Pass
A12: ='Content Calendar'!A12 -> HG-08 | B12: =IF(LEN('Content Calendar'!J12)<=1500,"Pass","Fail") -> Pass | C12: =IF(SUMPRODUCT(--ISNUMBER(SEARCH({"956","428-6066","428.6066","4286066"},'Content Calendar'!J12)))=0,"Pass","Fail") -> Pass | D12: =IF(ISNUMBER(SEARCH("@",'Content Calendar'!J12)),"Fail","Pass") -> Pass | E12: =IF(OR(ISNUMBER(SEARCH("http",'Content Calendar'!J12)),ISNUMBER(SEARCH("www.",'Content Calendar'!J12)),ISNUMBER(SEARCH(".com",'Content Calendar'!J12))),"Fail","Pass") -> Pass | F12: =IF(LEN('Content Calendar'!L12)>0,"Pass","Fail") -> Pass | G12: =IF(AND(ISNUMBER(SEARCH("utm_source=google",'Content Calendar'!O12)),ISNUMBER(SEARCH("utm_content=",'Content Calendar'!O12))),"Pass","Fail") -> Pass | H12: =IF(ISNUMBER(SEARCH(Overview!$B$24,'Content Calendar'!M12)),"Pass","Fail") -> Pass | I12: =IF('Content Calendar'!F12="Offer",IF(AND(LEN('Content Calendar'!I12)>0,LEN('Content Calendar'!I12)<=58),"Pass","Fail"),"N/A") -> N/A | J12: =IF(OR('Content Calendar'!E12="Service",'Content Calendar'!E12="FAQ",'Content Calendar'!E12="Local",'Content Calendar'!E12="Promotional"),"Pass","Fail") -> Pass | K12: =IF(COUNTIF(B12:J12,"Fail")=0,"Pass","Fail") -> Pass
A13: ='Content Calendar'!A13 -> HG-09 | B13: =IF(LEN('Content Calendar'!J13)<=1500,"Pass","Fail") -> Pass | C13: =IF(SUMPRODUCT(--ISNUMBER(SEARCH({"956","428-6066","428.6066","4286066"},'Content Calendar'!J13)))=0,"Pass","Fail") -> Pass | D13: =IF(ISNUMBER(SEARCH("@",'Content Calendar'!J13)),"Fail","Pass") -> Pass | E13: =IF(OR(ISNUMBER(SEARCH("http",'Content Calendar'!J13)),ISNUMBER(SEARCH("www.",'Content Calendar'!J13)),ISNUMBER(SEARCH(".com",'Content Calendar'!J13))),"Fail","Pass") -> Pass | F13: =IF(LEN('Content Calendar'!L13)>0,"Pass","Fail") -> Pass | G13: =IF(AND(ISNUMBER(SEARCH("utm_source=google",'Content Calendar'!O13)),ISNUMBER(SEARCH("utm_content=",'Content Calendar'!O13))),"Pass","Fail") -> Pass | H13: =IF(ISNUMBER(SEARCH(Overview!$B$24,'Content Calendar'!M13)),"Pass","Fail") -> Pass | I13: =IF('Content Calendar'!F13="Offer",IF(AND(LEN('Content Calendar'!I13)>0,LEN('Content Calendar'!I13)<=58),"Pass","Fail"),"N/A") -> N/A | J13: =IF(OR('Content Calendar'!E13="Service",'Content Calendar'!E13="FAQ",'Content Calendar'!E13="Local",'Content Calendar'!E13="Promotional"),"Pass","Fail") -> Pass | K13: =IF(COUNTIF(B13:J13,"Fail")=0,"Pass","Fail") -> Pass
A14: ='Content Calendar'!A14 -> HG-10 | B14: =IF(LEN('Content Calendar'!J14)<=1500,"Pass","Fail") -> Pass | C14: =IF(SUMPRODUCT(--ISNUMBER(SEARCH({"956","428-6066","428.6066","4286066"},'Content Calendar'!J14)))=0,"Pass","Fail") -> Pass | D14: =IF(ISNUMBER(SEARCH("@",'Content Calendar'!J14)),"Fail","Pass") -> Pass | E14: =IF(OR(ISNUMBER(SEARCH("http",'Content Calendar'!J14)),ISNUMBER(SEARCH("www.",'Content Calendar'!J14)),ISNUMBER(SEARCH(".com",'Content Calendar'!J14))),"Fail","Pass") -> Pass | F14: =IF(LEN('Content Calendar'!L14)>0,"Pass","Fail") -> Pass | G14: =IF(AND(ISNUMBER(SEARCH("utm_source=google",'Content Calendar'!O14)),ISNUMBER(SEARCH("utm_content=",'Content Calendar'!O14))),"Pass","Fail") -> Pass | H14: =IF(ISNUMBER(SEARCH(Overview!$B$24,'Content Calendar'!M14)),"Pass","Fail") -> Pass | I14: =IF('Content Calendar'!F14="Offer",IF(AND(LEN('Content Calendar'!I14)>0,LEN('Content Calendar'!I14)<=58),"Pass","Fail"),"N/A") -> N/A | J14: =IF(OR('Content Calendar'!E14="Service",'Content Calendar'!E14="FAQ",'Content Calendar'!E14="Local",'Content Calendar'!E14="Promotional"),"Pass","Fail") -> Pass | K14: =IF(COUNTIF(B14:J14,"Fail")=0,"Pass","Fail") -> Pass
A15: ='Content Calendar'!A15 -> HG-11 | B15: =IF(LEN('Content Calendar'!J15)<=1500,"Pass","Fail") -> Pass | C15: =IF(SUMPRODUCT(--ISNUMBER(SEARCH({"956","428-6066","428.6066","4286066"},'Content Calendar'!J15)))=0,"Pass","Fail") -> Pass | D15: =IF(ISNUMBER(SEARCH("@",'Content Calendar'!J15)),"Fail","Pass") -> Pass | E15: =IF(OR(ISNUMBER(SEARCH("http",'Content Calendar'!J15)),ISNUMBER(SEARCH("www.",'Content Calendar'!J15)),ISNUMBER(SEARCH(".com",'Content Calendar'!J15))),"Fail","Pass") -> Pass | F15: =IF(LEN('Content Calendar'!L15)>0,"Pass","Fail") -> Pass | G15: =IF(AND(ISNUMBER(SEARCH("utm_source=google",'Content Calendar'!O15)),ISNUMBER(SEARCH("utm_content=",'Content Calendar'!O15))),"Pass","Fail") -> Pass | H15: =IF(ISNUMBER(SEARCH(Overview!$B$24,'Content Calendar'!M15)),"Pass","Fail") -> Pass | I15: =IF('Content Calendar'!F15="Offer",IF(AND(LEN('Content Calendar'!I15)>0,LEN('Content Calendar'!I15)<=58),"Pass","Fail"),"N/A") -> N/A | J15: =IF(OR('Content Calendar'!E15="Service",'Content Calendar'!E15="FAQ",'Content Calendar'!E15="Local",'Content Calendar'!E15="Promotional"),"Pass","Fail") -> Pass | K15: =IF(COUNTIF(B15:J15,"Fail")=0,"Pass","Fail") -> Pass
A16: ='Content Calendar'!A16 -> HG-12 | B16: =IF(LEN('Content Calendar'!J16)<=1500,"Pass","Fail") -> Pass | C16: =IF(SUMPRODUCT(--ISNUMBER(SEARCH({"956","428-6066","428.6066","4286066"},'Content Calendar'!J16)))=0,"Pass","Fail") -> Pass | D16: =IF(ISNUMBER(SEARCH("@",'Content Calendar'!J16)),"Fail","Pass") -> Pass | E16: =IF(OR(ISNUMBER(SEARCH("http",'Content Calendar'!J16)),ISNUMBER(SEARCH("www.",'Content Calendar'!J16)),ISNUMBER(SEARCH(".com",'Content Calendar'!J16))),"Fail","Pass") -> Pass | F16: =IF(LEN('Content Calendar'!L16)>0,"Pass","Fail") -> Pass | G16: =IF(AND(ISNUMBER(SEARCH("utm_source=google",'Content Calendar'!O16)),ISNUMBER(SEARCH("utm_content=",'Content Calendar'!O16))),"Pass","Fail") -> Pass | H16: =IF(ISNUMBER(SEARCH(Overview!$B$24,'Content Calendar'!M16)),"Pass","Fail") -> Pass | I16: =IF('Content Calendar'!F16="Offer",IF(AND(LEN('Content Calendar'!I16)>0,LEN('Content Calendar'!I16)<=58),"Pass","Fail"),"N/A") -> Pass | J16: =IF(OR('Content Calendar'!E16="Service",'Content Calendar'!E16="FAQ",'Content Calendar'!E16="Local",'Content Calendar'!E16="Promotional"),"Pass","Fail") -> Pass | K16: =IF(COUNTIF(B16:J16,"Fail")=0,"Pass","Fail") -> Pass
... A26: ='Content Calendar'!A26 -> HG-22 | B26: =IF(LEN('Content Calendar'!J26)<=1500,"Pass","Fail") -> Pass | C26: =IF(SUMPRODUCT(--ISNUMBER(SEARCH({"956","428-6066","428.6066","4286066"},'Content Calendar'!J26)))=0,"Pass","Fail") -> Pass | D26: =IF(ISNUMBER(SEARCH("@",'Content Calendar'!J26)),"Fail","Pass") -> Pass | E26: =IF(OR(ISNUMBER(SEARCH("http",'Content Calendar'!J26)),ISNUMBER(SEARCH("www.",'Content Calendar'!J26)),ISNUMBER(SEARCH(".com",'Content Calendar'!J26))),"Fail","Pass") -> Pass | F26: =IF(LEN('Content Calendar'!L26)>0,"Pass","Fail") -> Pass | G26: =IF(AND(ISNUMBER(SEARCH("utm_source=google",'Content Calendar'!O26)),ISNUMBER(SEARCH("utm_content=",'Content Calendar'!O26))),"Pass","Fail") -> Pass | H26: =IF(ISNUMBER(SEARCH(Overview!$B$24,'Content Calendar'!M26)),"Pass","Fail") -> Pass | I26: =IF('Content Calendar'!F26="Offer",IF(AND(LEN('Content Calendar'!I26)>0,LEN('Content Calendar'!I26)<=58),"Pass","Fail"),"N/A") -> N/A | J26: =IF(OR('Content Calendar'!E26="Service",'Content Calendar'!E26="FAQ",'Content Calendar'!E26="Local",'Content Calendar'!E26="Promotional"),"Pass","Fail") -> Pass | K26: =IF(COUNTIF(B26:J26,"Fail")=0,"Pass","Fail") -> Pass
A28: Posts passing | B28: =COUNTIF(K5:K26,"Pass")&" of "&COUNTA(A5:A26) -> 22 of 22
A29: Note | B29: The phone check looks for the business phone digits and area code. The link check flags any URL written into the post text: links belong only in the CTA button.
